Workbook

Sheet A.Y
A1: ANYELUZ | C1: ENERO | H1: FEBRERO | M1: MARZO | R1: ABRIL | W1: MAYO | AB1: JUNIO | AG1: JULIO | AL1: AGOSTO | AQ1: SEPTIEMBRE | AV1: OCTUBRE | BA1: NOVIEMBRE | BF1: DICIEMBRE | BK1: ENERO
A2: PRODUCTO | B2: VR. COMPRA | C2: INV.I | D2: Entra | E2: Saldo | F2: SALIDA | G2: TOTAL | H2: INV.I | I2: Entra | J2: Saldo | K2: SALIDA | L2: TOTAL | M2: INV.I | N2: Entra | O2: Saldo | P2: SALIDA | Q2: TOTAL | R2: INV.I | S2: Entra | T2: Saldo | U2: SALIDA | V2: TOTAL | W2: INV.I | X2: Entra | Y2: Saldo | Z2: SALIDA | AA2: TOTAL | AB2: INV.I | AC2: Entra | AD2: Saldo | AE2: SALIDA | AF2: TOTAL | AG2: INV.I | AH2: Entra | AI2: Saldo | AJ2: SALIDA | AK2: TOTAL | AL2: INV.I | AM2: Entra | AN2: Saldo | AO2: SALIDA | AP2: TOTAL | AQ2: INV.I | AR2: Entra | AS2: Saldo | AT2: SALIDA | AU2: TOTAL | AV2: INV.I | AW2: Entra | AX2: Saldo | AY2: SALIDA | AZ2: TOTAL | BA2: INV.I | BB2: Entra | BC2: Saldo | BD2: SALIDA | BE2: TOTAL | BF2: INV.I | BG2: Entra | BH2: Saldo | BI2: SALIDA | BJ2: TOTAL | BK2: INV.I
A3: SH. CEBOLLA | B3: 31500 | F3: =+E3-H3 -> 0 | G3: =((E3-F3)*$B3) -> 0 | K3: =+J3-M3 -> 0 | L3: =((J3-K3)*$B3) -> 0 | P3: =+O3-R3 -> 0 | Q3: =((O3-P3)*$B3) -> 0 | U3: =+T3-W3 -> 0 | V3: =((T3-U3)*$B3) -> 0 | Y3: =+W3+X3 -> 0 | Z3: =+Y3-AB3 -> 0 | AA3: =((Y3-Z3)*$B3) -> 0 | AD3: =+AB3+AC3 -> 0 | AE3: =+AD3-AG3 -> -13 | AF3: =((AD3-AE3)*$B3) -> 409500 | AG3: 13 | AI3: =+AG3+AH3 -> 13 | AJ3: =+AI3-AL3 -> 1 | AK3: =((AI3-AJ3)*$B3) -> 378000 | AL3: 12 | AN3: =+AL3+AM3 -> 12 | AO3: =+AN3-AQ3 -> 3 | AP3: =((AN3-AO3)*$B3) -> 283500 | AQ3: 9 | AS3: =AQ3+AR3 -> 9 | AT3: =+AS3-AV3 -> 9 | AU3: =((AS3-AT3)*$B3) -> 0 | AX3: =+AV3+AW3 -> 0 | AY3: =+AX3-BA3 -> 0 | AZ3: =((AX3-AY3)*$B3) -> 0 | BC3: =+BA3+BB3 -> 0 | BD3: =+BC3-BF3 -> 0 | BE3: =((BC3-BD3)*$B3) -> 0 | BH3: =+BF3+BG3 -> 0 | BI3: =+BH3-BK3 -> 0 | BJ3: =((BH3-BI3)*$B3) -> 0
A4: AC. CEBOLLA | B4: 28000 | F4: =+E4-H4 -> 0 | G4: =((E4-F4)*$B4) -> 0 | K4: =+J4-M4 -> 0 | L4: =((J4-K4)*$B4) -> 0 | P4: =+O4-R4 -> 0 | Q4: =((O4-P4)*$B4) -> 0 | U4: =+T4-W4 -> 0 | V4: =((T4-U4)*$B4) -> 0 | Y4: =+W4+X4 -> 0 | Z4: =+Y4-AB4 -> 0 | AA4: =((Y4-Z4)*$B4) -> 0 | AD4: =+AB4+AC4 -> 0 | AE4: =+AD4-AG4 -> -9 | AF4: =((AD4-AE4)*$B4) -> 252000 | AG4: 9 | AI4: =+AG4+AH4 -> 9 | AJ4: =+AI4-AL4 -> 1 | AK4: =((AI4-AJ4)*$B4) -> 224000 | AL4: 8 | AN4: =+AL4+AM4 -> 8 | AO4: =+AN4-AQ4 -> 2 | AP4: =((AN4-AO4)*$B4) -> 168000 | AQ4: 6 | AS4: =AQ4+AR4 -> 6 | AT4: =+AS4-AV4 -> 6 | AU4: =((AS4-AT4)*$B4) -> 0 | AX4: =+AV4+AW4 -> 0 | AY4: =+AX4-BA4 -> 0 | AZ4: =((AX4-AY4)*$B4) -> 0 | BC4: =+BA4+BB4 -> 0 | BD4: =+BC4-BF4 -> 0 | BE4: =((BC4-BD4)*$B4) -> 0 | BH4: =+BF4+BG4 -> 0 | BI4: =+BH4-BK4 -> 0 | BJ4: =((BH4-BI4)*$B4) -> 0
A5: SH. ROMERO | B5: 31500 | F5: =+E5-H5 -> 0 | G5: =((E5-F5)*$B5) -> 0 | K5: =+J5-M5 -> 0 | L5: =((J5-K5)*$B5) -> 0 | P5: =+O5-R5 -> 0 | Q5: =((O5-P5)*$B5) -> 0 | U5: =+T5-W5 -> 0 | V5: =((T5-U5)*$B5) -> 0 | Y5: =+W5+X5 -> 0 | Z5: =+Y5-AB5 -> 0 | AA5: =((Y5-Z5)*$B5) -> 0 | AD5: =+AB5+AC5 -> 0 | AE5: =+AD5-AG5 -> -6 | AF5: =((AD5-AE5)*$B5) -> 189000 | AG5: 6 | AI5: =+AG5+AH5 -> 6 | AJ5: =+AI5-AL5 -> 1 | AK5: =((AI5-AJ5)*$B5) -> 157500 | AL5: 5 | AN5: =+AL5+AM5 -> 5 | AO5: =+AN5-AQ5 -> 2 | AP5: =((AN5-AO5)*$B5) -> 94500 | AQ5: 3 | AS5: =AQ5+AR5 -> 3 | AT5: =+AS5-AV5 -> 3 | AU5: =((AS5-AT5)*$B5) -> 0 | AX5: =+AV5+AW5 -> 0 | AY5: =+AX5-BA5 -> 0 | AZ5: =((AX5-AY5)*$B5) -> 0 | BC5: =+BA5+BB5 -> 0 | BD5: =+BC5-BF5 -> 0 | BE5: =((BC5-BD5)*$B5) -> 0 | BH5: =+BF5+BG5 -> 0 | BI5: =+BH5-BK5 -> 0 | BJ5: =((BH5-BI5)*$B5) -> 0
A6: AC. ROMERO | B6: 28000 | F6: =+E6-H6 -> 0 | G6: =((E6-F6)*$B6) -> 0 | K6: =+J6-M6 -> 0 | L6: =((J6-K6)*$B6) -> 0 | P6: =+O6-R6 -> 0 | Q6: =((O6-P6)*$B6) -> 0 | U6: =+T6-W6 -> 0 | V6: =((T6-U6)*$B6) -> 0 | Y6: =+W6+X6 -> 0 | Z6: =+Y6-AB6 -> 0 | AA6: =((Y6-Z6)*$B6) -> 0 | AD6: =+AB6+AC6 -> 0 | AE6: =+AD6-AG6 -> -10 | AF6: =((AD6-AE6)*$B6) -> 280000 | AG6: 10 | AI6: =+AG6+AH6 -> 10 | AJ6: =+AI6-AL6 -> 1 | AK6: =((AI6-AJ6)*$B6) -> 252000 | AL6: 9 | AN6: =+AL6+AM6 -> 9 | AO6: =+AN6-AQ6 -> 3 | AP6: =((AN6-AO6)*$B6) -> 168000 | AQ6: 6 | AS6: =AQ6+AR6 -> 6 | AT6: =+AS6-AV6 -> 6 | AU6: =((AS6-AT6)*$B6) -> 0 | AX6: =+AV6+AW6 -> 0 | AY6: =+AX6-BA6 -> 0 | AZ6: =((AX6-AY6)*$B6) -> 0 | BC6: =+BA6+BB6 -> 0 | BD6: =+BC6-BF6 -> 0 | BE6: =((BC6-BD6)*$B6) -> 0 | BH6: =+BF6+BG6 -> 0 | BI6: =+BH6-BK6 -> 0 | BJ6: =((BH6-BI6)*$B6) -> 0
A7: SH. ANTI CASPA | B7: 28000 | F7: =+E7-H7 -> 0 | G7: =((E7-F7)*$B7) -> 0 | K7: =+J7-M7 -> 0 | L7: =((J7-K7)*$B7) -> 0 | P7: =+O7-R7 -> 0 | Q7: =((O7-P7)*$B7) -> 0 | U7: =+T7-W7 -> 0 | V7: =((T7-U7)*$B7) -> 0 | Y7: =+W7+X7 -> 0 | Z7: =+Y7-AB7 -> 0 | AA7: =((Y7-Z7)*$B7) -> 0 | AD7: =+AB7+AC7 -> 0 | AE7: =+AD7-AG7 -> -4 | AF7: =((AD7-AE7)*$B7) -> 112000 | AG7: 4 | AI7: =+AG7+AH7 -> 4 | AJ7: =+AI7-AL7 -> 0 | AK7: =((AI7-AJ7)*$B7) -> 112000 | AL7: 4 | AN7: =+AL7+AM7 -> 4 | AO7: =+AN7-AQ7 -> 1 | AP7: =((AN7-AO7)*$B7) -> 84000 | AQ7: 3 | AS7: =AQ7+AR7 -> 3 | AT7: =+AS7-AV7 -> 3 | AU7: =((AS7-AT7)*$B7) -> 0 | AX7: =+AV7+AW7 -> 0 | AY7: =+AX7-BA7 -> 0 | AZ7: =((AX7-AY7)*$B7) -> 0 | BC7: =+BA7+BB7 -> 0 | BD7: =+BC7-BF7 -> 0 | BE7: =((BC7-BD7)*$B7) -> 0 | BH7: =+BF7+BG7 -> 0 | BI7: =+BH7-BK7 -> 0 | BJ7: =((BH7-BI7)*$B7) -> 0
A8: SH. GUSANO DE SEDA | B8: 28000 | F8: =+E8-H8 -> 0 | G8: =((E8-F8)*$B8) -> 0 | K8: =+J8-M8 -> 0 | L8: =((J8-K8)*$B8) -> 0 | P8: =+O8-R8 -> 0 | Q8: =((O8-P8)*$B8) -> 0 | U8: =+T8-W8 -> 0 | V8: =((T8-U8)*$B8) -> 0 | Y8: =+W8+X8 -> 0 | Z8: =+Y8-AB8 -> 0 | AA8: =((Y8-Z8)*$B8) -> 0 | AD8: =+AB8+AC8 -> 0 | AE8: =+AD8-AG8 -> -12 | AF8: =((AD8-AE8)*$B8) -> 336000 | AG8: 12 | AI8: =+AG8+AH8 -> 12 | AJ8: =+AI8-AL8 -> 0 | AK8: =((AI8-AJ8)*$B8) -> 336000 | AL8: 12 | AN8: =+AL8+AM8 -> 12 | AO8: =+AN8-AQ8 -> 0 | AP8: =((AN8-AO8)*$B8) -> 336000 | AQ8: 12 | AS8: =AQ8+AR8 -> 12 | AT8: =+AS8-AV8 -> 12 | AU8: =((AS8-AT8)*$B8) -> 0 | AX8: =+AV8+AW8 -> 0 | AY8: =+AX8-BA8 -> 0 | AZ8: =((AX8-AY8)*$B8) -> 0 | BC8: =+BA8+BB8 -> 0 | BD8: =+BC8-BF8 -> 0 | BE8: =((BC8-BD8)*$B8) -> 0 | BH8: =+BF8+BG8 -> 0 | BI8: =+BH8-BK8 -> 0 | BJ8: =((BH8-BI8)*$B8) -> 0
A9: SH. ALOE VERA | B9: 28000 | F9: =+E9-H9 -> 0 | G9: =((E9-F9)*$B9) -> 0 | K9: =+J9-M9 -> 0 | L9: =((J9-K9)*$B9) -> 0 | P9: =+O9-R9 -> 0 | Q9: =((O9-P9)*$B9) -> 0 | U9: =+T9-W9 -> 0 | V9: =((T9-U9)*$B9) -> 0 | Y9: =+W9+X9 -> 0 | Z9: =+Y9-AB9 -> 0 | AA9: =((Y9-Z9)*$B9) -> 0 | AD9: =+AB9+AC9 -> 0 | AE9: =+AD9-AG9 -> -10 | AF9: =((AD9-AE9)*$B9) -> 280000 | AG9: 10 | AI9: =+AG9+AH9 -> 10 | AJ9: =+AI9-AL9 -> 0 | AK9: =((AI9-AJ9)*$B9) -> 280000 | AL9: 10 | AN9: =+AL9+AM9 -> 10 | AO9: =+AN9-AQ9 -> 0 | AP9: =((AN9-AO9)*$B9) -> 280000 | AQ9: 10 | AS9: =AQ9+AR9 -> 10 | AT9: =+AS9-AV9 -> 10 | AU9: =((AS9-AT9)*$B9) -> 0 | AX9: =+AV9+AW9 -> 0 | AY9: =+AX9-BA9 -> 0 | AZ9: =((AX9-AY9)*$B9) -> 0 | BC9: =+BA9+BB9 -> 0 | BD9: =+BC9-BF9 -> 0 | BE9: =((BC9-BD9)*$B9) -> 0 | BH9: =+BF9+BG9 -> 0 | BI9: =+BH9-BK9 -> 0 | BJ9: =((BH9-BI9)*$B9) -> 0
A10: COCTEL FRUTAS | B10: 35000 | F10: =+E10-H10 -> 0 | G10: =((E10-F10)*$B10) -> 0 | K10: =+J10-M10 -> 0 | L10: =((J10-K10)*$B10) -> 0 | P10: =+O10-R10 -> 0 | Q10: =((O10-P10)*$B10) -> 0 | U10: =+T10-W10 -> 0 | V10: =((T10-U10)*$B10) -> 0 | Y10: =+W10+X10 -> 0 | Z10: =+Y10-AB10 -> 0 | AA10: =((Y10-Z10)*$B10) -> 0 | AD10: =+AB10+AC10 -> 0 | AE10: =+AD10-AG10 -> -6 | AF10: =((AD10-AE10)*$B10) -> 210000 | AG10: 6 | AI10: =+AG10+AH10 -> 6 | AJ10: =+AI10-AL10 -> 1 | AK10: =((AI10-AJ10)*$B10) -> 175000 | AL10: 5 | AN10: =+AL10+AM10 -> 5 | AO10: =+AN10-AQ10 -> -1 | AP10: =((AN10-AO10)*$B10) -> 210000 | AQ10: 6 | AS10: =AQ10+AR10 -> 6 | AT10: =+AS10-AV10 -> 6 | AU10: =((AS10-AT10)*$B10) -> 0 | AX10: =+AV10+AW10 -> 0 | AY10: =+AX10-BA10 -> 0 | AZ10: =((AX10-AY10)*$B10) -> 0 | BC10: =+BA10+BB10 -> 0 | BD10: =+BC10-BF10 -> 0 | BE10: =((BC10-BD10)*$B10) -> 0 | BH10: =+BF10+BG10 -> 0 | BI10: =+BH10-BK10 -> 0 | BJ10: =((BH10-BI10)*$B10) -> 0
A11: AC. ARGÁN | B11: 28000 | F11: =+E11-H11 -> 0 | G11: =((E11-F11)*$B11) -> 0 | K11: =+J11-M11 -> 0 | L11: =((J11-K11)*$B11) -> 0 | P11: =+O11-R11 -> 0 | Q11: =((O11-P11)*$B11) -> 0 | U11: =+T11-W11 -> 0 | V11: =((T11-U11)*$B11) -> 0 | Y11: =+W11+X11 -> 0 | Z11: =+Y11-AB11 -> 0 | AA11: =((Y11-Z11)*$B11) -> 0 | AD11: =+AB11+AC11 -> 0 | AE11: =+AD11-AG11 -> -6 | AF11: =((AD11-AE11)*$B11) -> 168000 | AG11: 6 | AI11: =+AG11+AH11 -> 6 | AJ11: =+AI11-AL11 -> 0 | AK11: =((AI11-AJ11)*$B11) -> 168000 | AL11: 6 | AN11: =+AL11+AM11 -> 6 | AO11: =+AN11-AQ11 -> 3 | AP11: =((AN11-AO11)*$B11) -> 84000 | AQ11: 3 | AS11: =AQ11+AR11 -> 3 | AT11: =+AS11-AV11 -> 3 | AU11: =((AS11-AT11)*$B11) -> 0 | AX11: =+AV11+AW11 -> 0 | AY11: =+AX11-BA11 -> 0 | AZ11: =((AX11-AY11)*$B11) -> 0 | BC11: =+BA11+BB11 -> 0 | BD11: =+BC11-BF11 -> 0 | BE11: =((BC11-BD11)*$B11) -> 0 | BH11: =+BF11+BG11 -> 0 | BI11: =+BH11-BK11 -> 0 | BJ11: =((BH11-BI11)*$B11) -> 0
A12: SH. AGUACATE | B12: 28000 | F12: =+E12-H12 -> 0 | G12: =((E12-F12)*$B12) -> 0 | K12: =+J12-M12 -> 0 | L12: =((J12-K12)*$B12) -> 0 | P12: =+O12-R12 -> 0 | Q12: =((O12-P12)*$B12) -> 0 | U12: =+T12-W12 -> 0 | V12: =((T12-U12)*$B12) -> 0 | Y12: =+W12+X12 -> 0 | Z12: =+Y12-AB12 -> 0 | AA12: =((Y12-Z12)*$B12) -> 0 | AD12: =+AB12+AC12 -> 0 | AE12: =+AD12-AG12 -> -3 | AF12: =((AD12-AE12)*$B12) -> 84000 | AG12: 3 | AI12: =+AG12+AH12 -> 3 | AJ12: =+AI12-AL12 -> 0 | AK12: =((AI12-AJ12)*$B12) -> 84000 | AL12: 3 | AN12: =+AL12+AM12 -> 3 | AO12: =+AN12-AQ12 -> 1 | AP12: =((AN12-AO12)*$B12) -> 56000 | AQ12: 2 | AS12: =AQ12+AR12 -> 2 | AT12: =+AS12-AV12 -> 2 | AU12: =((AS12-AT12)*$B12) -> 0 | AX12: =+AV12+AW12 -> 0 | AY12: =+AX12-BA12 -> 0 | AZ12: =((AX12-AY12)*$B12) -> 0 | BC12: =+BA12+BB12 -> 0 | BD12: =+BC12-BF12 -> 0 | BE12: =((BC12-BD12)*$B12) -> 0 | BH12: =+BF12+BG12 -> 0 | BI12: =+BH12-BK12 -> 0 | BJ12: =((BH12-BI12)*$B12) -> 0
A13: SH. BANANO | B13: 28000 | F13: =+E13-H13 -> 0 | G13: =((E13-F13)*$B13) -> 0 | K13: =+J13-M13 -> 0 | L13: =((J13-K13)*$B13) -> 0 | P13: =+O13-R13 -> 0 | Q13: =((O13-P13)*$B13) -> 0 | U13: =+T13-W13 -> 0 | V13: =((T13-U13)*$B13) -> 0 | Y13: =+W13+X13 -> 0 | Z13: =+Y13-AB13 -> 0 | AA13: =((Y13-Z13)*$B13) -> 0 | AD13: =+AB13+AC13 -> 0 | AE13: =+AD13-AG13 -> -3 | AF13: =((AD13-AE13)*$B13) -> 84000 | AG13: 3 | AI13: =+AG13+AH13 -> 3 | AJ13: =+AI13-AL13 -> 1 | AK13: =((AI13-AJ13)*$B13) -> 56000 | AL13: 2 | AM13: 4 | AN13: =+AL13+AM13 -> 6 | AO13: =+AN13-AQ13 -> 0 | AP13: =((AN13-AO13)*$B13) -> 168000 | AQ13: 6 | AS13: =AQ13+AR13 -> 6 | AT13: =+AS13-AV13 -> 6 | AU13: =((AS13-AT13)*$B13) -> 0 | AX13: =+AV13+AW13 -> 0 | AY13: =+AX13-BA13 -> 0 | AZ13: =((AX13-AY13)*$B13) -> 0 | BC13: =+BA13+BB13 -> 0 | BD13: =+BC13-BF13 -> 0 | BE13: =((BC13-BD13)*$B13) -> 0 | BH13: =+BF13+BG13 -> 0 | BI13: =+BH13-BK13 -> 0 | BJ13: =((BH13-BI13)*$B13) -> 0
A14: AC. BANANO | B14: 28000 | F14: =+E14-H14 -> 0 | G14: =((E14-F14)*$B14) -> 0 | K14: =+J14-M14 -> 0 | L14: =((J14-K14)*$B14) -> 0 | P14: =+O14-R14 -> 0 | Q14: =((O14-P14)*$B14) -> 0 | U14: =+T14-W14 -> 0 | V14: =((T14-U14)*$B14) -> 0 | Y14: =+W14+X14 -> 0 | Z14: =+Y14-AB14 -> 0 | AA14: =((Y14-Z14)*$B14) -> 0 | AD14: =+AB14+AC14 -> 0 | AE14: =+AD14-AG14 -> -2 | AF14: =((AD14-AE14)*$B14) -> 56000 | AG14: 2 | AI14: =+AG14+AH14 -> 2 | AJ14: =+AI14-AL14 -> 0 | AK14: =((AI14-AJ14)*$B14) -> 56000 | AL14: 2 | AN14: =+AL14+AM14 -> 2 | AO14: =+AN14-AQ14 -> 1 | AP14: =((AN14-AO14)*$B14) -> 28000 | AQ14: 1 | AS14: =AQ14+AR14 -> 1 | AT14: =+AS14-AV14 -> 1 | AU14: =((AS14-AT14)*$B14) -> 0 | AX14: =+AV14+AW14 -> 0 | AY14: =+AX14-BA14 -> 0 | AZ14: =((AX14-AY14)*$B14) -> 0 | BC14: =+BA14+BB14 -> 0 | BD14: =+BC14-BF14 -> 0 | BE14: =((BC14-BD14)*$B14) -> 0 | BH14: =+BF14+BG14 -> 0 | BI14: =+BH14-BK14 -> 0 | BJ14: =((BH14-BI14)*$B14) -> 0
A15: MASCARILLA NUTRITIVA DE BANANO | B15: 30100 | F15: =+E15-H15 -> 0 | G15: =((E15-F15)*$B15) -> 0 | K15: =+J15-M15 -> 0 | L15: =((J15-K15)*$B15) -> 0 | P15: =+O15-R15 -> 0 | Q15: =((O15-P15)*$B15) -> 0 | U15: =+T15-W15 -> 0 | V15: =((T15-U15)*$B15) -> 0 | Y15: =+W15+X15 -> 0 | Z15: =+Y15-AB15 -> 0 | AA15: =((Y15-Z15)*$B15) -> 0 | AD15: =+AB15+AC15 -> 0 | AE15: =+AD15-AG15 -> -3 | AF15: =((AD15-AE15)*$B15) -> 90300 | AG15: 3 | AI15: =+AG15+AH15 -> 3 | AJ15: =+AI15-AL15 -> 0 | AK15: =((AI15-AJ15)*$B15) -> 90300 | AL15: 3 | AN15: =+AL15+AM15 -> 3 | AO15: =+AN15-AQ15 -> 1 | AP15: =((AN15-AO15)*$B15) -> 60200 | AQ15: 2 | AS15: =AQ15+AR15 -> 2 | AT15: =+AS15-AV15 -> 2 | AU15: =((AS15-AT15)*$B15) -> 0 | AX15: =+AV15+AW15 -> 0 | AY15: =+AX15-BA15 -> 0 | AZ15: =((AX15-AY15)*$B15) -> 0 | BC15: =+BA15+BB15 -> 0 | BD15: =+BC15-BF15 -> 0 | BE15: =((BC15-BD15)*$B15) -> 0 | BH15: =+BF15+BG15 -> 0 | BI15: =+BH15-BK15 -> 0 | BJ15: =((BH15-BI15)*$B15) -> 0
A16: TERAPIA CAPILAR DE CEBOLLA | B16: 32200 | F16: =+E16-H16 -> 0 | G16: =((E16-F16)*$B16) -> 0 | K16: =+J16-M16 -> 0 | L16: =((J16-K16)*$B16) -> 0 | P16: =+O16-R16 -> 0 | Q16: =((O16-P16)*$B16) -> 0 | U16: =+T16-W16 -> 0 | V16: =((T16-U16)*$B16) -> 0 | Y16: =+W16+X16 -> 0 | Z16: =+Y16-AB16 -> 0 | AA16: =((Y16-Z16)*$B16) -> 0 | AD16: =+AB16+AC16 -> 0 | AE16: =+AD16-AG16 -> -12 | AF16: =((AD16-AE16)*$B16) -> 386400 | AG16: 12 | AI16: =+AG16+AH16 -> 12 | AJ16: =+AI16-AL16 -> 0 | AK16: =((AI16-AJ16)*$B16) -> 386400 | AL16: 12 | AN16: =+AL16+AM16 -> 12 | AO16: =+AN16-AQ16 -> 0 | AP16: =((AN16-AO16)*$B16) -> 386400 | AQ16: 12 | AS16: =AQ16+AR16 -> 12 | AT16: =+AS16-AV16 -> 12 | AU16: =((AS16-AT16)*$B16) -> 0 | AX16: =+AV16+AW16 -> 0 | AY16: =+AX16-BA16 -> 0 | AZ16: =((AX16-AY16)*$B16) -> 0 | BC16: =+BA16+BB16 -> 0 | BD16: =+BC16-BF16 -> 0 | BE16: =((BC16-BD16)*$B16) -> 0 | BH16: =+BF16+BG16 -> 0 | BI16: =+BH16-BK16 -> 0 | BJ16: =((BH16-BI16)*$B16) -> 0
A17: TRATAMIENTO NUTRITIVO | B17: 31500 | F17: =+E17-H17 -> 0 | G17: =((E17-F17)*$B17) -> 0 | K17: =+J17-M17 -> 0 | L17: =((J17-K17)*$B17) -> 0 | P17: =+O17-R17 -> 0 | Q17: =((O17-P17)*$B17) -> 0 | U17: =+T17-W17 -> 0 | V17: =((T17-U17)*$B17) -> 0 | Y17: =+W17+X17 -> 0 | Z17: =+Y17-AB17 -> 0 | AA17: =((Y17-Z17)*$B17) -> 0 | AD17: =+AB17+AC17 -> 0 | AE17: =+AD17-AG17 -> 0 | AF17: =((AD17-AE17)*$B17) -> 0 | AG17: 0 | AI17: =+AG17+AH17 -> 0 | AJ17: =+AI17-AL17 -> 0 | AK17: =((AI17-AJ17)*$B17) -> 0 | AL17: 0 | AM17: 6 | AN17: =+AL17+AM17 -> 6 | AO17: =+AN17-AQ17 -> 0 | AP17: =((AN17-AO17)*$B17) -> 189000 | AQ17: 6 | AS17: =AQ17+AR17 -> 6 | AT17: =+AS17-AV17 -> 6 | AU17: =((AS17-AT17)*$B17) -> 0 | AX17: =+AV17+AW17 -> 0 | AY17: =+AX17-BA17 -> 0 | AZ17: =((AX17-AY17)*$B17) -> 0 | BC17: =+BA17+BB17 -> 0 | BD17: =+BC17-BF17 -> 0 | BE17: =((BC17-BD17)*$B17) -> 0 | BH17: =+BF17+BG17 -> 0 | BI17: =+BH17-BK17 -> 0 | BJ17: =((BH17-BI17)*$B17) -> 0
A18: BIOTERAPIA CAPILAR | B18: 30100 | F18: =+E18-H18 -> 0 | G18: =((E18-F18)*$B18) -> 0 | K18: =+J18-M18 -> 0 | L18: =((J18-K18)*$B18) -> 0 | P18: =+O18-R18 -> 0 | Q18: =((O18-P18)*$B18) -> 0 | U18: =+T18-W18 -> 0 | V18: =((T18-U18)*$B18) -> 0 | Y18: =+W18+X18 -> 0 | Z18: =+Y18-AB18 -> 0 | AA18: =((Y18-Z18)*$B18) -> 0 | AD18: =+AB18+AC18 -> 0 | AE18: =+AD18-AG18 -> -4 | AF18: =((AD18-AE18)*$B18) -> 120400 | AG18: 4 | AI18: =+AG18+AH18 -> 4 | AJ18: =+AI18-AL18 -> 2 | AK18: =((AI18-AJ18)*$B18) -> 60200 | AL18: 2 | AN18: =+AL18+AM18 -> 2 | AO18: =+AN18-AQ18 -> -1 | AP18: =((AN18-AO18)*$B18) -> 90300 | AQ18: 3 | AS18: =AQ18+AR18 -> 3 | AT18: =+AS18-AV18 -> 3 | AU18: =((AS18-AT18)*$B18) -> 0 | AX18: =+AV18+AW18 -> 0 | AY18: =+AX18-BA18 -> 0 | AZ18: =((AX18-AY18)*$B18) -> 0 | BC18: =+BA18+BB18 -> 0 | BD18: =+BC18-BF18 -> 0 | BE18: =((BC18-BD18)*$B18) -> 0 | BH18: =+BF18+BG18 -> 0 | BI18: =+BH18-BK18 -> 0 | BJ18: =((BH18-BI18)*$B18) -> 0
A19: GEL ANTICELULITICO | B19: 26600 | F19: =+E19-H19 -> 0 | G19: =((E19-F19)*$B19) -> 0 | K19: =+J19-M19 -> 0 | L19: =((J19-K19)*$B19) -> 0 | P19: =+O19-R19 -> 0 | Q19: =((O19-P19)*$B19) -> 0 | U19: =+T19-W19 -> 0 | V19: =((T19-U19)*$B19) -> 0 | Y19: =+W19+X19 -> 0 | Z19: =+Y19-AB19 -> 0 | AA19: =((Y19-Z19)*$B19) -> 0 | AD19: =+AB19+AC19 -> 0 | AE19: =+AD19-AG19 -> -2 | AF19: =((AD19-AE19)*$B19) -> 53200 | AG19: 2 | AI19: =+AG19+AH19 -> 2 | AJ19: =+AI19-AL19 -> 1 | AK19: =((AI19-AJ19)*$B19) -> 26600 | AL19: 1 | AN19: =+AL19+AM19 -> 1 | AO19: =+AN19-AQ19 -> 0 | AP19: =((AN19-AO19)*$B19) -> 26600 | AQ19: 1 | AS19: =AQ19+AR19 -> 1 | AT19: =+AS19-AV19 -> 1 | AU19: =((AS19-AT19)*$B19) -> 0 | AX19: =+AV19+AW19 -> 0 | AY19: =+AX19-BA19 -> 0 | AZ19: =((AX19-AY19)*$B19) -> 0 | BC19: =+BA19+BB19 -> 0 | BD19: =+BC19-BF19 -> 0 | BE19: =((BC19-BD19)*$B19) -> 0 | BH19: =+BF19+BG19 -> 0 | BI19: =+BH19-BK19 -> 0 | BJ19: =((BH19-BI19)*$B19) -> 0
A20: POTENCIALIZADOR DE ROMERO | B20: 31500 | F20: =+E20-H20 -> 0 | G20: =((E20-F20)*$B20) -> 0 | K20: =+J20-M20 -> 0 | L20: =((J20-K20)*$B20) -> 0 | P20: =+O20-R20 -> 0 | Q20: =((O20-P20)*$B20) -> 0 | U20: =+T20-W20 -> 0 | V20: =((T20-U20)*$B20) -> 0 | Y20: =+W20+X20 -> 0 | Z20: =+Y20-AB20 -> 0 | AA20: =((Y20-Z20)*$B20) -> 0 | AD20: =+AB20+AC20 -> 0 | AE20: =+AD20-AG20 -> -5 | AF20: =((AD20-AE20)*$B20) -> 157500 | AG20: 5 | AI20: =+AG20+AH20 -> 5 | AJ20: =+AI20-AL20 -> 0 | AK20: =((AI20-AJ20)*$B20) -> 157500 | AL20: 5 | AN20: =+AL20+AM20 -> 5 | AO20: =+AN20-AQ20 -> 0 | AP20: =((AN20-AO20)*$B20) -> 157500 | AQ20: 5 | AS20: =AQ20+AR20 -> 5 | AT20: =+AS20-AV20 -> 5 | AU20: =((AS20-AT20)*$B20) -> 0 | AX20: =+AV20+AW20 -> 0 | AY20: =+AX20-BA20 -> 0 | AZ20: =((AX20-AY20)*$B20) -> 0 | BC20: =+BA20+BB20 -> 0 | BD20: =+BC20-BF20 -> 0 | BE20: =((BC20-BD20)*$B20) -> 0 | BH20: =+BF20+BG20 -> 0 | BI20: =+BH20-BK20 -> 0 | BJ20: =((BH20-BI20)*$B20) -> 0
A21: ÓLEO ANTIEDAD | B21: 49000 | F21: =+E21-H21 -> 0 | G21: =((E21-F21)*$B21) -> 0 | K21: =+J21-M21 -> 0 | L21: =((J21-K21)*$B21) -> 0 | P21: =+O21-R21 -> 0 | Q21: =((O21-P21)*$B21) -> 0 | U21: =+T21-W21 -> 0 | V21: =((T21-U21)*$B21) -> 0 | Y21: =+W21+X21 -> 0 | Z21: =+Y21-AB21 -> 0 | AA21: =((Y21-Z21)*$B21) -> 0 | AD21: =+AB21+AC21 -> 0 | AE21: =+AD21-AG21 -> -2 | AF21: =((AD21-AE21)*$B21) -> 98000 | AG21: 2 | AI21: =+AG21+AH21 -> 2 | AJ21: =+AI21-AL21 -> 0 | AK21: =((AI21-AJ21)*$B21) -> 98000 | AL21: 2 | AN21: =+AL21+AM21 -> 2 | AO21: =+AN21-AQ21 -> 0 | AP21: =((AN21-AO21)*$B21) -> 98000 | AQ21: 2 | AS21: =AQ21+AR21 -> 2 | AT21: =+AS21-AV21 -> 2 | AU21: =((AS21-AT21)*$B21) -> 0 | AX21: =+AV21+AW21 -> 0 | AY21: =+AX21-BA21 -> 0 | AZ21: =((AX21-AY21)*$B21) -> 0 | BC21: =+BA21+BB21 -> 0 | BD21: =+BC21-BF21 -> 0 | BE21: =((BC21-BD21)*$B21) -> 0 | BH21: =+BF21+BG21 -> 0 | BI21: =+BH21-BK21 -> 0 | BJ21: =((BH21-BI21)*$B21) -> 0
A22: TÓNICO ANTICAÍDA DE CEBOLLA | B22: 49000 | F22: =+E22-H22 -> 0 | G22: =((E22-F22)*$B22) -> 0 | K22: =+J22-M22 -> 0 | L22: =((J22-K22)*$B22) -> 0 | P22: =+O22-R22 -> 0 | Q22: =((O22-P22)*$B22) -> 0 | U22: =+T22-W22 -> 0 | V22: =((T22-U22)*$B22) -> 0 | Y22: =+W22+X22 -> 0 | Z22: =+Y22-AB22 -> 0 | AA22: =((Y22-Z22)*$B22) -> 0 | AD22: =+AB22+AC22 -> 0 | AE22: =+AD22-AG22 -> -3 | AF22: =((AD22-AE22)*$B22) -> 147000 | AG22: 3 | AI22: =+AG22+AH22 -> 3 | AJ22: =+AI22-AL22 -> 0 | AK22: =((AI22-AJ22)*$B22) -> 147000 | AL22: 3 | AN22: =+AL22+AM22 -> 3 | AO22: =+AN22-AQ22 -> 1 | AP22: =((AN22-AO22)*$B22) -> 98000 | AQ22: 2 | AS22: =AQ22+AR22 -> 2 | AT22: =+AS22-AV22 -> 2 | AU22: =((AS22-AT22)*$B22) -> 0 | AX22: =+AV22+AW22 -> 0 | AY22: =+AX22-BA22 -> 0 | AZ22: =((AX22-AY22)*$B22) -> 0 | BC22: =+BA22+BB22 -> 0 | BD22: =+BC22-BF22 -> 0 | BE22: =((BC22-BD22)*$B22) -> 0 | BH22: =+BF22+BG22 -> 0 | BI22: =+BH22-BK22 -> 0 | BJ22: =((BH22-BI22)*$B22) -> 0
A23: ÓLEO DE ARGÁN | B23: 49000 | F23: =+E23-H23 -> 0 | G23: =((E23-F23)*$B23) -> 0 | K23: =+J23-M23 -> 0 | L23: =((J23-K23)*$B23) -> 0 | P23: =+O23-R23 -> 0 | Q23: =((O23-P23)*$B23) -> 0 | U23: =+T23-W23 -> 0 | V23: =((T23-U23)*$B23) -> 0 | Y23: =+W23+X23 -> 0 | Z23: =+Y23-AB23 -> 0 | AA23: =((Y23-Z23)*$B23) -> 0 | AD23: =+AB23+AC23 -> 0 | AE23: =+AD23-AG23 -> -2 | AF23: =((AD23-AE23)*$B23) -> 98000 | AG23: 2 | AI23: =+AG23+AH23 -> 2 | AJ23: =+AI23-AL23 -> 1 | AK23: =((AI23-AJ23)*$B23) -> 49000 | AL23: 1 | AN23: =+AL23+AM23 -> 1 | AO23: =+AN23-AQ23 -> 0 | AP23: =((AN23-AO23)*$B23) -> 49000 | AQ23: 1 | AS23: =AQ23+AR23 -> 1 | AT23: =+AS23-AV23 -> 1 | AU23: =((AS23-AT23)*$B23) -> 0 | AX23: =+AV23+AW23 -> 0 | AY23: =+AX23-BA23 -> 0 | AZ23: =((AX23-AY23)*$B23) -> 0 | BC23: =+BA23+BB23 -> 0 | BD23: =+BC23-BF23 -> 0 | BE23: =((BC23-BD23)*$B23) -> 0 | BH23: =+BF23+BG23 -> 0 | BI23: =+BH23-BK23 -> 0 | BJ23: =((BH23-BI23)*$B23) -> 0
A24: CREMA PARA PEINAR COCO | B24: 26600 | F24: =+E24-H24 -> 0 | G24: =((E24-F24)*$B24) -> 0 | K24: =+J24-M24 -> 0 | L24: =((J24-K24)*$B24) -> 0 | P24: =+O24-R24 -> 0 | Q24: =((O24-P24)*$B24) -> 0 | U24: =+T24-W24 -> 0 | V24: =((T24-U24)*$B24) -> 0 | Y24: =+W24+X24 -> 0 | Z24: =+Y24-AB24 -> 0 | AA24: =((Y24-Z24)*$B24) -> 0 | AD24: =+AB24+AC24 -> 0 | AE24: =+AD24-AG24 -> 0 | AF24: =((AD24-AE24)*$B24) -> 0 | AG24: 0 | AI24: =+AG24+AH24 -> 0 | AJ24: =+AI24-AL24 -> 0 | AK24: =((AI24-AJ24)*$B24) -> 0 | AL24: 0 | AN24: =+AL24+AM24 -> 0 | AO24: =+AN24-AQ24 -> 0 | AP24: =((AN24-AO24)*$B24) -> 0 | AQ24: 0 | AS24: =AQ24+AR24 -> 0 | AT24: =+AS24-AV24 -> 0 | AU24: =((AS24-AT24)*$B24) -> 0 | AX24: =+AV24+AW24 -> 0 | AY24: =+AX24-BA24 -> 0 | AZ24: =((AX24-AY24)*$B24) -> 0 | BC24: =+BA24+BB24 -> 0 | BD24: =+BC24-BF24 -> 0 | BE24: =((BC24-BD24)*$B24) -> 0 | BH24: =+BF24+BG24 -> 0 | BI24: =+BH24-BK24 -> 0 | BJ24: =((BH24-BI24)*$B24) -> 0
A25: BLINDAGEM TERMOPROTECTOR | B25: 33600 | F25: =+E25-H25 -> 0 | G25: =((E25-F25)*$B25) -> 0 | K25: =+J25-M25 -> 0 | L25: =((J25-K25)*$B25) -> 0 | P25: =+O25-R25 -> 0 | Q25: =((O25-P25)*$B25) -> 0 | U25: =+T25-W25 -> 0 | V25: =((T25-U25)*$B25) -> 0 | Y25: =+W25+X25 -> 0 | Z25: =+Y25-AB25 -> 0 | AA25: =((Y25-Z25)*$B25) -> 0 | AD25: =+AB25+AC25 -> 0 | AE25: =+AD25-AG25 -> -1 | AF25: =((AD25-AE25)*$B25) -> 33600 | AG25: 1 | AI25: =+AG25+AH25 -> 1 | AJ25: =+AI25-AL25 -> 0 | AK25: =((AI25-AJ25)*$B25) -> 33600 | AL25: 1 | AN25: =+AL25+AM25 -> 1 | AO25: =+AN25-AQ25 -> 0 | AP25: =((AN25-AO25)*$B25) -> 33600 | AQ25: 1 | AS25: =AQ25+AR25 -> 1 | AT25: =+AS25-AV25 -> 1 | AU25: =((AS25-AT25)*$B25) -> 0 | AX25: =+AV25+AW25 -> 0 | AY25: =+AX25-BA25 -> 0 | AZ25: =((AX25-AY25)*$B25) -> 0 | BC25: =+BA25+BB25 -> 0 | BD25: =+BC25-BF25 -> 0 | BE25: =((BC25-BD25)*$B25) -> 0 | BH25: =+BF25+BG25 -> 0 | BI25: =+BH25-BK25 -> 0 | BJ25: =((BH25-BI25)*$B25) -> 0
A26: VITAMINA C DÍA | B26: 42000 | F26: =+E26-H26 -> 0 | G26: =((E26-F26)*$B26) -> 0 | K26: =+J26-M26 -> 0 | L26: =((J26-K26)*$B26) -> 0 | P26: =+O26-R26 -> 0 | Q26: =((O26-P26)*$B26) -> 0 | U26: =+T26-W26 -> 0 | V26: =((T26-U26)*$B26) -> 0 | Y26: =+W26+X26 -> 0 | Z26: =+Y26-AB26 -> 0 | AA26: =((Y26-Z26)*$B26) -> 0 | AD26: =+AB26+AC26 -> 0 | AE26: =+AD26-AG26 -> 0 | AF26: =((AD26-AE26)*$B26) -> 0 | AG26: 0 | AI26: =+AG26+AH26 -> 0 | AJ26: =+AI26-AL26 -> 0 | AK26: =((AI26-AJ26)*$B26) -> 0 | AL26: 0 | AN26: =+AL26+AM26 -> 0 | AO26: =+AN26-AQ26 -> 0 | AP26: =((AN26-AO26)*$B26) -> 0 | AQ26: 0 | AS26: =AQ26+AR26 -> 0 | AT26: =+AS26-AV26 -> 0 | AU26: =((AS26-AT26)*$B26) -> 0 | AX26: =+AV26+AW26 -> 0 | AY26: =+AX26-BA26 -> 0 | AZ26: =((AX26-AY26)*$B26) -> 0 | BC26: =+BA26+BB26 -> 0 | BD26: =+BC26-BF26 -> 0 | BE26: =((BC26-BD26)*$B26) -> 0 | BH26: =+BF26+BG26 -> 0 | BI26: =+BH26-BK26 -> 0 | BJ26: =((BH26-BI26)*$B26) -> 0
A27: VITAMINA C NOCHE | B27: 49000 | F27: =+E27-H27 -> 0 | G27: =((E27-F27)*$B27) -> 0 | K27: =+J27-M27 -> 0 | L27: =((J27-K27)*$B27) -> 0 | P27: =+O27-R27 -> 0 | Q27: =((O27-P27)*$B27) -> 0 | U27: =+T27-W27 -> 0 | V27: =((T27-U27)*$B27) -> 0 | Y27: =+W27+X27 -> 0 | Z27: =+Y27-AB27 -> 0 | AA27: =((Y27-Z27)*$B27) -> 0 | AD27: =+AB27+AC27 -> 0 | AE27: =+AD27-AG27 -> 0 | AF27: =((AD27-AE27)*$B27) -> 0 | AG27: 0 | AI27: =+AG27+AH27 -> 0 | AJ27: =+AI27-AL27 -> 0 | AK27: =((AI27-AJ27)*$B27) -> 0 | AL27: 0 | AN27: =+AL27+AM27 -> 0 | AO27: =+AN27-AQ27 -> 0 | AP27: =((AN27-AO27)*$B27) -> 0 | AQ27: 0 | AS27: =AQ27+AR27 -> 0 | AT27: =+AS27-AV27 -> 0 | AU27: =((AS27-AT27)*$B27) -> 0 | AX27: =+AV27+AW27 -> 0 | AY27: 0 | AZ27: =((AX27-AY27)*$B27) -> 0 | BC27: =+BA27+BB27 -> 0 | BD27: =+BC27-BF27 -> 0 | BE27: =((BC27-BD27)*$B27) -> 0 | BH27: =+BF27+BG27 -> 0 | BI27: =+BH27-BK27 -> 0 | BJ27: =((BH27-BI27)*$B27) -> 0
A28: CREMA HUMECTANTE Y REAFIRMANTE | B28: 26600 | F28: =+E28-H28 -> 0 | G28: =((E28-F28)*$B28) -> 0 | K28: =+J28-M28 -> 0 | L28: =((J28-K28)*$B28) -> 0 | P28: =+O28-R28 -> 0 | Q28: =((O28-P28)*$B28) -> 0 | U28: =+T28-W28 -> 0 | V28: =((T28-U28)*$B28) -> 0 | Y28: =+W28+X28 -> 0 | Z28: =+Y28-AB28 -> 0 | AA28: =((Y28-Z28)*$B28) -> 0 | AD28: =+AB28+AC28 -> 0 | AE28: =+AD28-AG28 -> -3 | AF28: =((AD28-AE28)*$B28) -> 79800 | AG28: 3 | AI28: =+AG28+AH28 -> 3 | AJ28: =+AI28-AL28 -> 0 | AK28: =((AI28-AJ28)*$B28) -> 79800 | AL28: 3 | AN28: =+AL28+AM28 -> 3 | AO28: =+AN28-AQ28 -> 0 | AP28: =((AN28-AO28)*$B28) -> 79800 | AQ28: 3 | AS28: =AQ28+AR28 -> 3 | AT28: =+AS28-AV28 -> 3 | AU28: =((AS28-AT28)*$B28) -> 0 | AX28: =+AV28+AW28 -> 0 | AY28: =+AX28-BA28 -> 0 | AZ28: =((AX28-AY28)*$B28) -> 0 | BC28: =+BA28+BB28 -> 0 | BD28: =+BC28-BF28 -> 0 | BE28: =((BC28-BD28)*$B28) -> 0 | BH28: =+BF28+BG28 -> 0 | BI28: =+BH28-BK28 -> 0 | BJ28: =((BH28-BI28)*$B28) -> 0
A29: PERFUME DE ROSAS | B29: 87500 | F29: =+E29-H29 -> 0 | G29: =((E29-F29)*$B29) -> 0 | K29: =+J29-M29 -> 0 | L29: =((J29-K29)*$B29) -> 0 | P29: =+O29-R29 -> 0 | Q29: =((O29-P29)*$B29) -> 0 | U29: =+T29-W29 -> 0 | V29: =((T29-U29)*$B29) -> 0 | Y29: =+W29+X29 -> 0 | Z29: =+Y29-AB29 -> 0 | AA29: =((Y29-Z29)*$B29) -> 0 | AD29: =+AB29+AC29 -> 0 | AE29: =+AD29-AG29 -> -1 | AF29: =((AD29-AE29)*$B29) -> 87500 | AG29: 1 | AI29: =+AG29+AH29 -> 1 | AJ29: =+AI29-AL29 -> 0 | AK29: =((AI29-AJ29)*$B29) -> 87500 | AL29: 1 | AN29: =+AL29+AM29 -> 1 | AO29: =+AN29-AQ29 -> 0 | AP29: =((AN29-AO29)*$B29) -> 87500 | AQ29: 1 | AS29: =AQ29+AR29 -> 1 | AT29: =+AS29-AV29 -> 1 | AU29: =((AS29-AT29)*$B29) -> 0 | AX29: =+AV29+AW29 -> 0 | AY29: =+AX29-BA29 -> 0 | AZ29: =((AX29-AY29)*$B29) -> 0 | BC29: =+BA29+BB29 -> 0 | BD29: =+BC29-BF29 -> 0 | BE29: =((BC29-BD29)*$B29) -> 0 | BH29: =+BF29+BG29 -> 0 | BI29: =+BH29-BK29 -> 0 | BJ29: =((BH29-BI29)*$B29) -> 0
A30: BRONCEADOR ACHIOTE / CANELA | B30: 29400 | F30: =+E30-H30 -> 0 | G30: =((E30-F30)*$B30) -> 0 | K30: =+J30-M30 -> 0 | L30: =((J30-K30)*$B30) -> 0 | P30: =+O30-R30 -> 0 | Q30: =((O30-P30)*$B30) -> 0 | U30: =+T30-W30 -> 0 | V30: =((T30-U30)*$B30) -> 0 | Y30: =+W30+X30 -> 0 | Z30: =+Y30-AB30 -> 0 | AA30: =((Y30-Z30)*$B30) -> 0 | AD30: =+AB30+AC30 -> 0 | AE30: =+AD30-AG30 -> -9 | AF30: =((AD30-AE30)*$B30) -> 264600 | AG30: 9 | AI30: =+AG30+AH30 -> 9 | AJ30: =+AI30-AL30 -> 0 | AK30: =((AI30-AJ30)*$B30) -> 264600 | AL30: 9 | AN30: =+AL30+AM30 -> 9 | AO30: =+AN30-AQ30 -> 0 | AP30: =((AN30-AO30)*$B30) -> 264600 | AQ30: 9 | AS30: =AQ30+AR30 -> 9 | AT30: =+AS30-AV30 -> 9 | AU30: =((AS30-AT30)*$B30) -> 0 | AX30: =+AV30+AW30 -> 0 | AY30: =+AX30-BA30 -> 0 | AZ30: =((AX30-AY30)*$B30) -> 0 | BC30: =+BA30+BB30 -> 0 | BD30: =+BC30-BF30 -> 0 | BE30: =((BC30-BD30)*$B30) -> 0 | BH30: =+BF30+BG30 -> 0 | BI30: =+BH30-BK30 -> 0 | BJ30: =((BH30-BI30)*$B30) -> 0
A31: JALEA FACIAL | B31: 35000 | F31: =+E31-H31 -> 0 | G31: =((E31-F31)*$B31) -> 0 | K31: =+J31-M31 -> 0 | L31: =((J31-K31)*$B31) -> 0 | P31: =+O31-R31 -> 0 | Q31: =((O31-P31)*$B31) -> 0 | U31: =+T31-W31 -> 0 | V31: =((T31-U31)*$B31) -> 0 | Y31: =+W31+X31 -> 0 | Z31: =+Y31-AB31 -> 0 | AA31: =((Y31-Z31)*$B31) -> 0 | AD31: =+AB31+AC31 -> 0 | AE31: =+AD31-AG31 -> 0 | AF31: =((AD31-AE31)*$B31) -> 0 | AG31: 0 | AI31: =+AG31+AH31 -> 0 | AJ31: =+AI31-AL31 -> 0 | AK31: =((AI31-AJ31)*$B31) -> 0 | AL31: 0 | AN31: =+AL31+AM31 -> 0 | AO31: =+AN31-AQ31 -> 0 | AP31: =((AN31-AO31)*$B31) -> 0 | AQ31: 0 | AS31: =AQ31+AR31 -> 0 | AT31: =+AS31-AV31 -> 0 | AU31: =((AS31-AT31)*$B31) -> 0 | AX31: =+AV31+AW31 -> 0 | AY31: =+AX31-BA31 -> 0 | AZ31: =((AX31-AY31)*$B31) -> 0 | BC31: =+BA31+BB31 -> 0 | BD31: =+BC31-BF31 -> 0 | BE31: =((BC31-BD31)*$B31) -> 0 | BH31: =+BF31+BG31 -> 0 | BI31: =+BH31-BK31 -> 0 | BJ31: =((BH31-BI31)*$B31) -> 0
A32: MASCARA REPARADORA GORRO | B32: 42000 | F32: =+E32-H32 -> 0 | G32: =((E32-F32)*$B32) -> 0 | K32: =+J32-M32 -> 0 | L32: =((J32-K32)*$B32) -> 0 | P32: =+O32-R32 -> 0 | Q32: =((O32-P32)*$B32) -> 0 | U32: =+T32-W32 -> 0 | V32: =((T32-U32)*$B32) -> 0 | Y32: =+W32+X32 -> 0 | Z32: =+Y32-AB32 -> 0 | AA32: =((Y32-Z32)*$B32) -> 0 | AD32: =+AB32+AC32 -> 0 | AE32: =+AD32-AG32 -> 0 | AF32: =((AD32-AE32)*$B32) -> 0 | AG32: 0 | AI32: =+AG32+AH32 -> 0 | AJ32: =+AI32-AL32 -> 0 | AK32: =((AI32-AJ32)*$B32) -> 0 | AL32: 0 | AM32: 2 | AN32: =+AL32+AM32 -> 2 | AO32: =+AN32-AQ32 -> 2 | AP32: =((AN32-AO32)*$B32) -> 0 | AQ32: 0 | AS32: =AQ32+AR32 -> 0 | AT32: =+AS32-AV32 -> 0 | AU32: =((AS32-AT32)*$B32) -> 0 | AX32: =+AV32+AW32 -> 0 | AY32: =+AX32-BA32 -> 0 | AZ32: =((AX32-AY32)*$B32) -> 0 | BC32: =+BA32+BB32 -> 0 | BD32: =+BC32-BF32 -> 0 | BE32: =((BC32-BD32)*$B32) -> 0 | BH32: =+BF32+BG32 -> 0 | BI32: =+BH32-BK32 -> 0 | BJ32: =((BH32-BI32)*$B32) -> 0
A33: TRATAMIENTO MACA | B33: 52500 | F33: =+E33-H33 -> 0 | G33: =((E33-F33)*$B33) -> 0 | K33: =+J33-M33 -> 0 | L33: =((J33-K33)*$B33) -> 0 | P33: =+O33-R33 -> 0 | Q33: =((O33-P33)*$B33) -> 0 | U33: =+T33-W33 -> 0 | V33: =((T33-U33)*$B33) -> 0 | Y33: =+W33+X33 -> 0 | Z33: =+Y33-AB33 -> 0 | AA33: =((Y33-Z33)*$B33) -> 0 | AD33: =+AB33+AC33 -> 0 | AE33: =+AD33-AG33 -> 0 | AF33: =((AD33-AE33)*$B33) -> 0 | AG33: 0 | AI33: =+AG33+AH33 -> 0 | AJ33: =+AI33-AL33 -> 0 | AK33: =((AI33-AJ33)*$B33) -> 0 | AL33: 0 | AM33: 6 | AN33: =+AL33+AM33 -> 6 | AO33: =+AN33-AQ33 -> 3 | AP33: =((AN33-AO33)*$B33) -> 157500 | AQ33: 3 | AS33: =AQ33+AR33 -> 3 | AT33: =+AS33-AV33 -> 3 | AU33: =((AS33-AT33)*$B33) -> 0 | AX33: =+AV33+AW33 -> 0 | AY33: =+AX33-BA33 -> 0 | AZ33: =((AX33-AY33)*$B33) -> 0 | BC33: =+BA33+BB33 -> 0 | BD33: =+BC33-BF33 -> 0 | BE33: =((BC33-BD33)*$B33) -> 0 | BH33: =+BF33+BG33 -> 0 | BI33: =+BH33-BK33 -> 0 | BJ33: =((BH33-BI33)*$B33) -> 0
F34: =+E34-H34 -> 0 | G34: =((E34-F34)*$B34) -> 0 | K34: =+J34-M34 -> 0 | L34: =((J34-K34)*$B34) -> 0 | P34: =+O34-R34 -> 0 | Q34: =((O34-P34)*$B34) -> 0 | U34: =+T34-W34 -> 0 | V34: =((T34-U34)*$B34) -> 0 | Y34: =+W34+X34 -> 0 | Z34: =+Y34-AB34 -> 0 | AA34: =((Y34-Z34)*$B34) -> 0 | AD34: =+AB34+AC34 -> 0 | AE34: =+AD34-AG34 -> 0 | AF34: =((AD34-AE34)*$B34) -> 0 | AI34: =+AG34+AH34 -> 0 | AJ34: =+AI34-AL34 -> 0 | AK34: =((AI34-AJ34)*$B34) -> 0 | AN34: =+AL34+AM34 -> 0 | AO34: =+AN34-AQ34 -> 0 | AP34: =((AN34-AO34)*$B34) -> 0 | AS34: =AQ34+AR34 -> 0 | AT34: =+AS34-AV34 -> 0 | AU34: =((AS34-AT34)*$B34) -> 0 | AX34: =+AV34+AW34 -> 0 | AY34: =+AX34-BA34 -> 0 | AZ34: =((AX34-AY34)*$B34) -> 0 | BC34: =+BA34+BB34 -> 0 | BD34: =+BC34-BF34 -> 0 | BE34: =((BC34-BD34)*$B34) -> 0 | BH34: =+BF34+BG34 -> 0 | BI34: =+BH34-BK34 -> 0 | BJ34: =((BH34-BI34)*$B34) -> 0
F35: =+E35-H35 -> 0 | G35: =((E35-F35)*$B35) -> 0 | K35: =+J35-M35 -> 0 | L35: =((J35-K35)*$B35) -> 0 | P35: =+O35-R35 -> 0 | Q35: =((O35-P35)*$B35) -> 0 | U35: =+T35-W35 -> 0 | V35: =((T35-U35)*$B35) -> 0 | Y35: =+W35+X35 -> 0 | Z35: =+Y35-AB35 -> 0 | AA35: =((Y35-Z35)*$B35) -> 0 | AD35: =+AB35+AC35 -> 0 | AE35: =+AD35-AG35 -> 0 | AF35: =((AD35-AE35)*$B35) -> 0 | AI35: =+AG35+AH35 -> 0 | AJ35: =+AI35-AL35 -> 0 | AK35: =((AI35-AJ35)*$B35) -> 0 | AN35: =+AL35+AM35 -> 0 | AO35: =+AN35-AQ35 -> 0 | AP35: =((AN35-AO35)*$B35) -> 0 | AS35: =AQ35+AR35 -> 0 | AT35: =+AS35-AV35 -> 0 | AU35: =((AS35-AT35)*$B35) -> 0 | AX35: =+AV35+AW35 -> 0 | AY35: =+AX35-BA35 -> 0 | AZ35: =((AX35-AY35)*$B35) -> 0 | BC35: =+BA35+BB35 -> 0 | BD35: =+BC35-BF35 -> 0 | BE35: =((BC35-BD35)*$B35) -> 0 | BH35: =+BF35+BG35 -> 0 | BI35: =+BH35-BK35 -> 0 | BJ35: =((BH35-BI35)*$B35) -> 0
F36: =+E36-H36 -> 0 | G36: =((E36-F36)*$B36) -> 0 | K36: =+J36-M36 -> 0 | L36: =((J36-K36)*$B36) -> 0 | P36: =+O36-R36 -> 0 | Q36: =((O36-P36)*$B36) -> 0 | U36: =+T36-W36 -> 0 | V36: =((T36-U36)*$B36) -> 0 | Y36: =+W36+X36 -> 0 | Z36: =+Y36-AB36 -> 0 | AA36: =((Y36-Z36)*$B36) -> 0 | AD36: =+AB36+AC36 -> 0 | AE36: =+AD36-AG36 -> 0 | AF36: =((AD36-AE36)*$B36) -> 0 | AI36: =+AG36+AH36 -> 0 | AJ36: =+AI36-AL36 -> 0 | AK36: =((AI36-AJ36)*$B36) -> 0 | AN36: =+AL36+AM36 -> 0 | AO36: =+AN36-AQ36 -> 0 | AP36: =((AN36-AO36)*$B36) -> 0 | AS36: =AQ36+AR36 -> 0 | AT36: =+AS36-AV36 -> 0 | AU36: =((AS36-AT36)*$B36) -> 0 | AX36: =+AV36+AW36 -> 0 | AY36: =+AX36-BA36 -> 0 | AZ36: =((AX36-AY36)*$B36) -> 0 | BC36: =+BA36+BB36 -> 0 | BD36: =+BC36-BF36 -> 0 | BE36: =((BC36-BD36)*$B36) -> 0 | BH36: =+BF36+BG36 -> 0 | BI36: =+BH36-BK36 -> 0 | BJ36: =((BH36-BI36)*$B36) -> 0
F37: =+E37-H37 -> 0 | G37: =((E37-F37)*$B37) -> 0 | K37: =+J37-M37 -> 0 | L37: =((J37-K37)*$B37) -> 0 | P37: =+O37-R37 -> 0 | Q37: =((O37-P37)*$B37) -> 0 | U37: =+T37-W37 -> 0 | V37: =((T37-U37)*$B37) -> 0 | Y37: =+W37+X37 -> 0 | Z37: =+Y37-AB37 -> 0 | AA37: =((Y37-Z37)*$B37) -> 0 | AD37: =+AB37+AC37 -> 0 | AE37: =+AD37-AG37 -> 0 | AF37: =((AD37-AE37)*$B37) -> 0 | AI37: =+AG37+AH37 -> 0 | AJ37: =+AI37-AL37 -> 0 | AK37: =((AI37-AJ37)*$B37) -> 0 | AN37: =+AL37+AM37 -> 0 | AO37: =+AN37-AQ37 -> 0 | AP37: =((AN37-AO37)*$B37) -> 0 | AS37: =AQ37+AR37 -> 0 | AT37: =+AS37-AV37 -> 0 | AU37: =((AS37-AT37)*$B37) -> 0 | AX37: =+AV37+AW37 -> 0 | AY37: =+AX37-BA37 -> 0 | AZ37: =((AX37-AY37)*$B37) -> 0 | BC37: =+BA37+BB37 -> 0 | BD37: =+BC37-BF37 -> 0 | BE37: =((BC37-BD37)*$B37) -> 0 | BH37: =+BF37+BG37 -> 0 | BI37: =+BH37-BK37 -> 0 | BJ37: =((BH37-BI37)*$B37) -> 0
G38: =+SUM(G3:G37) -> 0 | L38: =+SUM(L3:L37) -> 0 | Q38: =UPLUS(SUM(Q3:Q37)) -> #NAME? | V38: =+SUM(V3:V37) -> 0 | AA38: =SUM(AA3:AA37) -> 0 | AF38: =+SUM(AF3:AF32) -> 4076800 | AK38: =+SUM(AK3:AK32) -> 3759000 | AP38: =+SUM(AP3:AP37) -> 3738000 | AU38: =+SUM(AU3:AU37) -> 0 | AZ38: =+SUM(AZ3:AZ37) -> 0 | BE38: =+SUM(BE3:BE37) -> 0 | BJ38: =+SUM(BJ3:BJ37) -> 0

Sheet MZ
A1: MARIANA ZAPATA | C1: ENERO | H1: FEBRERO | M1: MARZO | R1: ABRIL | W1: MAYO | AB1: JUNIO | AG1: JULIO | AL1: AGOSTO | AQ1: SEPTIEMBRE | AV1: OCTUBRE | BA1: NOVIEMBRE | BF1: DICIEMBRE | BK1: ENERO
A2: PRODUCTO | B2: VR. COMPRA | C2: INV.I | D2: Entra | E2: Saldo | F2: SALIDA | G2: TOTAL | H2: INV.I | I2: Entra | J2: Saldo | K2: SALIDA | L2: TOTAL | M2: INV.I | N2: Entra | O2: Saldo | P2: SALIDA | Q2: TOTAL | R2: INV.I | S2: Entra | T2: Saldo | U2: SALIDA | V2: TOTAL | W2: INV.I | X2: Entra | Y2: Saldo | Z2: SALIDA | AA2: TOTAL | AB2: INV.I | AC2: Entra | AD2: Saldo | AE2: SALIDA | AF2: TOTAL | AG2: INV.I | AH2: Entra | AI2: Saldo | AJ2: SALIDA | AK2: TOTAL | AL2: INV.I | AM2: Entra | AN2: Saldo | AO2: SALIDA | AP2: TOTAL | AQ2: INV.I | AR2: Entra | AS2: Saldo | AT2: SALIDA | AU2: TOTAL | AV2: INV.I | AW2: Entra | AX2: Saldo | AY2: SALIDA | AZ2: TOTAL | BA2: INV.I | BB2: Entra | BC2: Saldo | BD2: SALIDA | BE2: TOTAL | BF2: INV.I | BG2: Entra | BH2: Saldo | BI2: SALIDA | BJ2: TOTAL | BK2: INV.I
A3: SHAMPOO | B3: 31000 | F3: =+E3-H3 -> 0 | G3: =((E3-F3)*$B3) -> 0 | K3: =+J3-M3 -> 0 | L3: =((J3-K3)*$B3) -> 0 | P3: =+O3-R3 -> 0 | Q3: =((O3-P3)*$B3) -> 0 | U3: =+T3-W3 -> 0 | V3: =((T3-U3)*$B3) -> 0 | Z3: =+Y3-AB3 -> 0 | AA3: =((Y3-Z3)*$B3) -> 0 | AE3: =+AD3-AG3 -> -44 | AF3: =((AD3-AE3)*$B3) -> 1364000 | AG3: 44 | AI3: =+AG3+AH3 -> 44 | AJ3: =+AI3-AL3 -> 2 | AK3: =((AI3-AJ3)*$B3) -> 1302000 | AL3: 42 | AN3: =+AL3+AM3 -> 42 | AO3: =+AN3-AQ3 -> 0 | AP3: =((AN3-AO3)*$B3) -> 1302000 | AQ3: 42 | AS3: =+AQ3+AR3 -> 42 | AT3: =+AS3-AV3 -> 42 | AU3: =((AS3-AT3)*$B3) -> 0 | AX3: =+AV3+AW3 -> 0 | AY3: =+AX3-BA3 -> 0 | AZ3: =((AX3-AY3)*$B3) -> 0 | BC3: =+BA3+BB3 -> 0 | BD3: =+BC3-BF3 -> 0 | BE3: =((BC3-BD3)*$B3) -> 0 | BH3: =+BF3+BG3 -> 0 | BI3: =+BH3-BK3 -> 0 | BJ3: =((BH3-BI3)*$B3) -> 0
A4: ACONDICIONADOR | B4: 30000 | F4: =+E4-H4 -> 0 | G4: =((E4-F4)*$B4) -> 0 | K4: =+J4-M4 -> 0 | L4: =((J4-K4)*$B4) -> 0 | P4: =+O4-R4 -> 0 | Q4: =((O4-P4)*$B4) -> 0 | U4: =+T4-W4 -> 0 | V4: =((T4-U4)*$B4) -> 0 | Z4: =+Y4-AB4 -> 0 | AA4: =((Y4-Z4)*$B4) -> 0 | AE4: =+AD4-AG4 -> -30 | AF4: =((AD4-AE4)*$B4) -> 900000 | AG4: 30 | AI4: =+AG4+AH4 -> 30 | AJ4: =+AI4-AL4 -> 2 | AK4: =((AI4-AJ4)*$B4) -> 840000 | AL4: 28 | AN4: =+AL4+AM4 -> 28 | AO4: =+AN4-AQ4 -> 0 | AP4: =((AN4-AO4)*$B4) -> 840000 | AQ4: 28 | AS4: =+AQ4+AR4 -> 28 | AT4: =+AS4-AV4 -> 28 | AU4: =((AS4-AT4)*$B4) -> 0 | AX4: =+AV4+AW4 -> 0 | AY4: =+AX4-BA4 -> 0 | AZ4: =((AX4-AY4)*$B4) -> 0 | BC4: =+BA4+BB4 -> 0 | BD4: =+BC4-BF4 -> 0 | BE4: =((BC4-BD4)*$B4) -> 0 | BH4: =+BF4+BG4 -> 0 | BI4: =+BH4-BK4 -> 0 | BJ4: =((BH4-BI4)*$B4) -> 0
A5: PERFUME CAPILAR MZ | B5: 22000 | AE5: =+AD5-AG5 -> -4 | AF5: =((AD5-AE5)*$B5) -> 88000 | AG5: 4 | AI5: =+AG5+AH5 -> 4 | AJ5: =+AI5-AL5 -> 0 | AK5: =((AI5-AJ5)*$B5) -> 88000 | AL5: 4 | AN5: =+AL5+AM5 -> 4 | AO5: =+AN5-AQ5 -> 0 | AP5: =((AN5-AO5)*$B5) -> 88000 | AQ5: 4
A6: MASCARILLA CAPILAR FRUTAS MZ | B6: 37000 | F6: =+E6-H6 -> 0 | G6: =((E6-F6)*$B6) -> 0 | K6: =+J6-M6 -> 0 | L6: =((J6-K6)*$B6) -> 0 | P6: =+O6-R6 -> 0 | Q6: =((O6-P6)*$B6) -> 0 | U6: =+T6-W6 -> 0 | V6: =((T6-U6)*$B6) -> 0 | Z6: =+Y6-AB6 -> 0 | AA6: =((Y6-Z6)*$B6) -> 0 | AE6: =+AD6-AG6 -> 0 | AF6: =((AD6-AE6)*$B6) -> 0 | AI6: =+AG6+AH6 -> 0 | AJ6: =+AI6-AL6 -> -4 | AK6: =((AI6-AJ6)*$B6) -> 148000 | AL6: 4 | AN6: =+AL6+AM6 -> 4 | AO6: =+AN6-AQ6 -> 4 | AP6: =((AN6-AO6)*$B6) -> 0 | AQ6: 0 | AS6: =+AQ6+AR6 -> 0 | AT6: =+AS6-AV6 -> 0 | AU6: =((AS6-AT6)*$B6) -> 0 | AX6: =+AV6+AW6 -> 0 | AY6: =+AX6-BA6 -> 0 | AZ6: =((AX6-AY6)*$B6) -> 0 | BB6: 3 | BC6: =+BA6+BB6 -> 3 | BD6: =+BC6-BF6 -> 3 | BE6: =((BC6-BD6)*$B6) -> 0 | BH6: =+BF6+BG6 -> 0 | BI6: =+BH6-BK6 -> 0 | BJ6: =((BH6-BI6)*$B6) -> 0
G7: =+SUM(G3:G6) -> 0 | L7: =+SUM(L3:L6) -> 0 | Q7: =+SUM(Q3:Q6) -> 0 | V7: =+SUM(V3:V6) -> 0 | AA7: =+SUM(AA3:AA6) -> 0 | AF7: =+SUM(AF3:AF6) -> 2352000 | AK7: =+SUM(AK3:AK6) -> 2378000 | AP7: =+SUM(AP3:AP6) -> 2230000 | AU7: =+SUM(AU3:AU6) -> 0 | AZ7: =+SUM(AZ3:AZ6) -> 0 | BE7: =+SUM(BE3:BE6) -> 0 | BJ7: =+SUM(BJ3:BJ6) -> 0

Sheet CEPILLOS
A1: CEPILLOS | C1: ENERO | H1: FEBRERO | M1: MARZO | R1: ABRIL | W1: MAYO | AB1: JUNIO | AG1: JULIO | AL1: AGOSTO | AQ1: SEPTIEMBRE | AV1: OCTUBRE | BA1: NOVIEMBRE | BF1: DICIEMBRE | BK1: ENERO
A2: PRODUCTO | B2: VR. COMPRA | C2: INV.I | D2: Entra | E2: Saldo | F2: SALIDA | G2: TOTAL | H2: INV.I | I2: Entra | J2: Saldo | K2: SALIDA | L2: TOTAL | M2: INV.I | N2: Entra | O2: Saldo | P2: SALIDA | Q2: TOTAL | R2: INV.I | S2: Entra | T2: Saldo | U2: SALIDA | V2: TOTAL | W2: INV.I | X2: Entra | Y2: Saldo | Z2: SALIDA | AA2: TOTAL | AB2: INV.I | AC2: Entra | AD2: Saldo | AE2: SALIDA | AF2: TOTAL | AG2: INV.I | AH2: Entra | AI2: Saldo | AJ2: SALIDA | AK2: TOTAL | AL2: INV.I | AM2: Entra | AN2: Saldo | AO2: SALIDA | AP2: TOTAL | AQ2: INV.I | AR2: Entra | AS2: Saldo | AT2: SALIDA | AU2: TOTAL | AV2: INV.I | AW2: Entra | AX2: Saldo | AY2: SALIDA | AZ2: TOTAL | BA2: INV.I | BB2: Entra | BC2: Saldo | BD2: SALIDA | BE2: TOTAL | BF2: INV.I | BG2: Entra | BH2: Saldo | BI2: SALIDA | BJ2: TOTAL | BK2: INV.I
A3: CEPILLOS MASAJEADOR | B3: 3800 | F3: =+E3-H3 -> 0 | G3: =((E3-F3)*$B3) -> 0 | K3: =+J3-M3 -> 0 | L3: =((J3-K3)*$B3) -> 0 | P3: =+O3-R3 -> 0 | Q3: =((O3-P3)*$B3) -> 0 | U3: =+T3-W3 -> 0 | V3: =((T3-U3)*$B3) -> 0 | Z3: =+Y3-AB3 -> 0 | AA3: =((Y3-Z3)*$B3) -> 0 | AE3: =+AD3-AG3 -> -42 | AF3: =((AD3-AE3)*$B3) -> 159600 | AG3: 42 | AI3: =+AG3+AH3 -> 42 | AJ3: =+AI3-AL3 -> 0 | AK3: =((AI3-AJ3)*$B3) -> 159600 | AL3: 42 | AN3: =+AL3+AM3 -> 42 | AO3: =+AN3-AQ3 -> 2 | AP3: =((AN3-AO3)*$B3) -> 152000 | AQ3: 40 | AS3: =+AQ3+AR3 -> 40 | AT3: =+AS3-AV3 -> 40 | AU3: =((AS3-AT3)*$B3) -> 0 | AX3: =+AV3+AW3 -> 0 | AY3: =+AX3-BA3 -> 0 | AZ3: =((AX3-AY3)*$B3) -> 0 | BC3: =+BA3+BB3 -> 0 | BD3: =+BC3-BF3 -> 0 | BE3: =((BC3-BD3)*$B3) -> 0 | BH3: =+BF3+BG3 -> 0 | BI3: =+BH3-BK3 -> 0 | BJ3: =((BH3-BI3)*$B3) -> 0
A4: CEPILLOS ANTI ENREDOS | B4: 6700 | F4: =+E4-H4 -> 0 | G4: =((E4-F4)*$B4) -> 0 | K4: =+J4-M4 -> 0 | L4: =((J4-K4)*$B4) -> 0 | P4: =+O4-R4 -> 0 | Q4: =((O4-P4)*$B4) -> 0 | U4: =+T4-W4 -> 0 | V4: =((T4-U4)*$B4) -> 0 | Z4: =+Y4-AB4 -> 0 | AA4: =((Y4-Z4)*$B4) -> 0 | AE4: =+AD4-AG4 -> -4 | AF4: =((AD4-AE4)*$B4) -> 26800 | AG4: 4 | AI4: =+AG4+AH4 -> 4 | AJ4: =+AI4-AL4 -> 0 | AK4: =((AI4-AJ4)*$B4) -> 26800 | AL4: 4 | AN4: =+AL4+AM4 -> 4 | AO4: =+AN4-AQ4 -> 0 | AP4: =((AN4-AO4)*$B4) -> 26800 | AQ4: 4 | AS4: =+AQ4+AR4 -> 4 | AT4: =+AS4-AV4 -> 4 | AU4: =((AS4-AT4)*$B4) -> 0 | AX4: =+AV4+AW4 -> 0 | AY4: =+AX4-BA4 -> 0 | AZ4: =((AX4-AY4)*$B4) -> 0 | BC4: =+BA4+BB4 -> 0 | BD4: =+BC4-BF4 -> 0 | BE4: =((BC4-BD4)*$B4) -> 0 | BH4: =+BF4+BG4 -> 0 | BI4: =+BH4-BK4 -> 0 | BJ4: =((BH4-BI4)*$B4) -> 0
A5: CEPILLOS DE BAMBU | B5: 8400 | AE5: =+AD5-AG5 -> 0 | AF5: =((AD5-AE5)*$B5) -> 0 | AG5: 0 | AI5: =+AG5+AH5 -> 0 | AJ5: =+AI5-AL5 -> 0 | AK5: =((AI5-AJ5)*$B5) -> 0 | AL5: 0 | AN5: =+AL5+AM5 -> 0 | AO5: =+AN5-AQ5 -> 0 | AP5: =((AN5-AO5)*$B5) -> 0 | AQ5: 0 | AS5: =+AQ5+AR5 -> 0 | AT5: =+AS5-AV5 -> 0 | AU5: =((AS5-AT5)*$B5) -> 0 | AX5: =+AV5+AW5 -> 0 | AY5: =+AX5-BA5 -> 0
A6: APLICADOR TÓNICO | B6: 2600 | AE6: =+AD6-AG6 -> -2 | AF6: =((AD6-AE6)*$B6) -> 5200 | AG6: 2 | AI6: =+AG6+AH6 -> 2 | AJ6: =+AI6-AL6 -> 0 | AK6: =((AI6-AJ6)*$B6) -> 5200 | AL6: 2 | AN6: =+AL6+AM6 -> 2 | AO6: =+AN6-AQ6 -> 0 | AP6: =((AN6-AO6)*$B6) -> 5200 | AQ6: 2 | AS6: =+AQ6+AR6 -> 2 | AT6: =+AS6-AV6 -> 2 | AU6: =((AS6-AT6)*$B6) -> 0 | AX6: =+AV6+AW6 -> 0 | AY6: =+AX6-BA6 -> 0
A7: CEPILLO ESQUELETO | B7: 7900 | AE7: =+AD7-AG7 -> -11 | AF7: =((AD7-AE7)*$B7) -> 86900 | AG7: 11 | AI7: =+AG7+AH7 -> 11 | AJ7: =+AI7-AL7 -> 0 | AK7: =((AI7-AJ7)*$B7) -> 86900 | AL7: 11 | AN7: =+AL7+AM7 -> 11 | AO7: =+AN7-AQ7 -> 0 | AP7: =((AN7-AO7)*$B7) -> 86900 | AQ7: 11 | AS7: =+AQ7+AR7 -> 11 | AT7: =+AS7-AV7 -> 11 | AU7: =((AS7-AT7)*$B7) -> 0 | AX7: =+AV7+AW7 -> 0 | AY7: =+AX7-BA7 -> 0
A8: CEPILLO CURLY | B8: 9000 | AE8: =+AD8-AG8 -> -12 | AF8: =((AD8-AE8)*$B8) -> 108000 | AG8: 12 | AI8: =+AG8+AH8 -> 12 | AJ8: =+AI8-AL8 -> 0 | AK8: =((AI8-AJ8)*$B8) -> 108000 | AL8: 12 | AN8: =+AL8+AM8 -> 12 | AO8: =+AN8-AQ8 -> 1 | AP8: =((AN8-AO8)*$B8) -> 99000 | AQ8: 11 | AS8: =+AQ8+AR8 -> 11 | AT8: =+AS8-AV8 -> 11 | AU8: =((AS8-AT8)*$B8) -> 0 | AX8: =+AV8+AW8 -> 0 | AY8: =+AX8-BA8 -> 0
A9: CEPILLO CRESPOS PEQ | B9: 6000 | AE9: =+AD9-AG9 -> -6 | AF9: =((AD9-AE9)*$B9) -> 36000 | AG9: 6 | AI9: =+AG9+AH9 -> 6 | AJ9: =+AI9-AL9 -> 0 | AK9: =((AI9-AJ9)*$B9) -> 36000 | AL9: 6 | AN9: =+AL9+AM9 -> 6 | AO9: =+AN9-AQ9 -> 0 | AP9: =((AN9-AO9)*$B9) -> 36000 | AQ9: 6 | AS9: =+AQ9+AR9 -> 6 | AT9: =+AS9-AV9 -> 6 | AU9: =((AS9-AT9)*$B9) -> 0 | AX9: =+AV9+AW9 -> 0 | AY9: =+AX9-BA9 -> 0
A10: CEPILLO GOTA DESENREDANTE | B10: 6000 | AE10: =+AD10-AG10 -> -12 | AF10: =((AD10-AE10)*$B10) -> 72000 | AG10: 12 | AI10: =+AG10+AH10 -> 12 | AJ10: =+AI10-AL10 -> 0 | AK10: =((AI10-AJ10)*$B10) -> 72000 | AL10: 12 | AN10: =+AL10+AM10 -> 12 | AO10: =+AN10-AQ10 -> 1 | AP10: =((AN10-AO10)*$B10) -> 66000 | AQ10: 11 | AS10: =+AQ10+AR10 -> 11 | AT10: =+AS10-AV10 -> 11 | AU10: =((AS10-AT10)*$B10) -> 0 | AX10: =+AV10+AW10 -> 0 | AY10: =+AX10-BA10 -> 0
A11: CEPILLO LABEATY PROFESIONAL | B11: 44000 | AM11: 6 | AN11: =+AL11+AM11 -> 6 | AO11: =+AN11-AQ11 -> 4 | AP11: =((AN11-AO11)*$B11) -> 88000 | AQ11: 2 | AS11: =+AQ11+AR11 -> 2 | AT11: =+AS11-AV11 -> 2 | AU11: =((AS11-AT11)*$B11) -> 0
A12: CEPILLO PLANCHA | B12: 22950 | AE12: =+AD12-AG12 -> -4 | AF12: =((AD12-AE12)*$B12) -> 91800 | AG12: 4 | AI12: =+AG12+AH12 -> 4 | AJ12: =+AI12-AL12 -> 0 | AK12: =((AI12-AJ12)*$B12) -> 91800 | AL12: 4 | AN12: =+AL12+AM12 -> 4 | AO12: =+AN12-AQ12 -> 0 | AP12: =((AN12-AO12)*$B12) -> 91800 | AQ12: 4 | AS12: =+AQ12+AR12 -> 4 | AT12: =+AS12-AV12 -> 4 | AU12: =((AS12-AT12)*$B12) -> 0 | AX12: =+AV12+AW12 -> 0 | AY12: =+AX12-BA12 -> 0
G13: =+SUM(G3:G12) -> 0 | L13: =+SUM(L3:L12) -> 0 | Q13: =+SUM(Q3:Q12) -> 0 | V13: =+SUM(V3:V12) -> 0 | AA13: =+SUM(AA3:AA12) -> 0 | AF13: =+SUM(AF3:AF12) -> 586300 | AK13: =+SUM(AK3:AK12) -> 586300 | AP13: =+SUM(AP3:AP12) -> 651700 | AU13: =+SUM(AU3:AU12) -> 0 | AZ13: =+SUM(AZ3:AZ12) -> 0 | BE13: =+SUM(BE3:BE12) -> 0 | BJ13: =+SUM(BJ3:BJ12) -> 0

Sheet LB
A1: TRATAMIENTOS LB | C1: ENERO | H1: FEBRERO | M1: MARZO | R1: ABRIL | W1: MAYO | AB1: JUNIO | AG1: JULIO | AL1: AGOSTO | AQ1: SEPTIEMBRE | AV1: OCTUBRE | BA1: NOVIEMBRE | BF1: DICIEMBRE | BK1: ENERO
A2: PRODUCTO | B2: VR. COMPRA | C2: INV.I | D2: Entra | E2: Saldo | F2: SALIDA | G2: TOTAL | H2: INV.I | I2: Entra | J2: Saldo | K2: SALIDA | L2: TOTAL | M2: INV.I | N2: Entra | O2: Saldo | P2: SALIDA | Q2: TOTAL | R2: INV.I | S2: Entra | T2: Saldo | U2: SALIDA | V2: TOTAL | W2: INV.I | X2: Entra | Y2: Saldo | Z2: SALIDA | AA2: TOTAL | AB2: INV.I | AC2: Entra | AD2: Saldo | AE2: SALIDA | AF2: TOTAL | AG2: INV.I | AH2: Entra | AI2: Saldo | AJ2: SALIDA | AK2: TOTAL | AL2: INV.I | AM2: Entra | AN2: Saldo | AO2: SALIDA | AP2: TOTAL | AQ2: INV.I | AR2: Entra | AS2: Saldo | AT2: SALIDA | AU2: TOTAL | AV2: INV.I | AW2: Entra | AX2: Saldo | AY2: SALIDA | AZ2: TOTAL | BA2: INV.I | BB2: Entra | BC2: Saldo | BD2: SALIDA | BE2: TOTAL | BF2: INV.I | BG2: Entra | BH2: Saldo | BI2: SALIDA | BJ2: TOTAL | BK2: INV.I
A3: TÓNICO FACIAL | B3: 21000 | F3: =+E3-H3 -> 0 | G3: =((E3-F3)*$B3) -> 0 | K3: =+J3-M3 -> 0 | L3: =((J3-K3)*$B3) -> 0 | P3: =+O3-R3 -> 0 | Q3: =((O3-P3)*$B3) -> 0 | U3: =+T3-W3 -> 0 | V3: =((T3-U3)*$B3) -> 0 | Z3: =+Y3-AB3 -> 0 | AA3: =((Y3-Z3)*$B3) -> 0 | AE3: =+AD3-AG3 -> -18 | AF3: =((AD3-AE3)*$B3) -> 378000 | AG3: 18 | AI3: =+AG3+AH3 -> 18 | AJ3: =+AI3-AL3 -> 1 | AK3: =((AI3-AJ3)*$B3) -> 357000 | AL3: 17 | AN3: =+AL3+AM3 -> 17 | AO3: =+AN3-AQ3 -> 7 | AP3: =((AN3-AO3)*$B3) -> 210000 | AQ3: 10 | AS3: =+AQ3+AR3 -> 10 | AT3: =+AS3-AV3 -> 10 | AU3: =((AS3-AT3)*$B3) -> 0 | AX3: =+AV3+AW3 -> 0 | AY3: =+AX3-BA3 -> 0 | AZ3: =((AX3-AY3)*$B3) -> 0 | BC3: =+BA3+BB3 -> 0 | BD3: =+BC3-BF3 -> 0 | BE3: =((BC3-BD3)*$B3) -> 0 | BH3: =+BF3+BG3 -> 0 | BI3: =+BH3-BK3 -> 0 | BJ3: =((BH3-BI3)*$B3) -> 0
A4: GEL INTIMO | B4: 28000 | F4: =+E4-H4 -> 0 | G4: =((E4-F4)*$B4) -> 0 | K4: =+J4-M4 -> 0 | L4: =((J4-K4)*$B4) -> 0 | P4: =+O4-R4 -> 0 | Q4: =((O4-P4)*$B4) -> 0 | U4: =+T4-W4 -> 0 | V4: =((T4-U4)*$B4) -> 0 | Z4: =+Y4-AB4 -> 0 | AA4: =((Y4-Z4)*$B4) -> 0 | AE4: =+AD4-AG4 -> -16 | AF4: =((AD4-AE4)*$B4) -> 448000 | AG4: 16 | AI4: =+AG4+AH4 -> 16 | AJ4: =+AI4-AL4 -> 0 | AK4: =((AI4-AJ4)*$B4) -> 448000 | AL4: 16 | AN4: =+AL4+AM4 -> 16 | AO4: =+AN4-AQ4 -> 1 | AP4: =((AN4-AO4)*$B4) -> 420000 | AQ4: 15 | AS4: =+AQ4+AR4 -> 15 | AT4: =+AS4-AV4 -> 15 | AU4: =((AS4-AT4)*$B4) -> 0 | AX4: =+AV4+AW4 -> 0 | AY4: =+AX4-BA4 -> 0 | AZ4: =((AX4-AY4)*$B4) -> 0 | BC4: =+BA4+BB4 -> 0 | BD4: =+BC4-BF4 -> 0 | BE4: =((BC4-BD4)*$B4) -> 0 | BH4: =+BF4+BG4 -> 0 | BI4: =+BH4-BK4 -> 0 | BJ4: =((BH4-BI4)*$B4) -> 0
A5: ÁCIDO HIALURÓNICO | B5: 24000 | AE5: =+AD5-AG5 -> -8 | AF5: =((AD5-AE5)*$B5) -> 192000 | AG5: 8 | AI5: =+AG5+AH5 -> 8 | AJ5: =+AI5-AL5 -> 1 | AK5: =((AI5-AJ5)*$B5) -> 168000 | AL5: 7 | AN5: =+AL5+AM5 -> 7 | AO5: =+AN5-AQ5 -> 0 | AP5: =((AN5-AO5)*$B5) -> 168000 | AQ5: 7 | AS5: =+AQ5+AR5 -> 7 | AT5: =+AS5-AV5 -> 7 | AU5: =((AS5-AT5)*$B5) -> 0
A6: PANTALLA SOLAR | B6: 19000 | AE6: =+AD6-AG6 -> -1 | AF6: =((AD6-AE6)*$B6) -> 19000 | AG6: 1 | AI6: =+AG6+AH6 -> 1 | AJ6: =+AI6-AL6 -> 0 | AK6: =((AI6-AJ6)*$B6) -> 19000 | AL6: 1 | AN6: =+AL6+AM6 -> 1 | AO6: =+AN6-AQ6 -> 0 | AP6: =((AN6-AO6)*$B6) -> 19000 | AQ6: 1 | AS6: =+AQ6+AR6 -> 1 | AT6: =+AS6-AV6 -> 1 | AU6: =((AS6-AT6)*$B6) -> 0
A7: DESODORANTE ACLARANTE | B7: 21000 | AE7: =+AD7-AG7 -> -4 | AF7: =((AD7-AE7)*$B7) -> 84000 | AG7: 4 | AI7: =+AG7+AH7 -> 4 | AJ7: =+AI7-AL7 -> 0 | AK7: =((AI7-AJ7)*$B7) -> 84000 | AL7: 4 | AN7: =+AL7+AM7 -> 4 | AO7: =+AN7-AQ7 -> 0 | AP7: =((AN7-AO7)*$B7) -> 84000 | AQ7: 4 | AS7: =+AQ7+AR7 -> 4 | AT7: =+AS7-AV7 -> 4 | AU7: =((AS7-AT7)*$B7) -> 0
G8: =+SUM(G3:G7) -> 0 | L8: =+SUM(L3:L7) -> 0 | Q8: =+SUM(Q3:Q7) -> 0 | V8: =+SUM(V3:V7) -> 0 | AA8: =+SUM(AA3:AA7) -> 0 | AF8: =+SUM(AF3:AF7) -> 1121000 | AK8: =+SUM(AK3:AK7) -> 1076000 | AP8: =+SUM(AP3:AP7) -> 901000 | AU8: =+SUM(AU3:AU7) -> 0 | AZ8: =+SUM(AZ3:AZ7) -> 0 | BE8: =+SUM(BE3:BE7) -> 0 | BJ8: =+SUM(BJ3:BJ7) -> 0

Sheet ML
A1: MILAGROS | C1: ENERO | H1: FEBRERO | M1: MARZO | R1: ABRIL | W1: MAYO | AB1: JUNIO | AG1: JULIO | AL1: AGOSTO | AQ1: SEPTIEMBRE | AV1: OCTUBRE | BA1: NOVIEMBRE | BF1: DICIEMBRE | BK1: ENERO
A2: PRODUCTO | B2: VR. COMPRA | C2: INV.I | D2: Entra | E2: Saldo | F2: SALIDA | G2: TOTAL | H2: INV.I | I2: Entra | J2: Saldo | K2: SALIDA | L2: TOTAL | M2: INV.I | N2: Entra | O2: Saldo | P2: SALIDA | Q2: TOTAL | R2: INV.I | S2: Entra | T2: Saldo | U2: SALIDA | V2: TOTAL | W2: INV.I | X2: Entra | Y2: Saldo | Z2: SALIDA | AA2: TOTAL | AB2: INV.I | AC2: Entra | AD2: Saldo | AE2: SALIDA | AF2: TOTAL | AG2: INV.I | AH2: Entra | AI2: Saldo | AJ2: SALIDA | AK2: TOTAL | AL2: INV.I | AM2: Entra | AN2: Saldo | AO2: SALIDA | AP2: TOTAL | AQ2: INV.I | AR2: Entra | AS2: Saldo | AT2: SALIDA | AU2: TOTAL | AV2: INV.I | AW2: Entra | AX2: Saldo | AY2: SALIDA | AZ2: TOTAL | BA2: INV.I | BB2: Entra | BC2: Saldo | BD2: SALIDA | BE2: TOTAL | BF2: INV.I | BG2: Entra | BH2: Saldo | BI2: SALIDA | BJ2: TOTAL | BK2: INV.I
A3: SH. ARROZ | B3: 20000 | AD3: =+AB3+AC3 -> 0 | AE3: =+AD3-AG3 -> -18 | AF3: =((AD3-AE3)*$B3) -> 360000 | AG3: 18 | AI3: =+AG3+AH3 -> 18 | AJ3: =+AI3-AL3 -> 1 | AK3: =((AI3-AJ3)*$B3) -> 340000 | AL3: 17 | AN3: =+AL3+AM3 -> 17 | AO3: =+AN3-AQ3 -> 2 | AP3: =((AN3-AO3)*$B3) -> 300000 | AQ3: 15 | AS3: =+AQ3+AR3 -> 15 | AT3: =+AS3-AV3 -> 15 | AU3: =((AS3-AT3)*$B3) -> 0 | AX3: =+AV3+AW3 -> 0 | AY3: =+AX3-BA3 -> 0 | AZ3: =((AX3-AY3)*$B3) -> 0 | BC3: =+BA3+BB3 -> 0 | BD3: =+BC3-BF3 -> 0 | BE3: =((BC3-BD3)*$B3) -> 0 | BH3: =+BF3+BG3 -> 0 | BI3: =+BH3-BK3 -> 0 | BJ3: =((BH3-BI3)*$B3) -> 0
A4: AC. ARROZ | B4: 21000 | AD4: =+AB4+AC4 -> 0 | AE4: =+AD4-AG4 -> -18 | AF4: =((AD4-AE4)*$B4) -> 378000 | AG4: 18 | AI4: =+AG4+AH4 -> 18 | AJ4: =+AI4-AL4 -> 1 | AK4: =((AI4-AJ4)*$B4) -> 357000 | AL4: 17 | AN4: =+AL4+AM4 -> 17 | AO4: =+AN4-AQ4 -> 2 | AP4: =((AN4-AO4)*$B4) -> 315000 | AQ4: 15 | AS4: =+AQ4+AR4 -> 15 | AT4: =+AS4-AV4 -> 15 | AU4: =((AS4-AT4)*$B4) -> 0 | AX4: =+AV4+AW4 -> 0 | AY4: =+AX4-BA4 -> 0 | AZ4: =((AX4-AY4)*$B4) -> 0 | BC4: =+BA4+BB4 -> 0 | BD4: =+BC4-BF4 -> 0 | BE4: =((BC4-BD4)*$B4) -> 0 | BH4: =+BF4+BG4 -> 0 | BI4: =+BH4-BK4 -> 0 | BJ4: =((BH4-BI4)*$B4) -> 0
A5: SH. CEBOLLA | B5: 27989 | AD5: =+AB5+AC5 -> 0 | AE5: =+AD5-AG5 -> -35 | AF5: =((AD5-AE5)*$B5) -> 979615 | AG5: 35 | AI5: =+AG5+AH5 -> 35 | AJ5: =+AI5-AL5 -> 4 | AK5: =((AI5-AJ5)*$B5) -> 867659 | AL5: 31 | AN5: =+AL5+AM5 -> 31 | AO5: =+AN5-AQ5 -> 5 | AP5: =((AN5-AO5)*$B5) -> 727714 | AQ5: 26 | AS5: =+AQ5+AR5 -> 26 | AT5: =+AS5-AV5 -> 26 | AU5: =((AS5-AT5)*$B5) -> 0 | AX5: =+AV5+AW5 -> 0 | AY5: =+AX5-BA5 -> 0 | AZ5: =((AX5-AY5)*$B5) -> 0 | BC5: =+BA5+BB5 -> 0 | BD5: =+BC5-BF5 -> 0 | BE5: =((BC5-BD5)*$B5) -> 0 | BH5: =+BF5+BG5 -> 0 | BI5: =+BH5-BK5 -> 0 | BJ5: =((BH5-BI5)*$B5) -> 0
A6: AC.CEBOLLA | B6: 25873 | AD6: =+AB6+AC6 -> 0 | AE6: =+AD6-AG6 -> -17 | AF6: =((AD6-AE6)*$B6) -> 439841 | AG6: 17 | AI6: =+AG6+AH6 -> 17 | AJ6: =+AI6-AL6 -> 5 | AK6: =((AI6-AJ6)*$B6) -> 310476 | AL6: 12 | AN6: =+AL6+AM6 -> 12 | AO6: =+AN6-AQ6 -> 3 | AP6: =((AN6-AO6)*$B6) -> 232857 | AQ6: 9 | AR6: 30 | AS6: =+AQ6+AR6 -> 39 | AT6: =+AS6-AV6 -> 39 | AU6: =((AS6-AT6)*$B6) -> 0 | AX6: =+AV6+AW6 -> 0 | AY6: =+AX6-BA6 -> 0 | AZ6: =((AX6-AY6)*$B6) -> 0 | BC6: =+BA6+BB6 -> 0 | BD6: =+BC6-BF6 -> 0 | BE6: =((BC6-BD6)*$B6) -> 0 | BH6: =+BF6+BG6 -> 0 | BI6: =+BH6-BK6 -> 0 | BJ6: =((BH6-BI6)*$B6) -> 0
A7: SH. HERBAL | B7: 28600 | AD7: =+AB7+AC7 -> 0 | AE7: =+AD7-AG7 -> -10 | AF7: =((AD7-AE7)*$B7) -> 286000 | AG7: 10 | AI7: =+AG7+AH7 -> 10 | AJ7: =+AI7-AL7 -> 0 | AK7: =((AI7-AJ7)*$B9) -> 286000 | AL7: 10 | AN7: =+AL7+AM7 -> 10 | AO7: =+AN7-AQ7 -> 3 | AP7: =((AN7-AO7)*$B7) -> 200200 | AQ7: 7 | AS7: =+AQ7+AR7 -> 7 | AT7: =+AS7-AV7 -> 7 | AU7: =((AS7-AT7)*$B9) -> 0 | AX7: =+AV7+AW7 -> 0 | AY7: =+AX7-BA7 -> 0 | AZ7: =((AX7-AY7)*$B9) -> 0 | BC7: =+BA7+BB7 -> 0 | BD7: =+BC7-BF7 -> 0 | BE7: =((BC7-BD7)*$B9) -> 0 | BH7: =+BF7+BG7 -> 0 | BI7: =+BH7-BK7 -> 0 | BJ7: =((BH7-BI7)*$B9) -> 0
A8: AC. HERBAL | B8: 29000 | AD8: =+AB8+AC8 -> 0 | AE8: =+AD8-AG8 -> -8 | AF8: =((AD8-AE8)*$B8) -> 232000 | AG8: 8 | AI8: =+AG8+AH8 -> 8 | AJ8: =+AI8-AL8 -> 0 | AK8: =((AI8-AJ8)*$B10) -> 232000 | AL8: 8 | AN8: =+AL8+AM8 -> 8 | AO8: =+AN8-AQ8 -> 1 | AP8: =((AN8-AO8)*$B8) -> 203000 | AQ8: 7 | AS8: =+AQ8+AR8 -> 7 | AT8: =+AS8-AV8 -> 7 | AU8: =((AS8-AT8)*$B10) -> 0 | AX8: =+AV8+AW8 -> 0 | AY8: =+AX8-BA8 -> 0 | AZ8: =((AX8-AY8)*$B10) -> 0 | BC8: =+BA8+BB8 -> 0 | BD8: =+BC8-BF8 -> 0 | BE8: =((BC8-BD8)*$B10) -> 0 | BH8: =+BF8+BG8 -> 0 | BI8: =+BH8-BK8 -> 0 | BJ8: =((BH8-BI8)*$B10) -> 0
A9: SH. ULTRANUTRITIVO | B9: 28600 | AD9: =+AB9+AC9 -> 0 | AE9: =+AD9-AG9 -> -9 | AF9: =((AD9-AE9)*$B9) -> 257400 | AG9: 9 | AI9: =+AG9+AH9 -> 9 | AJ9: =+AI9-AL9 -> 0 | AK9: =((AI9-AJ9)*$B11) -> 257400 | AL9: 9 | AN9: =+AL9+AM9 -> 9 | AO9: =+AN9-AQ9 -> 2 | AP9: =((AN9-AO9)*$B9) -> 200200 | AQ9: 7 | AS9: =+AQ9+AR9 -> 7 | AT9: =+AS9-AV9 -> 7 | AU9: =((AS9-AT9)*$B11) -> 0 | AX9: =+AV9+AW9 -> 0 | AY9: =+AX9-BA9 -> 0 | AZ9: =((AX9-AY9)*$B11) -> 0 | BC9: =+BA9+BB9 -> 0 | BD9: =+BC9-BF9 -> 0 | BE9: =((BC9-BD9)*$B11) -> 0 | BH9: =+BF9+BG9 -> 0 | BI9: =+BH9-BK9 -> 0 | BJ9: =((BH9-BI9)*$B11) -> 0
A10: AC. ULTRANUTRITIVO | B10: 29000 | AD10: =+AB10+AC10 -> 0 | AE10: =+AD10-AG10 -> -5 | AF10: =((AD10-AE10)*$B10) -> 145000 | AG10: 5 | AI10: =+AG10+AH10 -> 5 | AJ10: =+AI10-AL10 -> 0 | AK10: =((AI10-AJ10)*$B12) -> 143000 | AL10: 5 | AN10: =+AL10+AM10 -> 5 | AO10: =+AN10-AQ10 -> 3 | AP10: =((AN10-AO10)*$B10) -> 58000 | AQ10: 2 | AR10: 6 | AS10: =+AQ10+AR10 -> 8 | AT10: =+AS10-AV10 -> 8 | AU10: =((AS10-AT10)*$B12) -> 0 | AX10: =+AV10+AW10 -> 0 | AY10: =+AX10-BA10 -> 0 | AZ10: =((AX10-AY10)*$B12) -> 0 | BC10: =+BA10+BB10 -> 0 | BD10: =+BC10-BF10 -> 0 | BE10: =((BC10-BD10)*$B12) -> 0 | BH10: =+BF10+BG10 -> 0 | BI10: =+BH10-BK10 -> 0 | BJ10: =((BH10-BI10)*$B12) -> 0
A11: SH. EMERGENCIA CAPILAR | B11: 28600 | AD11: =+AB11+AC11 -> 0 | AE11: =+AD11-AG11 -> -9 | AF11: =((AD11-AE11)*$B11) -> 257400 | AG11: 9 | AI11: =+AG11+AH11 -> 9 | AJ11: =+AI11-AL11 -> 0 | AK11: =((AI11-AJ11)*$B13) -> 210078 | AL11: 9 | AN11: =+AL11+AM11 -> 9 | AO11: =+AN11-AQ11 -> 0 | AP11: =((AN11-AO11)*$B11) -> 257400 | AQ11: 9 | AS11: =+AQ11+AR11 -> 9 | AT11: =+AS11-AV11 -> 9 | AU11: =((AS11-AT11)*$B13) -> 0 | AX11: =+AV11+AW11 -> 0 | AY11: =+AX11-BA11 -> 0 | AZ11: =((AX11-AY11)*$B13) -> 0 | BC11: =+BA11+BB11 -> 0 | BD11: =+BC11-BF11 -> 0 | BE11: =((BC11-BD11)*$B13) -> 0 | BH11: =+BF11+BG11 -> 0 | BI11: =+BH11-BK11 -> 0 | BJ11: =((BH11-BI11)*$B13) -> 0
A12: SH. MAGÍA CAPILAR | B12: 28600 | AD12: =+AB12+AC12 -> 0 | AE12: =+AD12-AG12 -> -9 | AF12: =((AD12-AE12)*$B12) -> 257400 | AG12: 9 | AI12: =+AG12+AH12 -> 9 | AJ12: =+AI12-AL12 -> 0 | AK12: =((AI12-AJ12)*$B14) -> 257400 | AL12: 9 | AN12: =+AL12+AM12 -> 9 | AO12: =+AN12-AQ12 -> 0 | AP12: =((AN12-AO12)*$B12) -> 257400 | AQ12: 9 | AS12: =+AQ12+AR12 -> 9 | AT12: =+AS12-AV12 -> 9 | AU12: =((AS12-AT12)*$B14) -> 0 | AX12: =+AV12+AW12 -> 0 | AY12: =+AX12-BA12 -> 0 | AZ12: =((AX12-AY12)*$B14) -> 0 | BC12: =+BA12+BB12 -> 0 | BD12: =+BC12-BF12 -> 0 | BE12: =((BC12-BD12)*$B14) -> 0 | BH12: =+BF12+BG12 -> 0 | BI12: =+BH12-BK12 -> 0 | BJ12: =((BH12-BI12)*$B14) -> 0
A13: SH. KIDS | B13: 23342 | AD13: =+AB13+AC13 -> 0 | AE13: =+AD13-AG13 -> -27 | AF13: =((AD13-AE13)*$B13) -> 630234 | AG13: 27 | AI13: =+AG13+AH13 -> 27 | AJ13: =+AI13-AL13 -> 0 | AK13: =((AI13-AJ13)*$B16) -> 729000 | AL13: 27 | AN13: =+AL13+AM13 -> 27 | AO13: =+AN13-AQ13 -> 0 | AP13: =((AN13-AO13)*$B13) -> 630234 | AQ13: 27 | AS13: =+AQ13+AR13 -> 27 | AT13: =+AS13-AV13 -> 27 | AU13: =((AS13-AT13)*$B16) -> 0 | AX13: =+AV13+AW13 -> 0 | AY13: =+AX13-BA13 -> 0 | AZ13: =((AX13-AY13)*$B16) -> 0 | BC13: =+BA13+BB13 -> 0 | BD13: =+BC13-BF13 -> 0 | BE13: =((BC13-BD13)*$B16) -> 0 | BH13: =+BF13+BG13 -> 0 | BI13: =+BH13-BK13 -> 0 | BJ13: =((BH13-BI13)*$B16) -> 0
A14: SH. ANTI CASPA | B14: 28600 | AD14: =+AB14+AC14 -> 0 | AE14: =+AD14-AG14 -> -10 | AF14: =((AD14-AE14)*$B14) -> 286000 | AG14: 10 | AI14: =+AG14+AH14 -> 10 | AJ14: =+AI14-AL14 -> 0 | AK14: =((AI14-AJ14)*$B17) -> 286000 | AL14: 10 | AN14: =+AL14+AM14 -> 10 | AO14: =+AN14-AQ14 -> 1 | AP14: =((AN14-AO14)*$B14) -> 257400 | AQ14: 9 | AS14: =+AQ14+AR14 -> 9 | AT14: =+AS14-AV14 -> 9 | AU14: =((AS14-AT14)*$B17) -> 0 | AX14: =+AV14+AW14 -> 0 | AY14: =+AX14-BA14 -> 0 | AZ14: =((AX14-AY14)*$B17) -> 0 | BC14: =+BA14+BB14 -> 0 | BD14: =+BC14-BF14 -> 0 | BE14: =((BC14-BD14)*$B17) -> 0 | BH14: =+BF14+BG14 -> 0 | BI14: =+BH14-BK14 -> 0 | BJ14: =((BH14-BI14)*$B17) -> 0
A15: SH. EXFOLIANTE PRIME | B15: 23746 | AR15: 30 | AS15: =+AQ15+AR15 -> 30 | AT15: =+AS15-AV15 -> 30 | AU15: =((AS15-AT15)*$B18) -> 0
A16: SH. EXFOLIANTE | B16: 27000 | AD16: =+AB16+AC16 -> 0 | AE16: =+AD16-AG16 -> -8 | AF16: =((AD16-AE16)*$B16) -> 216000 | AG16: 8 | AI16: =+AG16+AH16 -> 8 | AJ16: =+AI16-AL16 -> 0 | AK16: =((AI16-AJ16)*$B19) -> 480000 | AL16: 8 | AN16: =+AL16+AM16 -> 8 | AO16: =+AN16-AQ16 -> 0 | AP16: =((AN16-AO16)*$B16) -> 216000 | AQ16: 8 | AS16: =+AQ16+AR16 -> 8 | AT16: =+AS16-AV16 -> 8 | AU16: =((AS16-AT16)*$B19) -> 0 | AX16: =+AV16+AW16 -> 0 | AY16: =+AX16-BA16 -> 0 | AZ16: =((AX16-AY16)*$B19) -> 0 | BC16: =+BA16+BB16 -> 0 | BD16: =+BC16-BF16 -> 0 | BE16: =((BC16-BD16)*$B19) -> 0 | BH16: =+BF16+BG16 -> 0 | BI16: =+BH16-BK16 -> 0 | BJ16: =((BH16-BI16)*$B19) -> 0
A17: SH. BIO REPOLARIZADOR | B17: 28600 | AD17: =+AB17+AC17 -> 0 | AE17: =+AD17-AG17 -> -6 | AF17: =((AD17-AE17)*$B17) -> 171600 | AG17: 6 | AI17: =+AG17+AH17 -> 6 | AJ17: =+AI17-AL17 -> 0 | AK17: =((AI17-AJ17)*$B20) -> 174000 | AL17: 6 | AN17: =+AL17+AM17 -> 6 | AO17: =+AN17-AQ17 -> 0 | AP17: =((AN17-AO17)*$B17) -> 171600 | AQ17: 6 | AS17: =+AQ17+AR17 -> 6 | AT17: =+AS17-AV17 -> 6 | AU17: =((AS17-AT17)*$B20) -> 0 | AX17: =+AV17+AW17 -> 0 | AY17: =+AX17-BA17 -> 0 | AZ17: =((AX17-AY17)*$B20) -> 0 | BC17: =+BA17+BB17 -> 0 | BD17: =+BC17-BF17 -> 0 | BE17: =((BC17-BD17)*$B20) -> 0 | BH17: =+BF17+BG17 -> 0 | BI17: =+BH17-BK17 -> 0 | BJ17: =((BH17-BI17)*$B20) -> 0
A18: BIO REPOLARIZADOR LITRO | B18: 45000 | AD18: =+AB18+AC18 -> 0 | AE18: =+AD18-AG18 -> -6 | AF18: =((AD18-AE18)*$B18) -> 270000 | AG18: 6 | AI18: =+AG18+AH18 -> 6 | AJ18: =+AI18-AL18 -> 2 | AK18: =((AI18-AJ18)*$B21) -> 116000 | AL18: 4 | AN18: =+AL18+AM18 -> 4 | AO18: =+AN18-AQ18 -> 1 | AP18: =((AN18-AO18)*$B18) -> 135000 | AQ18: 3 | AS18: =+AQ18+AR18 -> 3 | AT18: =+AS18-AV18 -> 3 | AU18: =((AS18-AT18)*$B21) -> 0 | AX18: =+AV18+AW18 -> 0 | AY18: =+AX18-BA18 -> 0 | AZ18: =((AX18-AY18)*$B21) -> 0 | BC18: =+BA18+BB18 -> 0 | BD18: =+BC18-BF18 -> 0 | BE18: =((BC18-BD18)*$B21) -> 0 | BH18: =+BF18+BG18 -> 0 | BI18: =+BH18-BK18 -> 0 | BJ18: =((BH18-BI18)*$B21) -> 0
A19: SH. ARROZ LITRO | B19: 60000 | AD19: =+AB19+AC19 -> 0 | AE19: =+AD19-AG19 -> -1 | AF19: =((AD19-AE19)*$B19) -> 60000 | AG19: 1 | AI19: =+AG19+AH19 -> 1 | AJ19: =+AI19-AL19 -> 0 | AK19: =((AI19-AJ19)*$B22) -> 23577 | AL19: 1 | AN19: =+AL19+AM19 -> 1 | AO19: =+AN19-AQ19 -> 0 | AP19: =((AN19-AO19)*$B19) -> 60000 | AQ19: 1 | AS19: =+AQ19+AR19 -> 1 | AT19: =+AS19-AV19 -> 1 | AU19: =((AS19-AT19)*$B22) -> 0 | AX19: =+AV19+AW19 -> 0 | AY19: =+AX19-BA19 -> 0 | AZ19: =((AX19-AY19)*#REF!) -> #REF! | BC19: =+BA19+BB19 -> 0 | BD19: =+BC19-BF19 -> 0 | BE19: =((BC19-BD19)*#REF!) -> #REF! | BH19: =+BF19+BG19 -> 0 | BI19: =+BH19-BK19 -> 0 | BJ19: =((BH19-BI19)*#REF!) -> #REF!
A20: BIO REPOLARIZADOR PEQ | B20: 29000 | AD20: =+AB20+AC20 -> 0 | AE20: =+AD20-AG20 -> -9 | AF20: =((AD20-AE20)*$B20) -> 261000 | AG20: 9 | AI20: =+AG20+AH20 -> 9 | AJ20: =+AI20-AL20 -> 2 | AK20: =((AI20-AJ20)*$B23) -> 203000 | AL20: 7 | AN20: =+AL20+AM20 -> 7 | AO20: =+AN20-AQ20 -> 2 | AP20: =((AN20-AO20)*$B20) -> 145000 | AQ20: 5 | AR20: 6 | AS20: =+AQ20+AR20 -> 11 | AT20: =+AS20-AV20 -> 11 | AU20: =((AS20-AT20)*$B23) -> 0 | AX20: =+AV20+AW20 -> 0 | AY20: =+AX20-BA20 -> 0 | AZ20: =((AX20-AY20)*#REF!) -> #REF! | BC20: =+BA20+BB20 -> 0 | BD20: =+BC20-BF20 -> 0 | BE20: =((BC20-BD20)*#REF!) -> #REF! | BH20: =+BF20+BG20 -> 0 | BI20: =+BH20-BK20 -> 0 | BJ20: =((BH20-BI20)*#REF!) -> #REF!
A21: TRATAMIENTO RIZOS | B21: 29000 | AD21: =+AB21+AC21 -> 0 | AE21: =+AD21-AG21 -> -10 | AF21: =((AD21-AE21)*$B21) -> 290000 | AG21: 10 | AI21: =+AG21+AH21 -> 10 | AJ21: =+AI21-AL21 -> 4 | AK21: =((AI21-AJ21)*$B24) -> 174000 | AL21: 6 | AN21: =+AL21+AM21 -> 6 | AO21: =+AN21-AQ21 -> -4 | AP21: =((AN21-AO21)*$B21) -> 290000 | AQ21: 10 | AS21: =+AQ21+AR21 -> 10 | AT21: =+AS21-AV21 -> 10 | AU21: =((AS21-AT21)*$B24) -> 0 | AX21: =+AV21+AW21 -> 0 | AY21: =+AX21-BA21 -> 0 | AZ21: =((AX21-AY21)*#REF!) -> #REF! | BC21: =+BA21+BB21 -> 0 | BD21: =+BC21-BF21 -> 0 | BE21: =((BC21-BD21)*#REF!) -> #REF! | BH21: =+BF21+BG21 -> 0 | BI21: =+BH21-BK21 -> 0 | BJ21: =((BH21-BI21)*#REF!) -> #REF!
A22: TRATAMIENTO DE FRUTAS | B22: 23577 | AD22: =+AB22+AC22 -> 0 | AE22: =+AD22-AG22 -> -31 | AF22: =((AD22-AE22)*$B22) -> 730887 | AG22: 31 | AI22: =+AG22+AH22 -> 31 | AJ22: =+AI22-AL22 -> 3 | AK22: =((AI22-AJ22)*$B25) -> 616000 | AL22: 28 | AN22: =+AL22+AM22 -> 28 | AO22: =+AN22-AQ22 -> 1 | AP22: =((AN22-AO22)*$B22) -> 636579 | AQ22: 27 | AS22: =+AQ22+AR22 -> 27 | AT22: =+AS22-AV22 -> 27 | AU22: =((AS22-AT22)*$B25) -> 0 | AX22: =+AV22+AW22 -> 0 | AY22: =+AX22-BA22 -> 0 | AZ22: =((AX22-AY22)*$B22) -> 0 | BC22: =+BA22+BB22 -> 0 | BD22: =+BC22-BF22 -> 0 | BE22: =((BC22-BD22)*$B22) -> 0 | BH22: =+BF22+BG22 -> 0 | BI22: =+BH22-BK22 -> 0 | BJ22: =((BH22-BI22)*$B22) -> 0
A23: TRATAMIENTO EMERGENCIA | B23: 29000 | AD23: =+AB23+AC23 -> 0 | AE23: =+AD23-AG23 -> -8 | AF23: =((AD23-AE23)*$B23) -> 232000 | AG23: 8 | AI23: =+AG23+AH23 -> 8 | AJ23: =+AI23-AL23 -> 1 | AK23: =((AI23-AJ23)*$B26) -> 189000 | AL23: 7 | AN23: =+AL23+AM23 -> 7 | AO23: =+AN23-AQ23 -> 0 | AP23: =((AN23-AO23)*$B23) -> 203000 | AQ23: 7 | AS23: =+AQ23+AR23 -> 7 | AT23: =+AS23-AV23 -> 7 | AU23: =((AS23-AT23)*$B26) -> 0 | AX23: =+AV23+AW23 -> 0 | AY23: =+AX23-BA23 -> 0 | AZ23: =((AX23-AY23)*$B23) -> 0 | BC23: =+BA23+BB23 -> 0 | BD23: =+BC23-BF23 -> 0 | BE23: =((BC23-BD23)*$B23) -> 0 | BH23: =+BF23+BG23 -> 0 | BI23: =+BH23-BK23 -> 0 | BJ23: =((BH23-BI23)*$B23) -> 0
A24: TRATAMIENTO MAGIA | B24: 29000 | AD24: =+AB24+AC24 -> 0 | AE24: =+AD24-AG24 -> -6 | AF24: =((AD24-AE24)*$B24) -> 174000 | AG24: 6 | AI24: =+AG24+AH24 -> 6 | AJ24: =+AI24-AL24 -> 0 | AK24: =((AI24-AJ24)*$B27) -> 175212 | AL24: 6 | AN24: =+AL24+AM24 -> 6 | AO24: =+AN24-AQ24 -> 0 | AP24: =((AN24-AO24)*$B24) -> 174000 | AQ24: 6 | AS24: =+AQ24+AR24 -> 6 | AT24: =+AS24-AV24 -> 6 | AU24: =((AS24-AT24)*$B27) -> 0 | AX24: =+AV24+AW24 -> 0 | AY24: =+AX24-BA24 -> 0 | AZ24: =((AX24-AY24)*$B24) -> 0 | BC24: =+BA24+BB24 -> 0 | BD24: =+BC24-BF24 -> 0 | BE24: =((BC24-BD24)*$B24) -> 0 | BH24: =+BF24+BG24 -> 0 | BI24: =+BH24-BK24 -> 0 | BJ24: =((BH24-BI24)*$B24) -> 0
A25: DESENREDANTE MARTINA | B25: 22000 | AE25: =+AD25-AG25 -> -16 | AF25: =((AD25-AE25)*$B25) -> 352000 | AG25: 16 | AI25: =+AG25+AH25 -> 16 | AJ25: =+AI25-AL25 -> 0 | AK25: =((AI25-AJ25)*$B28) -> 800000 | AL25: 16 | AN25: =+AL25+AM25 -> 16 | AO25: =+AN25-AQ25 -> 4 | AP25: =((AN25-AO25)*$B25) -> 264000 | AQ25: 12 | AS25: =+AQ25+AR25 -> 12 | AT25: =+AS25-AV25 -> 12 | AU25: =((AS25-AT25)*$B28) -> 0
A26: DESENREDANTE MORADO/GOLD | B26: 27000 | AE26: =+AD26-AG26 -> -16 | AF26: =((AD26-AE26)*$B26) -> 432000 | AG26: 16 | AI26: =+AG26+AH26 -> 16 | AJ26: =+AI26-AL26 -> 4 | AK26: =((AI26-AJ26)*$B29) -> 306000 | AL26: 12 | AN26: =+AL26+AM26 -> 12 | AO26: =+AN26-AQ26 -> 2 | AP26: =((AN26-AO26)*$B26) -> 270000 | AQ26: 10 | AS26: =+AQ26+AR26 -> 10 | AT26: =+AS26-AV26 -> 10 | AU26: =((AS26-AT26)*$B29) -> 0
A27: TRATAMIENTO DE PESTAÑAS | B27: 29202 | AE27: =+AD27-AG27 -> -6 | AF27: =((AD27-AE27)*$B27) -> 175212 | AG27: 6 | AI27: =+AG27+AH27 -> 6 | AJ27: =+AI27-AL27 -> 0 | AK27: =((AI27-AJ27)*$B30) -> 264000 | AL27: 6 | AN27: =+AL27+AM27 -> 6 | AO27: =+AN27-AQ27 -> 0 | AP27: =((AN27-AO27)*$B27) -> 175212 | AQ27: 6 | AR27: 24 | AS27: =+AQ27+AR27 -> 30 | AT27: =+AS27-AV27 -> 30 | AU27: =((AS27-AT27)*$B30) -> 0
A28: BLOQUEADOR CON Y SIN COLOR | B28: 50000 | AE28: =+AD28-AG28 -> -5 | AF28: =((AD28-AE28)*$B28) -> 250000 | AG28: 5 | AI28: =+AG28+AH28 -> 5 | AJ28: =+AI28-AL28 -> 0 | AK28: =((AI28-AJ28)*$B31) -> 136490 | AL28: 5 | AN28: =+AL28+AM28 -> 5 | AO28: =+AN28-AQ28 -> 1 | AP28: =((AN28-AO28)*$B28) -> 200000 | AQ28: 4 | AS28: =+AQ28+AR28 -> 4 | AT28: =+AS28-AV28 -> 4 | AU28: =((AS28-AT28)*$B31) -> 0
A29: GOTAS MILAGROS | B29: 25500 | AE29: =+AD29-AG29 -> -9 | AF29: =((AD29-AE29)*$B29) -> 229500 | AG29: 9 | AI29: =+AG29+AH29 -> 9 | AJ29: =+AI29-AL29 -> 7 | AK29: =((AI29-AJ29)*$B32) -> 60000 | AL29: 2 | AM29: 12 | AN29: =+AL29+AM29 -> 14 | AO29: =+AN29-AQ29 -> 0 | AP29: =((AN29-AO29)*$B29) -> 357000 | AQ29: 14 | AS29: =+AQ29+AR29 -> 14 | AT29: =+AS29-AV29 -> 14 | AU29: =((AS29-AT29)*$B32) -> 0
A30: MASCARILLA DE PROTEÍNA | B30: 44000 | AE30: =+AD30-AG30 -> -24 | AF30: =((AD30-AE30)*$B30) -> 1056000 | AG30: 24 | AI30: =+AG30+AH30 -> 24 | AJ30: =+AI30-AL30 -> 2 | AK30: =((AI30-AJ30)*$B33) -> 379214 | AL30: 22 | AN30: =+AL30+AM30 -> 22 | AO30: =+AN30-AQ30 -> 2 | AP30: =((AN30-AO30)*$B30) -> 880000 | AQ30: 20 | AS30: =+AQ30+AR30 -> 20 | AT30: =+AS30-AV30 -> 20 | AU30: =((AS30-AT30)*$B33) -> 0
A31: MASCARILLA DE CEBOLLA | B31: 27298 | AE31: =+AD31-AG31 -> -26 | AF31: =((AD31-AE31)*$B31) -> 709748 | AG31: 26 | AI31: =+AG31+AH31 -> 26 | AJ31: =+AI31-AL31 -> 4 | AK31: =((AI31-AJ31)*$B34) -> 594000 | AL31: 22 | AN31: =+AL31+AM31 -> 22 | AO31: =+AN31-AQ31 -> 6 | AP31: =((AN31-AO31)*$B31) -> 436768 | AQ31: 16 | AS31: =+AQ31+AR31 -> 16 | AT31: =+AS31-AV31 -> 16 | AU31: =((AS31-AT31)*$B34) -> 0
A32: MASCARILLA MULTIVITAMINICA | B32: 30000 | AE32: =+AD32-AG32 -> 0 | AF32: =((AD32-AE32)*$B32) -> 0 | AG32: 0 | AH32: 1 | AI32: =+AG32+AH32 -> 1 | AJ32: =+AI32-AL32 -> 1 | AK32: =((AI32-AJ32)*$B35) -> 0 | AL32: 0 | AN32: =+AL32+AM32 -> 0 | AO32: =+AN32-AQ32 -> 0 | AP32: =((AN32-AO32)*$B32) -> 0 | AQ32: 0 | AS32: =+AQ32+AR32 -> 0 | AT32: =+AS32-AV32 -> 0 | AU32: =((AS32-AT32)*$B35) -> 0
A33: PERFUMES MARTINA | B33: 17237 | AE33: =+AD33-AG33 -> -16 | AF33: =((AD33-AE33)*$B33) -> 275792 | AG33: 16 | AI33: =+AG33+AH33 -> 16 | AJ33: =+AI33-AL33 -> 5 | AK33: =((AI33-AJ33)*$B36) -> 71903.7 | AL33: 11 | AN33: =+AL33+AM33 -> 11 | AO33: =+AN33-AQ33 -> 0 | AP33: =((AN33-AO33)*$B33) -> 189607 | AQ33: 11 | AS33: =+AQ33+AR33 -> 11 | AT33: =+AS33-AV33 -> 11 | AU33: =((AS33-AT33)*$B36) -> 0
A34: PERFUMES SURTIDOS | B34: 27000 | AE34: =+AD34-AG34 -> -26 | AF34: =((AD34-AE34)*$B34) -> 702000 | AG34: 26 | AI34: =+AG34+AH34 -> 26 | AJ34: =+AI34-AL34 -> 0 | AK34: =((AI34-AJ34)*$B37) -> 286000 | AL34: 26 | AN34: =+AL34+AM34 -> 26 | AO34: =+AN34-AQ34 -> 1 | AP34: =((AN34-AO34)*$B34) -> 675000 | AQ34: 25 | AS34: =+AQ34+AR34 -> 25 | AT34: =+AS34-AV34 -> 25 | AU34: =((AS34-AT34)*$B37) -> 0
A35: PERFUMES KIT X 5 | B35: =327976/10 -> 32797.6 | AE35: =+AD35-AG35 -> -6 | AF35: =((AD35-AE35)*$B35) -> 196785.6 | AG35: 6 | AI35: =+AG35+AH35 -> 6 | AJ35: =+AI35-AL35 -> 1 | AK35: =((AI35-AJ35)*$B38) -> 139500 | AL35: 5 | AN35: =+AL35+AM35 -> 5 | AO35: =+AN35-AQ35 -> 3 | AP35: =((AN35-AO35)*$B35) -> 65595.2 | AQ35: 2 | AR35: 10 | AS35: =+AQ35+AR35 -> 12 | AT35: =+AS35-AV35 -> 12 | AU35: =((AS35-AT35)*$B38) -> 0
A36: PERFUMES MINI UNIDAD | B36: =326835/50 -> 6536.7 | AE36: =+AD36-AG36 -> -4 | AF36: =((AD36-AE36)*$B36) -> 26146.8 | AG36: 4 | AI36: =+AG36+AH36 -> 4 | AJ36: =+AI36-AL36 -> 0 | AK36: =((AI36-AJ36)*$B39) -> 127600 | AL36: 4 | AN36: =+AL36+AM36 -> 4 | AO36: =+AN36-AQ36 -> 0 | AP36: =((AN36-AO36)*$B36) -> 26146.8 | AQ36: 4 | AS36: =+AQ36+AR36 -> 4 | AT36: =+AS36-AV36 -> 4 | AU36: =((AS36-AT36)*$B39) -> 0
A37: AMPOLLAS RESCATE AZUL/ROSADA | B37: 11000 | AE37: =+AD37-AG37 -> -17 | AF37: =((AD37-AE37)*$B37) -> 187000 | AG37: 17 | AI37: =+AG37+AH37 -> 17 | AJ37: =+AI37-AL37 -> 1 | AK37: =((AI37-AJ37)*$B40) -> 148512 | AL37: 16 | AN37: =+AL37+AM37 -> 16 | AO37: =+AN37-AQ37 -> 4 | AP37: =((AN37-AO37)*$B37) -> 132000 | AQ37: 12 | AS37: =+AQ37+AR37 -> 12 | AT37: =+AS37-AV37 -> 12 | AU37: =((AS37-AT37)*$B40) -> 0
A38: ÓLEO REVITALIZANTE | B38: 27900 | AE38: =+AD38-AG38 -> -11 | AF38: =((AD38-AE38)*$B38) -> 306900 | AG38: 11 | AI38: =+AG38+AH38 -> 11 | AJ38: =+AI38-AL38 -> 2 | AK38: =((AI38-AJ38)*$B41) -> 65331 | AL38: 9 | AN38: =+AL38+AM38 -> 9 | AO38: =+AN38-AQ38 -> 0 | AP38: =((AN38-AO38)*$B38) -> 251100 | AQ38: 9 | AS38: =+AQ38+AR38 -> 9 | AT38: =+AS38-AV38 -> 9 | AU38: =((AS38-AT38)*$B41) -> 0
A39: STICK HAIR | B39: 31900 | AE39: =+AD39-AG39 -> 0 | AF39: =((AD39-AE39)*$B39) -> 0 | AG39: 0 | AH39: 2 | AI39: =+AG39+AH39 -> 2 | AJ39: =+AI39-AL39 -> 2 | AK39: =((AI39-AJ39)*$B42) -> 0 | AL39: 0 | AN39: =+AL39+AM39 -> 0 | AO39: =+AN39-AQ39 -> 0 | AP39: =((AN39-AO39)*$B39) -> 0 | AQ39: 0 | AS39: =+AQ39+AR39 -> 0 | AT39: =+AS39-AV39 -> 0 | AU39: =((AS39-AT39)*$B42) -> 0
A40: SH. MINI CEBOLLA | B40: 9282 | AE40: =+AD40-AG40 -> -33 | AF40: =((AD40-AE40)*$B40) -> 306306 | AG40: 33 | AI40: =+AG40+AH40 -> 33 | AJ40: =+AI40-AL40 -> 3 | AK40: =((AI40-AJ40)*$B43) -> 217770 | AL40: 30 | AN40: =+AL40+AM40 -> 30 | AO40: =+AN40-AQ40 -> 0 | AP40: =((AN40-AO40)*$B40) -> 278460 | AQ40: 30 | AS40: =+AQ40+AR40 -> 30 | AT40: =+AS40-AV40 -> 30 | AU40: =((AS40-AT40)*$B43) -> 0
A41: AC. MINI CEBOLLA | B41: 7259 | AE41: =+AD41-AG41 -> -32 | AF41: =((AD41-AE41)*$B41) -> 232288 | AG41: 32 | AI41: =+AG41+AH41 -> 32 | AJ41: =+AI41-AL41 -> 0 | AK41: =((AI41-AJ41)*$B44) -> 232288 | AL41: 32 | AN41: =+AL41+AM41 -> 32 | AO41: =+AN41-AQ41 -> 2 | AP41: =((AN41-AO41)*$B41) -> 217770 | AQ41: 30 | AS41: =+AQ41+AR41 -> 30 | AT41: =+AS41-AV41 -> 30 | AU41: =((AS41-AT41)*$B44) -> 0
A42: SH. MINI ULTRA NUTRITIVO | B42: 7259 | AE42: =+AD42-AG42 -> -16 | AF42: =((AD42-AE42)*$B42) -> 116144 | AG42: 16 | AI42: =+AG42+AH42 -> 16 | AJ42: =+AI42-AL42 -> 1 | AK42: =((AI42-AJ42)*$B45) -> 108885 | AL42: 15 | AN42: =+AL42+AM42 -> 15 | AO42: =+AN42-AQ42 -> 1 | AP42: =((AN42-AO42)*$B42) -> 101626 | AQ42: 14 | AS42: =+AQ42+AR42 -> 14 | AT42: =+AS42-AV42 -> 14 | AU42: =((AS42-AT42)*$B45) -> 0
A43: AC. MINI ULTRA NUTRITIVO | B43: 7259 | AE43: =+AD43-AG43 -> -17 | AF43: =((AD43-AE43)*$B43) -> 123403 | AG43: 17 | AI43: =+AG43+AH43 -> 17 | AJ43: =+AI43-AL43 -> 1 | AK43: =((AI43-AJ43)*$B46) -> 116144 | AL43: 16 | AN43: =+AL43+AM43 -> 16 | AO43: =+AN43-AQ43 -> 1 | AP43: =((AN43-AO43)*$B43) -> 108885 | AQ43: 15 | AS43: =+AQ43+AR43 -> 15 | AT43: =+AS43-AV43 -> 15 | AU43: =((AS43-AT43)*$B46) -> 0
A44: MINI BIO REPOLARIZADOR | B44: 7259 | AE44: =+AD44-AG44 -> -30 | AF44: =((AD44-AE44)*$B44) -> 217770 | AG44: 30 | AI44: =+AG44+AH44 -> 30 | AJ44: =+AI44-AL44 -> 0 | AK44: =((AI44-AJ44)*$B47) -> 217770 | AL44: 30 | AN44: =+AL44+AM44 -> 30 | AO44: =+AN44-AQ44 -> 3 | AP44: =((AN44-AO44)*$B44) -> 195993 | AQ44: 27 | AS44: =+AQ44+AR44 -> 27 | AT44: =+AS44-AV44 -> 27 | AU44: =((AS44-AT44)*$B47) -> 0
A45: MINI SHAMPOO EMERGENCIA | B45: 7259 | AE45: =+AD45-AG45 -> -19 | AF45: =((AD45-AE45)*$B45) -> 137921 | AG45: 19 | AI45: =+AG45+AH45 -> 19 | AJ45: =+AI45-AL45 -> 1 | AK45: =((AI45-AJ45)*$B49) -> 351000 | AL45: 18 | AN45: =+AL45+AM45 -> 18 | AO45: =+AN45-AQ45 -> 0 | AP45: =((AN45-AO45)*$B45) -> 130662 | AQ45: 18 | AS45: =+AQ45+AR45 -> 18 | AT45: =+AS45-AV45 -> 18 | AU45: =((AS45-AT45)*$B49) -> 0
A46: MINI ACONDICIONADOR HERBAL | B46: 7259 | E46: =+C46+D46 -> 0 | F46: =+E46-H46 -> 0 | G46: =((E46-F46)*$B46) -> 0 | J46: =+H46+I46 -> 0 | K46: =+J46-M46 -> 0 | L46: =((J46-K46)*$B49) -> 0 | O46: =+M46+N46 -> 0 | P46: =+O46-R46 -> 0 | Q46: =((O46-P46)*$B46) -> 0 | T46: =+R46+S46 -> 0 | U46: =+T46-W46 -> 0 | V46: =((T46-U46)*$B46) -> 0 | Y46: =+W46+X46 -> 0 | Z46: =+Y46-AB46 -> 0 | AA46: =((Y46-Z46)*$B46) -> 0 | AD46: =+AB46+AC46 -> 0 | AE46: =+AD46-AG46 -> -19 | AF46: =((AD46-AE46)*$B46) -> 137921 | AG46: 19 | AI46: =+AG46+AH46 -> 19 | AJ46: =+AI46-AL46 -> 1 | AK46: =((AI46-AJ46)*$B46) -> 130662 | AL46: 18 | AN46: =+AL46+AM46 -> 18 | AO46: =+AN46-AQ46 -> 0 | AP46: =((AN46-AO46)*$B46) -> 130662 | AQ46: 18 | AS46: =+AQ46+AR46 -> 18 | AT46: =+AS46-AV46 -> 18 | AU46: =((AS46-AT46)*$B46) -> 0 | AX46: =+AV46+AW46 -> 0 | AY46: =+AX46-BA46 -> 0 | AZ46: =((AX46-AY46)*$B46) -> 0 | BC46: =+BA46+BB46 -> 0 | BD46: =+BC46-BF46 -> 0 | BE46: =((BC46-BD46)*$B46) -> 0 | BH46: =+BF46+BG46 -> 0 | BI46: =+BH46-BK46 -> 0 | BJ46: =((BH46-BI46)*$B46) -> 0
A47: MINI TTO FRUTAS | B47: 7259 | E47: =+C47+D47 -> 0 | F47: =+E47-H47 -> 0 | G47: =((E47-F47)*$B47) -> 0 | J47: =+H47+I47 -> 0 | K47: =+J47-M47 -> 0 | L47: =((J47-K47)*$B50) -> 0 | O47: =+M47+N47 -> 0 | P47: =+O47-R47 -> 0 | Q47: =((O47-P47)*$B47) -> 0 | T47: =+R47+S47 -> 0 | U47: =+T47-W47 -> 0 | V47: =((T47-U47)*$B47) -> 0 | Y47: =+W47+X47 -> 0 | Z47: =+Y47-AB47 -> 0 | AA47: =((Y47-Z47)*$B47) -> 0 | AD47: =+AB47+AC47 -> 0 | AE47: =+AD47-AG47 -> -17 | AF47: =((AD47-AE47)*$B47) -> 123403 | AG47: 17 | AI47: =+AG47+AH47 -> 17 | AJ47: =+AI47-AL47 -> 1 | AK47: =((AI47-AJ47)*$B47) -> 116144 | AL47: 16 | AN47: =+AL47+AM47 -> 16 | AO47: =+AN47-AQ47 -> 0 | AP47: =((AN47-AO47)*$B47) -> 116144 | AQ47: 16 | AS47: =+AQ47+AR47 -> 16 | AT47: =+AS47-AV47 -> 16 | AU47: =((AS47-AT47)*$B47) -> 0 | AX47: =+AV47+AW47 -> 0 | AY47: =+AX47-BA47 -> 0 | AZ47: =((AX47-AY47)*$B47) -> 0 | BC47: =+BA47+BB47 -> 0 | BD47: =+BC47-BF47 -> 0 | BE47: =((BC47-BD47)*$B47) -> 0 | BH47: =+BF47+BG47 -> 0 | BI47: =+BH47-BK47 -> 0 | BJ47: =((BH47-BI47)*$B47) -> 0
A48: CEPILLO ANTI - ENREDOS BEIGE | B48: 15470 | AR48: 10 | AS48: =+AQ48+AR48 -> 10 | AT48: =+AS48-AV48 -> 10 | AU48: =((AS48-AT48)*$B48) -> 0
A49: CEPILLO | B49: 19500 | E49: =+C49+D49 -> 0 | F49: =+E49-H49 -> 0 | G49: =((E49-F49)*$B49) -> 0 | J49: =+H49+I49 -> 0 | K49: =+J49-M49 -> 0 | L49: =((J49-K49)*$B51) -> 0 | O49: =+M49+N49 -> 0 | P49: =+O49-R49 -> 0 | Q49: =((O49-P49)*$B49) -> 0 | T49: =+R49+S49 -> 0 | U49: =+T49-W49 -> 0 | V49: =((T49-U49)*$B49) -> 0 | Y49: =+W49+X49 -> 0 | Z49: =+Y49-AB49 -> 0 | AA49: =((Y49-Z49)*$B49) -> 0 | AD49: =+AB49+AC49 -> 0 | AE49: =+AD49-AG49 -> -2 | AF49: =((AD49-AE49)*$B49) -> 39000 | AG49: 2 | AI49: =+AG49+AH49 -> 2 | AJ49: =+AI49-AL49 -> 0 | AK49: =((AI49-AJ49)*$B49) -> 39000 | AL49: 2 | AN49: =+AL49+AM49 -> 2 | AO49: =+AN49-AQ49 -> 0 | AP49: =((AN49-AO49)*$B49) -> 39000 | AQ49: 2 | AS49: =+AQ49+AR49 -> 2 | AT49: =+AS49-AV49 -> 2 | AU49: =((AS49-AT49)*$B49) -> 0 | AX49: =+AV49+AW49 -> 0 | AY49: =+AX49-BA49 -> 0 | AZ49: =((AX49-AY49)*$B49) -> 0 | BC49: =+BA49+BB49 -> 0 | BD49: =+BC49-BF49 -> 0 | BE49: =((BC49-BD49)*$B49) -> 0 | BH49: =+BF49+BG49 -> 0 | BI49: =+BH49-BK49 -> 0 | BJ49: =((BH49-BI49)*$B49) -> 0
A50: TÓNICO HERBAL | B50: 39900 | E50: =+C50+D50 -> 0 | F50: =+E50-H50 -> 0 | G50: =((E50-F50)*$B50) -> 0 | J50: =+H50+I50 -> 0 | K50: =+J50-M50 -> 0 | L50: =((J50-K50)*$B52) -> 0 | O50: =+M50+N50 -> 0 | P50: =+O50-R50 -> 0 | Q50: =((O50-P50)*$B50) -> 0 | T50: =+R50+S50 -> 0 | U50: =+T50-W50 -> 0 | V50: =((T50-U50)*$B50) -> 0 | Y50: =+W50+X50 -> 0 | Z50: =+Y50-AB50 -> 0 | AA50: =((Y50-Z50)*$B50) -> 0 | AD50: =+AB50+AC50 -> 0 | AE50: =+AD50-AG50 -> -2 | AF50: =((AD50-AE50)*$B50) -> 79800 | AG50: 2 | AI50: =+AG50+AH50 -> 2 | AJ50: =+AI50-AL50 -> 0 | AK50: =((AI50-AJ50)*$B50) -> 79800 | AL50: 2 | AN50: =+AL50+AM50 -> 2 | AO50: =+AN50-AQ50 -> 0 | AP50: =((AN50-AO50)*$B50) -> 79800 | AQ50: 2 | AS50: =+AQ50+AR50 -> 2 | AT50: =+AS50-AV50 -> 2 | AU50: =((AS50-AT50)*$B50) -> 0 | AX50: =+AV50+AW50 -> 0 | AY50: =+AX50-BA50 -> 0 | AZ50: =((AX50-AY50)*$B50) -> 0 | BC50: =+BA50+BB50 -> 0 | BD50: =+BC50-BF50 -> 0 | BE50: =((BC50-BD50)*$B50) -> 0 | BH50: =+BF50+BG50 -> 0 | BI50: =+BH50-BK50 -> 0 | BJ50: =((BH50-BI50)*$B50) -> 0
G51: =+SUM(G3:G50) -> 0 | L51: =+SUM(L3:L50) -> 0 | Q51: =+SUM(Q3:Q50) -> 0 | V51: =+SUM(V3:V50) -> 0 | AA51: =+SUM(AA3:AA50) -> 0 | AF51: =+SUM(AF3:AF50) -> 13327417 | AK51: =+SUM(AK3:AK50) -> 11414816 | AP51: =+SUM(AP3:AP50) -> 10992015 | AU51: =+SUM(AU3:AU50) -> 0 | AZ51: =+SUM(AZ3:AZ50) -> #REF! | BE51: =+SUM(BE3:BE50) -> #REF! | BJ51: =+SUM(BJ3:BJ50) -> #REF!
A60: SH. EMERGENCIA CAPILAR (GRASOS) | B60: 27500 | C60: =#REF!*B60 -> #REF!
A61: SH. ULTRA NUTRITIVO PREMIUM (FRIZZ) | B61: 28500 | C61: =#REF!*B61 -> #REF!
A62: SH. NATURAL KIDS | B62: 27500 | C62: =#REF!*B62 -> #REF!
A63: SH. HERBAL (CAÍDA) | B63: 28500 | C63: =#REF!*B63 -> #REF!
A64: SH. ARROZ (SECOS) | B64: 27500 | C64: =#REF!*B64 -> #REF!
A65: GOTAS MÁGICAS | B65: 23500 | C65: =#REF!*B65 -> #REF!
A66: AC. ROMERO | B66: 29000 | C66: =#REF!*B66 -> #REF!
A67: AC.ARROZ | B67: 27500 | C67: =#REF!*B67 -> #REF!
A68: BIO REPOLARIZADOR | B68: 29000 | C68: =#REF!*B68 -> #REF!
A69: MASC MULTIVITAMINICA | B69: 32500 | C69: =#REF!*B69 -> #REF!
A70: TRA. EMERGENCIA CAPILAR | B70: 29000 | C70: =#REF!*B70 -> #REF!
A71: TRA. NUTRICIÓN Y CRECIMIENTO | B71: 29000 | C71: =#REF!*B71 -> #REF!
... A77: SERUM REVITALIZANTE CAPILAR | B77: 26500 | C77: =#REF!*B77 -> #REF!
C78: =SUM(C60:C77) -> #REF!

Sheet OLE
A1: OLÉ | C1: ENERO | H1: FEBRERO | M1: MARZO | R1: ABRIL | W1: MAYO | AB1: JUNIO | AG1: JULIO | AL1: AGOSTO | AQ1: SEPTIEMBRE | AV1: OCTUBRE | BA1: NOVIEMBRE | BF1: DICIEMBRE | BK1: ENERO
A2: PRODUCTO | B2: VR. COMPRA | C2: INV.I | D2: Entra | E2: Saldo | F2: SALIDA | G2: TOTAL | H2: INV.I | I2: Entra | J2: Saldo | K2: SALIDA | L2: TOTAL | M2: INV.I | N2: Entra | O2: Saldo | P2: SALIDA | Q2: TOTAL | R2: INV.I | S2: Entra | T2: Saldo | U2: SALIDA | V2: TOTAL | W2: INV.I | X2: Entra | Y2: Saldo | Z2: SALIDA | AA2: TOTAL | AB2: INV.I | AC2: Entra | AD2: Saldo | AE2: SALIDA | AF2: TOTAL | AG2: INV.I | AH2: Entra | AI2: Saldo | AJ2: SALIDA | AK2: TOTAL | AL2: INV.I | AM2: Entra | AN2: Saldo | AO2: SALIDA | AP2: TOTAL | AQ2: INV.I | AR2: Entra | AS2: Saldo | AT2: SALIDA | AU2: TOTAL | AV2: INV.I | AW2: Entra | AX2: Saldo | AY2: SALIDA | AZ2: TOTAL | BA2: INV.I | BB2: Entra | BC2: Saldo | BD2: SALIDA | BE2: TOTAL | BF2: INV.I | BG2: Entra | BH2: Saldo | BI2: SALIDA | BJ2: TOTAL | BK2: INV.I
A3: POLVO TRASLUCIDO (SH. EN SECO) | B3: 18700 | F3: =+E3-H3 -> 0 | G3: =((E3-F3)*$B3) -> 0 | K3: =+J3-M3 -> 0 | L3: =((J3-K3)*$B3) -> 0 | P3: =+O3-R3 -> 0 | Q3: =((O3-P3)*$B3) -> 0 | U3: =+T3-W3 -> 0 | V3: =((T3-U3)*$B3) -> 0 | Z3: =+Y3-AB3 -> 0 | AA3: =((Y3-Z3)*$B3) -> 0 | AE3: =+AD3-AG3 -> -2 | AF3: =((AD3-AE3)*$B3) -> 37400 | AG3: 2 | AI3: =+AG3+AH3 -> 2 | AJ3: =+AI3-AL3 -> 0 | AK3: =((AI3-AJ3)*$B3) -> 37400 | AL3: 2 | AN3: =+AL3+AM3 -> 2 | AO3: =+AN3-AQ3 -> 0 | AP3: =((AN3-AO3)*$B3) -> 37400 | AQ3: 2 | AS3: =+AQ3+AR3 -> 2 | AT3: =+AS3-AV3 -> 2 | AU3: =((AS3-AT3)*$B3) -> 0 | AX3: =+AV3+AW3 -> 0 | AY3: =+AX3-BA3 -> 0 | AZ3: =((AX3-AY3)*$B3) -> 0 | BC3: =+BA3+BB3 -> 0 | BD3: =+BC3-BF3 -> 0 | BE3: =((BC3-BD3)*$B3) -> 0 | BH3: =+BF3+BG3 -> 0 | BI3: =+BH3-BK3 -> 0 | BJ3: =((BH3-BI3)*$B3) -> 0
A4: SH. COCO HIDRATACIÓN | B4: 30000 | F4: =+E4-H4 -> 0 | G4: =((E4-F4)*$B4) -> 0 | K4: =+J4-M4 -> 0 | L4: =((J4-K4)*$B4) -> 0 | P4: =+O4-R4 -> 0 | Q4: =((O4-P4)*$B4) -> 0 | U4: =+T4-W4 -> 0 | V4: =((T4-U4)*$B4) -> 0 | Z4: =+Y4-AB4 -> 0 | AA4: =((Y4-Z4)*$B4) -> 0 | AE4: =+AD4-AG4 -> -5 | AF4: =((AD4-AE4)*$B4) -> 150000 | AG4: 5 | AI4: =+AG4+AH4 -> 5 | AJ4: =+AI4-AL4 -> 0 | AK4: =((AI4-AJ4)*$B4) -> 150000 | AL4: 5 | AN4: =+AL4+AM4 -> 5 | AO4: =+AN4-AQ4 -> 2 | AP4: =((AN4-AO4)*$B4) -> 90000 | AQ4: 3 | AS4: =+AQ4+AR4 -> 3 | AT4: =+AS4-AV4 -> 3 | AU4: =((AS4-AT4)*$B4) -> 0 | AX4: =+AV4+AW4 -> 0 | AY4: =+AX4-BA4 -> 0 | AZ4: =((AX4-AY4)*$B4) -> 0 | BC4: =+BA4+BB4 -> 0 | BD4: =+BC4-BF4 -> 0 | BE4: =((BC4-BD4)*$B4) -> 0 | BH4: =+BF4+BG4 -> 0 | BI4: =+BH4-BK4 -> 0 | BJ4: =((BH4-BI4)*$B4) -> 0
A5: SH. CEBOLLA ANTIGRASA | B5: 30000 | F5: =+E5-H5 -> 0 | AA5: =((Y5-Z5)*$B5) -> 0 | AE5: =+AD5-AG5 -> -6 | AF5: =((AD5-AE5)*$B5) -> 180000 | AG5: 6 | AI5: =+AG5+AH5 -> 6 | AJ5: =+AI5-AL5 -> 0 | AK5: =((AI5-AJ5)*$B5) -> 180000 | AL5: 6 | AN5: =+AL5+AM5 -> 6 | AO5: =+AN5-AQ5 -> 4 | AP5: =((AN5-AO5)*$B5) -> 60000 | AQ5: 2 | AS5: =+AQ5+AR5 -> 2 | AT5: =+AS5-AV5 -> 2 | AU5: =((AS5-AT5)*$B5) -> 0 | AX5: =+AV5+AW5 -> 0 | AY5: =+AX5-BA5 -> 0 | AZ5: =((AX5-AY5)*$B5) -> 0 | BC5: =+BA5+BB5 -> 0 | BD5: =+BC5-BF5 -> 0 | BE5: =((BC5-BD5)*$B5) -> 0 | BH5: =+BF5+BG5 -> 0 | BI5: =+BH5-BK5 -> 0 | BJ5: =((BH5-BI5)*$B5) -> 0
A6: SH. REVITALIZANTE CRECIMIENTO | B6: 30000 | F6: =+E6-H6 -> 0 | AA6: =((Y6-Z6)*$B6) -> 0 | AE6: =+AD6-AG6 -> -4 | AF6: =((AD6-AE6)*$B6) -> 120000 | AG6: 4 | AI6: =+AG6+AH6 -> 4 | AJ6: =+AI6-AL6 -> 0 | AK6: =((AI6-AJ6)*$B6) -> 120000 | AL6: 4 | AN6: =+AL6+AM6 -> 4 | AO6: =+AN6-AQ6 -> 0 | AP6: =((AN6-AO6)*$B6) -> 120000 | AQ6: 4 | AS6: =+AQ6+AR6 -> 4 | AT6: =+AS6-AV6 -> 4 | AU6: =((AS6-AT6)*$B6) -> 0 | AX6: =+AV6+AW6 -> 0 | AY6: =+AX6-BA6 -> 0 | AZ6: =((AX6-AY6)*$B6) -> 0 | BC6: =+BA6+BB6 -> 0 | BD6: =+BC6-BF6 -> 0 | BE6: =((BC6-BD6)*$B6) -> 0 | BH6: =+BF6+BG6 -> 0 | BI6: =+BH6-BK6 -> 0 | BJ6: =((BH6-BI6)*$B6) -> 0
A7: SH. MIX DE FRUTAS | B7: 30000 | F7: =+E7-H7 -> 0 | AA7: =((Y7-Z7)*$B7) -> 0 | AE7: =+AD7-AG7 -> -2 | AF7: =((AD7-AE7)*$B7) -> 60000 | AG7: 2 | AI7: =+AG7+AH7 -> 2 | AJ7: =+AI7-AL7 -> 1 | AK7: =((AI7-AJ7)*$B7) -> 30000 | AL7: 1 | AM7: 4 | AN7: =+AL7+AM7 -> 5 | AO7: =+AN7-AQ7 -> 1 | AP7: =((AN7-AO7)*$B7) -> 120000 | AQ7: 4 | AS7: =+AQ7+AR7 -> 4 | AT7: =+AS7-AV7 -> 4 | AU7: =((AS7-AT7)*$B7) -> 0 | AX7: =+AV7+AW7 -> 0 | AY7: =+AX7-BA7 -> 0 | AZ7: =((AX7-AY7)*$B7) -> 0 | BC7: =+BA7+BB7 -> 0 | BD7: =+BC7-BF7 -> 0 | BE7: =((BC7-BD7)*$B7) -> 0 | BH7: =+BF7+BG7 -> 0 | BI7: =+BH7-BK7 -> 0 | BJ7: =((BH7-BI7)*$B7) -> 0
A8: SH. 2 EN 1 | B8: 30000 | F8: =+E8-H8 -> 0 | AA8: =((Y8-Z8)*$B8) -> 0 | AE8: =+AD8-AG8 -> 0 | AF8: =((AD8-AE8)*$B8) -> 0 | AG8: 0 | AI8: =+AG8+AH8 -> 0 | AJ8: =+AI8-AL8 -> 0 | AK8: =((AI8-AJ8)*$B8) -> 0 | AL8: 0 | AN8: =+AL8+AM8 -> 0 | AO8: =+AN8-AQ8 -> 0 | AP8: =((AN8-AO8)*$B8) -> 0 | AQ8: 0 | AS8: =+AQ8+AR8 -> 0 | AT8: =+AS8-AV8 -> 0 | AU8: =((AS8-AT8)*$B8) -> 0 | AX8: =+AV8+AW8 -> 0 | AY8: =+AX8-BA8 -> 0 | AZ8: =((AX8-AY8)*$B8) -> 0 | BC8: =+BA8+BB8 -> 0 | BD8: =+BC8-BF8 -> 0 | BE8: =((BC8-BD8)*$B8) -> 0 | BH8: =+BF8+BG8 -> 0 | BI8: =+BH8-BK8 -> 0 | BJ8: =((BH8-BI8)*$B8) -> 0
A9: AC. ALGODÓN | B9: 28500 | F9: =+E9-H9 -> 0 | AA9: =((Y9-Z9)*$B9) -> 0 | AE9: =+AD9-AG9 -> -3 | AF9: =((AD9-AE9)*$B9) -> 85500 | AG9: 3 | AI9: =+AG9+AH9 -> 3 | AJ9: =+AI9-AL9 -> 1 | AK9: =((AI9-AJ9)*$B9) -> 57000 | AL9: 2 | AN9: =+AL9+AM9 -> 2 | AO9: =+AN9-AQ9 -> 2 | AP9: =((AN9-AO9)*$B9) -> 0 | AQ9: 0 | AS9: =+AQ9+AR9 -> 0 | AT9: =+AS9-AV9 -> 0 | AU9: =((AS9-AT9)*$B9) -> 0 | AX9: =+AV9+AW9 -> 0 | AY9: =+AX9-BA9 -> 0 | AZ9: =((AX9-AY9)*$B9) -> 0 | BC9: =+BA9+BB9 -> 0 | BD9: =+BC9-BF9 -> 0 | BE9: =((BC9-BD9)*$B9) -> 0 | BH9: =+BF9+BG9 -> 0 | BI9: =+BH9-BK9 -> 0 | BJ9: =((BH9-BI9)*$B9) -> 0
A10: AC. JARABE DE MANGO | B10: 28500 | F10: =+E10-H10 -> 0 | AA10: =((Y10-Z10)*$B10) -> 0 | AE10: =+AD10-AG10 -> -3 | AF10: =((AD10-AE10)*$B10) -> 85500 | AG10: 3 | AI10: =+AG10+AH10 -> 3 | AJ10: =+AI10-AL10 -> 1 | AK10: =((AI10-AJ10)*$B10) -> 57000 | AL10: 2 | AN10: =+AL10+AM10 -> 2 | AO10: =+AN10-AQ10 -> 1 | AP10: =((AN10-AO10)*$B10) -> 28500 | AQ10: 1 | AS10: =+AQ10+AR10 -> 1 | AT10: =+AS10-AV10 -> 1 | AU10: =((AS10-AT10)*$B10) -> 0 | AX10: =+AV10+AW10 -> 0 | AY10: =+AX10-BA10 -> 0 | AZ10: =((AX10-AY10)*$B10) -> 0 | BC10: =+BA10+BB10 -> 0 | BD10: =+BC10-BF10 -> 0 | BE10: =((BC10-BD10)*$B10) -> 0 | BH10: =+BF10+BG10 -> 0 | BI10: =+BH10-BK10 -> 0 | BJ10: =((BH10-BI10)*$B10) -> 0
A11: ÓLEO UCHUVA | B11: 27000 | F11: =+E11-H11 -> 0 | AA11: =((Y11-Z11)*$B11) -> 0 | AE11: =+AD11-AG11 -> 0 | AF11: =((AD11-AE11)*$B11) -> 0 | AG11: 0 | AI11: =+AG11+AH11 -> 0 | AJ11: =+AI11-AL11 -> 0 | AK11: =((AI11-AJ11)*$B11) -> 0 | AL11: 0 | AM11: 6 | AN11: =+AL11+AM11 -> 6 | AO11: =+AN11-AQ11 -> 0 | AP11: =((AN11-AO11)*$B11) -> 162000 | AQ11: 6 | AS11: =+AQ11+AR11 -> 6 | AT11: =+AS11-AV11 -> 6 | AU11: =((AS11-AT11)*$B11) -> 0 | AX11: =+AV11+AW11 -> 0 | AY11: =+AX11-BA11 -> 0 | AZ11: =((AX11-AY11)*$B11) -> 0 | BC11: =+BA11+BB11 -> 0 | BD11: =+BC11-BF11 -> 0 | BE11: =((BC11-BD11)*$B11) -> 0 | BH11: =+BF11+BG11 -> 0 | BI11: =+BH11-BK11 -> 0 | BJ11: =((BH11-BI11)*$B11) -> 0
A12: ANTI FRIZZ CON COLOR/ SIN COLOR | B12: 28000 | F12: =+E12-H12 -> 0 | AA12: =((Y12-Z12)*$B12) -> 0 | AE12: =+AD12-AG12 -> -1 | AF12: =((AD12-AE12)*$B12) -> 28000 | AG12: 1 | AI12: =+AG12+AH12 -> 1 | AJ12: =+AI12-AL12 -> 0 | AK12: =((AI12-AJ12)*$B12) -> 28000 | AL12: 1 | AN12: =+AL12+AM12 -> 1 | AO12: =+AN12-AQ12 -> 0 | AP12: =((AN12-AO12)*$B12) -> 28000 | AQ12: 1 | AS12: =+AQ12+AR12 -> 1 | AT12: =+AS12-AV12 -> 1 | AU12: =((AS12-AT12)*$B12) -> 0 | AX12: =+AV12+AW12 -> 0 | AY12: =+AX12-BA12 -> 0 | AZ12: =((AX12-AY12)*$B12) -> 0 | BC12: =+BA12+BB12 -> 0 | BD12: =+BC12-BF12 -> 0 | BE12: =((BC12-BD12)*$B12) -> 0 | BH12: =+BF12+BG12 -> 0 | BI12: =+BH12-BK12 -> 0 | BJ12: =((BH12-BI12)*$B12) -> 0
A13: TRATAMIENTO DE ARROZ | B13: 31000 | F13: =+E13-H13 -> 0 | AA13: =((Y13-Z13)*$B13) -> 0 | AE13: =+AD13-AG13 -> 0 | AF13: =((AD13-AE13)*$B13) -> 0 | AG13: 0 | AI13: =+AG13+AH13 -> 0 | AJ13: =+AI13-AL13 -> 0 | AK13: =((AI13-AJ13)*$B13) -> 0 | AL13: 0 | AN13: =+AL13+AM13 -> 0 | AO13: =+AN13-AQ13 -> 0 | AP13: =((AN13-AO13)*$B13) -> 0 | AQ13: 0 | AS13: =+AQ13+AR13 -> 0 | AT13: =+AS13-AV13 -> 0 | AU13: =((AS13-AT13)*$B13) -> 0 | AX13: =+AV13+AW13 -> 0 | AY13: =+AX13-BA13 -> 0 | AZ13: =((AX13-AY13)*$B13) -> 0 | BC13: =+BA13+BB13 -> 0 | BD13: =+BC13-BF13 -> 0 | BE13: =((BC13-BD13)*$B13) -> 0 | BH13: =+BF13+BG13 -> 0 | BI13: =+BH13-BK13 -> 0 | BJ13: =((BH13-BI13)*$B13) -> 0
A14: TRATAMIENTO DE COCO | B14: 31000 | F14: =+E14-H14 -> 0 | AA14: =((Y14-Z14)*$B14) -> 0 | AE14: =+AD14-AG14 -> -2 | AF14: =((AD14-AE14)*$B14) -> 62000 | AG14: 2 | AI14: =+AG14+AH14 -> 2 | AJ14: =+AI14-AL14 -> 0 | AK14: =((AI14-AJ14)*$B14) -> 62000 | AL14: 2 | AN14: =+AL14+AM14 -> 2 | AO14: =+AN14-AQ14 -> 0 | AP14: =((AN14-AO14)*$B14) -> 62000 | AQ14: 2 | AS14: =+AQ14+AR14 -> 2 | AT14: =+AS14-AV14 -> 2 | AU14: =((AS14-AT14)*$B14) -> 0 | AX14: =+AV14+AW14 -> 0 | AY14: =+AX14-BA14 -> 0 | AZ14: =((AX14-AY14)*$B14) -> 0 | BC14: =+BA14+BB14 -> 0 | BD14: =+BC14-BF14 -> 0 | BE14: =((BC14-BD14)*$B14) -> 0 | BH14: =+BF14+BG14 -> 0 | BI14: =+BH14-BK14 -> 0 | BJ14: =((BH14-BI14)*$B14) -> 0
A15: TRATAMIENTO REPARADOR DE FRUTAS | B15: 31000 | F15: =+E15-H15 -> 0 | AA15: =((Y15-Z15)*$B15) -> 0 | AE15: =+AD15-AG15 -> 0 | AF15: =((AD15-AE15)*$B15) -> 0 | AG15: 0 | AI15: =+AG15+AH15 -> 0 | AJ15: =+AI15-AL15 -> 0 | AK15: =((AI15-AJ15)*$B15) -> 0 | AL15: 0 | AN15: =+AL15+AM15 -> 0 | AO15: =+AN15-AQ15 -> 0 | AP15: =((AN15-AO15)*$B15) -> 0 | AQ15: 0 | AS15: =+AQ15+AR15 -> 0 | AT15: =+AS15-AV15 -> 0 | AU15: =((AS15-AT15)*$B15) -> 0 | AX15: =+AV15+AW15 -> 0 | AY15: =+AX15-BA15 -> 0 | AZ15: =((AX15-AY15)*$B15) -> 0 | BC15: =+BA15+BB15 -> 0 | BD15: =+BC15-BF15 -> 0 | BE15: =((BC15-BD15)*$B15) -> 0 | BH15: =+BF15+BG15 -> 0 | BI15: =+BH15-BK15 -> 0 | BJ15: =((BH15-BI15)*$B15) -> 0
A16: TERMOPROTECTOR | B16: 35000 | F16: =+E16-H16 -> 0 | AA16: =((Y16-Z16)*$B16) -> 0 | AE16: =+AD16-AG16 -> -3 | AF16: =((AD16-AE16)*$B16) -> 105000 | AG16: 3 | AI16: =+AG16+AH16 -> 3 | AJ16: =+AI16-AL16 -> 1 | AK16: =((AI16-AJ16)*$B16) -> 70000 | AL16: 2 | AM16: 6 | AN16: =+AL16+AM16 -> 8 | AO16: =+AN16-AQ16 -> 1 | AP16: =((AN16-AO16)*$B16) -> 245000 | AQ16: 7 | AS16: =+AQ16+AR16 -> 7 | AT16: =+AS16-AV16 -> 7 | AU16: =((AS16-AT16)*$B16) -> 0 | AX16: =+AV16+AW16 -> 0 | AY16: =+AX16-BA16 -> 0 | AZ16: =((AX16-AY16)*$B16) -> 0 | BC16: =+BA16+BB16 -> 0 | BD16: =+BC16-BF16 -> 0 | BE16: =((BC16-BD16)*$B16) -> 0 | BH16: =+BF16+BG16 -> 0 | BI16: =+BH16-BK16 -> 0 | BJ16: =((BH16-BI16)*$B16) -> 0
A17: TERMOPROTECTOR GLITTER | B17: 35000 | F17: =+E17-H17 -> 0 | AA17: =((Y17-Z17)*$B17) -> 0 | AE17: =+AD17-AG17 -> 0 | AF17: =((AD17-AE17)*$B17) -> 0 | AG17: 0 | AI17: =+AG17+AH17 -> 0 | AJ17: =+AI17-AL17 -> 0 | AK17: =((AI17-AJ17)*$B17) -> 0 | AL17: 0 | AN17: =+AL17+AM17 -> 0 | AO17: =+AN17-AQ17 -> 0 | AP17: =((AN17-AO17)*$B17) -> 0 | AQ17: 0 | AS17: =+AQ17+AR17 -> 0 | AT17: =+AS17-AV17 -> 0 | AU17: =((AS17-AT17)*$B17) -> 0 | AX17: =+AV17+AW17 -> 0 | AY17: =+AX17-BA17 -> 0 | AZ17: =((AX17-AY17)*$B17) -> 0 | BC17: =+BA17+BB17 -> 0 | BD17: =+BC17-BF17 -> 0 | BE17: =((BC17-BD17)*$B17) -> 0 | BH17: =+BF17+BG17 -> 0 | BI17: =+BH17-BK17 -> 0 | BJ17: =((BH17-BI17)*$B17) -> 0
A18: TERMOPROTECTOR MINI | B18: 17200 | F18: =+E18-H18 -> 0 | AA18: =((Y18-Z18)*$B18) -> 0 | AE18: =+AD18-AG18 -> 0 | AF18: =((AD18-AE18)*$B18) -> 0 | AG18: 0 | AI18: =+AG18+AH18 -> 0 | AJ18: =+AI18-AL18 -> 0 | AK18: =((AI18-AJ18)*$B18) -> 0 | AL18: 0 | AM18: 4 | AN18: =+AL18+AM18 -> 4 | AO18: =+AN18-AQ18 -> 0 | AP18: =((AN18-AO18)*$B18) -> 68800 | AQ18: 4 | AS18: =+AQ18+AR18 -> 4 | AT18: =+AS18-AV18 -> 4 | AU18: =((AS18-AT18)*$B18) -> 0 | AX18: =+AV18+AW18 -> 0 | AY18: =+AX18-BA18 -> 0 | AZ18: =((AX18-AY18)*$B18) -> 0 | BC18: =+BA18+BB18 -> 0 | BD18: =+BC18-BF18 -> 0 | BE18: =((BC18-BD18)*$B18) -> 0 | BH18: =+BF18+BG18 -> 0 | BI18: =+BH18-BK18 -> 0 | BJ18: =((BH18-BI18)*$B18) -> 0
A19: SLIK PESTAÑINA ANTI FRIZZ | B19: 20200 | F19: =+E19-H19 -> 0 | AA19: =((Y19-Z19)*$B19) -> 0 | AE19: =+AD19-AG19 -> -2 | AF19: =((AD19-AE19)*$B19) -> 40400 | AG19: 2 | AI19: =+AG19+AH19 -> 2 | AJ19: =+AI19-AL19 -> 0 | AK19: =((AI19-AJ19)*$B19) -> 40400 | AL19: 2 | AN19: =+AL19+AM19 -> 2 | AO19: =+AN19-AQ19 -> 0 | AP19: =((AN19-AO19)*$B19) -> 40400 | AQ19: 2 | AS19: =+AQ19+AR19 -> 2 | AT19: =+AS19-AV19 -> 2 | AU19: =((AS19-AT19)*$B19) -> 0 | AX19: =+AV19+AW19 -> 0 | AY19: =+AX19-BA19 -> 0 | AZ19: =((AX19-AY19)*$B19) -> 0 | BC19: =+BA19+BB19 -> 0 | BD19: =+BC19-BF19 -> 0 | BE19: =((BC19-BD19)*$B19) -> 0 | BH19: =+BF19+BG19 -> 0 | BI19: =+BH19-BK19 -> 0 | BJ19: =((BH19-BI19)*$B19) -> 0
A20: CREMA PEINADORA ANTI FRIZZ | B20: 23000 | F20: =+E20-H20 -> 0 | AA20: =((Y20-Z20)*$B20) -> 0 | AE20: =+AD20-AG20 -> -2 | AF20: =((AD20-AE20)*$B20) -> 46000 | AG20: 2 | AI20: =+AG20+AH20 -> 2 | AJ20: =+AI20-AL20 -> 0 | AK20: =((AI20-AJ20)*$B20) -> 46000 | AL20: 2 | AN20: =+AL20+AM20 -> 2 | AO20: =+AN20-AQ20 -> 0 | AP20: =((AN20-AO20)*$B20) -> 46000 | AQ20: 2 | AS20: =+AQ20+AR20 -> 2 | AT20: =+AS20-AV20 -> 2 | AU20: =((AS20-AT20)*$B20) -> 0 | AX20: =+AV20+AW20 -> 0 | AY20: =+AX20-BA20 -> 0 | AZ20: =((AX20-AY20)*$B20) -> 0 | BC20: =+BA20+BB20 -> 0 | BD20: =+BC20-BF20 -> 0 | BE20: =((BC20-BD20)*$B20) -> 0 | BH20: =+BF20+BG20 -> 0 | BI20: =+BH20-BK20 -> 0 | BJ20: =((BH20-BI20)*$B20) -> 0
A21: ANTI HUMEDAD ANTI FRIZZ | B21: 27700 | F21: =+E21-H21 -> 0 | AA21: =((Y21-Z21)*$B21) -> 0 | AE21: =+AD21-AG21 -> 0 | AF21: =((AD21-AE21)*$B21) -> 0 | AG21: 0 | AI21: =+AG21+AH21 -> 0 | AJ21: =+AI21-AL21 -> 0 | AK21: =((AI21-AJ21)*$B21) -> 0 | AL21: 0 | AM21: 4 | AN21: =+AL21+AM21 -> 4 | AO21: =+AN21-AQ21 -> 0 | AP21: =((AN21-AO21)*$B21) -> 110800 | AQ21: 4 | AS21: =+AQ21+AR21 -> 4 | AT21: =+AS21-AV21 -> 4 | AU21: =((AS21-AT21)*$B21) -> 0 | AX21: =+AV21+AW21 -> 0 | AY21: =+AX21-BA21 -> 0 | AZ21: =((AX21-AY21)*$B21) -> 0 | BC21: =+BA21+BB21 -> 0 | BD21: =+BC21-BF21 -> 0 | BE21: =((BC21-BD21)*$B21) -> 0 | BH21: =+BF21+BG21 -> 0 | BI21: =+BH21-BK21 -> 0 | BJ21: =((BH21-BI21)*$B21) -> 0
A22: PERFUMES | B22: 20000 | F22: =+E22-H22 -> 0 | AA22: =((Y22-Z22)*$B22) -> 0 | AE22: =+AD22-AG22 -> -1 | AF22: =((AD22-AE22)*$B22) -> 20000 | AG22: 1 | AI22: =+AG22+AH22 -> 1 | AJ22: =+AI22-AL22 -> 0 | AK22: =((AI22-AJ22)*$B22) -> 20000 | AL22: 1 | AN22: =+AL22+AM22 -> 1 | AO22: =+AN22-AQ22 -> 0 | AP22: =((AN22-AO22)*$B22) -> 20000 | AQ22: 1 | AS22: =+AQ22+AR22 -> 1 | AT22: =+AS22-AV22 -> 1 | AU22: =((AS22-AT22)*$B22) -> 0 | AX22: =+AV22+AW22 -> 0 | AY22: =+AX22-BA22 -> 0 | AZ22: =((AX22-AY22)*$B22) -> 0 | BC22: =+BA22+BB22 -> 0 | BD22: =+BC22-BF22 -> 0 | BE22: =((BC22-BD22)*$B22) -> 0 | BH22: =+BF22+BG22 -> 0 | BI22: =+BH22-BK22 -> 0 | BJ22: =((BH22-BI22)*$B22) -> 0
G23: =+SUM(G3:G22) -> 0 | L23: =+SUM(L3:L22) -> 0 | Q23: =+SUM(Q3:Q22) -> 0 | V23: =+SUM(V3:V22) -> 0 | AA23: =+SUM(AA3:AA22) -> 0 | AF23: =+SUM(AF3:AF22) -> 1019800 | AK23: =+SUM(AK3:AK22) -> 897800 | AP23: =+SUM(AP3:AP22) -> 1238900 | AU23: =+SUM(AU3:AU22) -> 0 | AZ23: =+SUM(AZ3:AZ22) -> 0 | BE23: =+SUM(BE3:BE22) -> 0 | BJ23: =+SUM(BJ3:BJ22) -> 0

Sheet A.H
A1: ANDREINA HAIR | C1: ENERO | H1: FEBRERO | M1: MARZO | R1: ABRIL | W1: MAYO | AB1: JUNIO | AG1: JULIO | AL1: AGOSTO | AQ1: SEPTIEMBRE | AV1: OCTUBRE | BA1: NOVIEMBRE | BF1: DICIEMBRE | BK1: ENERO
A2: PRODUCTO | B2: VR. COMPRA | C2: INV.I | D2: Entra | E2: Saldo | F2: SALIDA | G2: TOTAL | H2: INV.I | I2: Entra | J2: Saldo | K2: SALIDA | L2: TOTAL | M2: INV.I | N2: Entra | O2: Saldo | P2: SALIDA | Q2: TOTAL | R2: INV.I | S2: Entra | T2: Saldo | U2: SALIDA | V2: TOTAL | W2: INV.I | X2: Entra | Y2: Saldo | Z2: SALIDA | AA2: TOTAL | AB2: INV.I | AC2: Entra | AD2: Saldo | AE2: SALIDA | AF2: TOTAL | AG2: INV.I | AH2: Entra | AI2: Saldo | AJ2: SALIDA | AK2: TOTAL | AL2: INV.I | AM2: Entra | AN2: Saldo | AO2: SALIDA | AP2: TOTAL | AQ2: INV.I | AR2: Entra | AS2: Saldo | AT2: SALIDA | AU2: TOTAL | AV2: INV.I | AW2: Entra | AX2: Saldo | AY2: SALIDA | AZ2: TOTAL | BA2: INV.I | BB2: Entra | BC2: Saldo | BD2: SALIDA | BE2: TOTAL | BF2: INV.I | BG2: Entra | BH2: Saldo | BI2: SALIDA | BJ2: TOTAL | BK2: INV.I
A3: SERUM CAPILAR | B3: 33000 | AD3: =+AB3+AC3 -> 0 | AE3: =+AD3-AG3 -> 0 | AF3: =((AD3-AE3)*$B3) -> 0 | AG3: 0 | AI3: =+AG3+AH3 -> 0 | AJ3: =+AI3-AL3 -> 0 | AK3: =((AI3-AJ3)*$B3) -> 0 | AL3: 0 | AM3: 6 | AN3: =+AL3+AM3 -> 6 | AO3: =+AN3-AQ3 -> 0 | AP3: =((AN3-AO3)*$B3) -> 198000 | AQ3: 6 | AS3: =+AQ3+AR3 -> 6 | AT3: =+AS3-AV3 -> 6 | AU3: =((AS3-AT3)*$B3) -> 0 | AX3: =+AV3+AW3 -> 0 | AY3: =+AX3-BA3 -> 0 | AZ3: =((AX3-AY3)*$B3) -> 0 | BC3: =+BA3+BB3 -> 0 | BD3: =+BC3-BF3 -> 0 | BE3: =((BC3-BD3)*$B3) -> 0 | BH3: =+BF3+BG3 -> 0 | BI3: =+BH3-BK3 -> 0 | BJ3: =((BH3-BI3)*$B3) -> 0
A4: ACEITE DE ROMERO | B4: 32000 | AD4: =+AB4+AC4 -> 0 | AE4: =+AD4-AG4 -> 0 | AF4: =((AD4-AE4)*$B4) -> 0 | AG4: 0 | AI4: =+AG4+AH4 -> 0 | AJ4: =+AI4-AL4 -> 0 | AK4: =((AI4-AJ4)*$B4) -> 0 | AL4: 0 | AN4: =+AL4+AM4 -> 0 | AO4: =+AN4-AQ4 -> 0 | AP4: =((AN4-AO4)*$B4) -> 0 | AQ4: 0 | AS4: =+AQ4+AR4 -> 0 | AT4: =+AS4-AV4 -> 0 | AU4: =((AS4-AT4)*$B4) -> 0 | AX4: =+AV4+AW4 -> 0 | AY4: =+AX4-BA4 -> 0 | AZ4: =((AX4-AY4)*$B4) -> 0 | BC4: =+BA4+BB4 -> 0 | BD4: =+BC4-BF4 -> 0 | BE4: =((BC4-BD4)*$B4) -> 0 | BH4: =+BF4+BG4 -> 0 | BI4: =+BH4-BK4 -> 0 | BJ4: =((BH4-BI4)*$B4) -> 0
A5: TÓNICO DE ROMERO | B5: 33000 | AD5: =+AB5+AC5 -> 0 | AE5: =+AD5-AG5 -> -2 | AF5: =((AD5-AE5)*$B5) -> 66000 | AG5: 2 | AI5: =+AG5+AH5 -> 2 | AJ5: =+AI5-AL5 -> 0 | AK5: =((AI5-AJ5)*$B5) -> 66000 | AL5: 2 | AM5: 2 | AN5: =+AL5+AM5 -> 4 | AO5: =+AN5-AQ5 -> 0 | AP5: =((AN5-AO5)*$B5) -> 132000 | AQ5: 4 | AS5: =+AQ5+AR5 -> 4 | AT5: =+AS5-AV5 -> 4 | AU5: =((AS5-AT5)*$B5) -> 0 | AX5: =+AV5+AW5 -> 0 | AY5: =+AX5-BA5 -> 0 | AZ5: =((AX5-AY5)*$B5) -> 0 | BC5: =+BA5+BB5 -> 0 | BD5: =+BC5-BF5 -> 0 | BE5: =((BC5-BD5)*$B5) -> 0 | BH5: =+BF5+BG5 -> 0 | BI5: =+BH5-BK5 -> 0 | BJ5: =((BH5-BI5)*$B5) -> 0
A6: TERMOPROTECTOR | B6: 32000 | AD6: =+AB6+AC6 -> 0 | AE6: =+AD6-AG6 -> -4 | AF6: =((AD6-AE6)*$B6) -> 128000 | AG6: 4 | AI6: =+AG6+AH6 -> 4 | AJ6: =+AI6-AL6 -> 2 | AK6: =((AI6-AJ6)*$B6) -> 64000 | AL6: 2 | AM6: 6 | AN6: =+AL6+AM6 -> 8 | AO6: =+AN6-AQ6 -> 0 | AP6: =((AN6-AO6)*$B6) -> 256000 | AQ6: 8 | AS6: =+AQ6+AR6 -> 8 | AT6: =+AS6-AV6 -> 8 | AU6: =((AS6-AT6)*$B6) -> 0 | AX6: =+AV6+AW6 -> 0 | AY6: =+AX6-BA6 -> 0 | AZ6: =((AX6-AY6)*$B6) -> 0 | BC6: =+BA6+BB6 -> 0 | BD6: =+BC6-BF6 -> 0 | BE6: =((BC6-BD6)*$B6) -> 0 | BH6: =+BF6+BG6 -> 0 | BI6: =+BH6-BK6 -> 0 | BJ6: =((BH6-BI6)*$B6) -> 0
A7: CÓLAGENO + BIOTINA | B7: 45000 | AD7: =+AB7+AC7 -> 0 | AE7: =+AD7-AG7 -> 0 | AF7: =((AD7-AE7)*$B7) -> 0 | AG7: 0 | AI7: =+AG7+AH7 -> 0 | AJ7: =+AI7-AL7 -> 0 | AK7: =((AI7-AJ7)*$B7) -> 0 | AL7: 0 | AN7: =+AL7+AM7 -> 0 | AO7: =+AN7-AQ7 -> 0 | AP7: =((AN7-AO7)*$B7) -> 0 | AQ7: 0 | AR7: 1 | AS7: =+AQ7+AR7 -> 1 | AT7: =+AS7-AV7 -> 1 | AU7: =((AS7-AT7)*$B7) -> 0 | AX7: =+AV7+AW7 -> 0 | AY7: =+AX7-BA7 -> 0 | AZ7: =((AX7-AY7)*$B7) -> 0 | BC7: =+BA7+BB7 -> 0 | BD7: =+BC7-BF7 -> 0 | BE7: =((BC7-BD7)*$B7) -> 0 | BH7: =+BF7+BG7 -> 0 | BI7: =+BH7-BK7 -> 0 | BJ7: =((BH7-BI7)*$B7) -> 0
A8: SH. CEBOLLLA | B8: 30000 | AD8: =+AB8+AC8 -> 0 | AE8: =+AD8-AG8 -> -5 | AF8: =((AD8-AE8)*$B8) -> 150000 | AG8: 5 | AI8: =+AG8+AH8 -> 5 | AJ8: =+AI8-AL8 -> 1 | AK8: =((AI8-AJ8)*$B8) -> 120000 | AL8: 4 | AM8: 3 | AN8: =+AL8+AM8 -> 7 | AO8: =+AN8-AQ8 -> 0 | AP8: =((AN8-AO8)*$B8) -> 210000 | AQ8: 7 | AS8: =+AQ8+AR8 -> 7 | AT8: =+AS8-AV8 -> 7 | AU8: =((AS8-AT8)*$B8) -> 0 | AX8: =+AV8+AW8 -> 0 | AY8: =+AX8-BA8 -> 0 | AZ8: =((AX8-AY8)*$B8) -> 0 | BC8: =+BA8+BB8 -> 0 | BD8: =+BC8-BF8 -> 0 | BE8: =((BC8-BD8)*$B8) -> 0 | BH8: =+BF8+BG8 -> 0 | BI8: =+BH8-BK8 -> 0 | BJ8: =((BH8-BI8)*$B8) -> 0
A9: SH. ROMERO | B9: 30000 | AD9: =+AB9+AC9 -> 0 | AE9: =+AD9-AG9 -> -5 | AF9: =((AD9-AE9)*$B9) -> 150000 | AG9: 5 | AI9: =+AG9+AH9 -> 5 | AJ9: =+AI9-AL9 -> 2 | AK9: =((AI9-AJ9)*$B9) -> 90000 | AL9: 3 | AM9: 6 | AN9: =+AL9+AM9 -> 9 | AO9: =+AN9-AQ9 -> 1 | AP9: =((AN9-AO9)*$B9) -> 240000 | AQ9: 8 | AR9: 4 | AS9: =+AQ9+AR9 -> 12 | AT9: =+AS9-AV9 -> 12 | AU9: =((AS9-AT9)*$B9) -> 0 | AX9: =+AV9+AW9 -> 0 | AY9: =+AX9-BA9 -> 0 | AZ9: =((AX9-AY9)*$B9) -> 0 | BC9: =+BA9+BB9 -> 0 | BD9: =+BC9-BF9 -> 0 | BE9: =((BC9-BD9)*$B9) -> 0 | BH9: =+BF9+BG9 -> 0 | BI9: =+BH9-BK9 -> 0 | BJ9: =((BH9-BI9)*$B9) -> 0
A10: SH. REESTRUCTURANTE | B10: 30000 | AD10: =+AB10+AC10 -> 0 | AE10: =+AD10-AG10 -> -2 | AF10: =((AD10-AE10)*$B10) -> 60000 | AG10: 2 | AI10: =+AG10+AH10 -> 2 | AJ10: =+AI10-AL10 -> 1 | AK10: =((AI10-AJ10)*$B10) -> 30000 | AL10: 1 | AM10: 6 | AN10: =+AL10+AM10 -> 7 | AO10: =+AN10-AQ10 -> 0 | AP10: =((AN10-AO10)*$B10) -> 210000 | AQ10: 7 | AS10: =+AQ10+AR10 -> 7 | AT10: =+AS10-AV10 -> 7 | AU10: =((AS10-AT10)*$B10) -> 0 | AX10: =+AV10+AW10 -> 0 | AY10: =+AX10-BA10 -> 0 | AZ10: =((AX10-AY10)*$B10) -> 0 | BC10: =+BA10+BB10 -> 0 | BD10: =+BC10-BF10 -> 0 | BE10: =((BC10-BD10)*$B10) -> 0 | BH10: =+BF10+BG10 -> 0 | BI10: =+BH10-BK10 -> 0 | BJ10: =((BH10-BI10)*$B10) -> 0
A11: SH. EN SECO | B11: 43000 | AD11: =+AB11+AC11 -> 0 | AE11: =+AD11-AG11 -> -1 | AF11: =((AD11-AE11)*$B11) -> 43000 | AG11: 1 | AI11: =+AG11+AH11 -> 1 | AJ11: =+AI11-AL11 -> 0 | AK11: =((AI11-AJ11)*$B11) -> 43000 | AL11: 1 | AN11: =+AL11+AM11 -> 1 | AO11: =+AN11-AQ11 -> 0 | AP11: =((AN11-AO11)*$B11) -> 43000 | AQ11: 1 | AS11: =+AQ11+AR11 -> 1 | AT11: =+AS11-AV11 -> 1 | AU11: =((AS11-AT11)*$B11) -> 0 | AX11: =+AV11+AW11 -> 0 | AY11: =+AX11-BA11 -> 0 | AZ11: =((AX11-AY11)*$B11) -> 0 | BC11: =+BA11+BB11 -> 0 | BD11: =+BC11-BF11 -> 0 | BE11: =((BC11-BD11)*$B11) -> 0 | BH11: =+BF11+BG11 -> 0 | BI11: =+BH11-BK11 -> 0 | BJ11: =((BH11-BI11)*$B11) -> 0
A12: BRILLO DE SEDA 500ML | B12: 30000 | AD12: =+AB12+AC12 -> 0 | AE12: =+AD12-AG12 -> -4 | AF12: =((AD12-AE12)*$B12) -> 120000 | AG12: 4 | AI12: =+AG12+AH12 -> 4 | AJ12: =+AI12-AL12 -> 4 | AK12: =((AI12-AJ12)*$B12) -> 0 | AL12: 0 | AM12: 6 | AN12: =+AL12+AM12 -> 6 | AO12: =+AN12-AQ12 -> 1 | AP12: =((AN12-AO12)*$B12) -> 150000 | AQ12: 5 | AR12: 4 | AS12: =+AQ12+AR12 -> 9 | AT12: =+AS12-AV12 -> 9 | AU12: =((AS12-AT12)*$B12) -> 0 | AX12: =+AV12+AW12 -> 0 | AY12: =+AX12-BA12 -> 0 | AZ12: =((AX12-AY12)*$B12) -> 0 | BC12: =+BA12+BB12 -> 0 | BD12: =+BC12-BF12 -> 0 | BE12: =((BC12-BD12)*$B12) -> 0 | BH12: =+BF12+BG12 -> 0 | BI12: =+BH12-BK12 -> 0 | BJ12: =((BH12-BI12)*$B12) -> 0
A13: MASCARILLA DE CHOCOLATE | B13: 30000 | AD13: =+AB13+AC13 -> 0 | AE13: =+AD13-AG13 -> -4 | AF13: =((AD13-AE13)*$B13) -> 120000 | AG13: 4 | AI13: =+AG13+AH13 -> 4 | AJ13: =+AI13-AL13 -> 2 | AK13: =((AI13-AJ13)*$B13) -> 60000 | AL13: 2 | AM13: 6 | AN13: =+AL13+AM13 -> 8 | AO13: =+AN13-AQ13 -> 2 | AP13: =((AN13-AO13)*$B13) -> 180000 | AQ13: 6 | AS13: =+AQ13+AR13 -> 6 | AT13: =+AS13-AV13 -> 6 | AU13: =((AS13-AT13)*$B13) -> 0 | AX13: =+AV13+AW13 -> 0 | AY13: =+AX13-BA13 -> 0 | AZ13: =((AX13-AY13)*$B13) -> 0 | BC13: =+BA13+BB13 -> 0 | BD13: =+BC13-BF13 -> 0 | BE13: =((BC13-BD13)*$B13) -> 0 | BH13: =+BF13+BG13 -> 0 | BI13: =+BH13-BK13 -> 0 | BJ13: =((BH13-BI13)*$B13) -> 0
A14: PROTECTOR PISCINA Y MAR | B14: 30500 | AD14: =+AB14+AC14 -> 0 | AE14: =+AD14-AG14 -> -2 | AF14: =((AD14-AE14)*$B14) -> 61000 | AG14: 2 | AI14: =+AG14+AH14 -> 2 | AJ14: =+AI14-AL14 -> 0 | AK14: =((AI14-AJ14)*$B14) -> 61000 | AL14: 2 | AM14: 6 | AN14: =+AL14+AM14 -> 8 | AO14: =+AN14-AQ14 -> 2 | AP14: =((AN14-AO14)*$B14) -> 183000 | AQ14: 6 | AS14: =+AQ14+AR14 -> 6 | AT14: =+AS14-AV14 -> 6 | AU14: =((AS14-AT14)*$B14) -> 0 | AX14: =+AV14+AW14 -> 0 | AY14: =+AX14-BA14 -> 0 | AZ14: =((AX14-AY14)*$B14) -> 0 | BC14: =+BA14+BB14 -> 0 | BD14: =+BC14-BF14 -> 0 | BE14: =((BC14-BD14)*$B14) -> 0 | BH14: =+BF14+BG14 -> 0 | BI14: =+BH14-BK14 -> 0 | BJ14: =((BH14-BI14)*$B14) -> 0
A15: KIT ALISADO ENJUAGABLE 250ML | B15: 150000 | AD15: =+AB15+AC15 -> 0 | AE15: =+AD15-AG15 -> 0 | AF15: =((AD15-AE15)*$B15) -> 0 | AG15: 0 | AI15: =+AG15+AH15 -> 0 | AJ15: =+AI15-AL15 -> 0 | AK15: =((AI15-AJ15)*$B15) -> 0 | AL15: 0 | AN15: =+AL15+AM15 -> 0 | AO15: =+AN15-AQ15 -> 0 | AP15: =((AN15-AO15)*$B15) -> 0 | AQ15: 0 | AS15: =+AQ15+AR15 -> 0 | AT15: =+AS15-AV15 -> 0 | AU15: =((AS15-AT15)*$B15) -> 0 | AX15: =+AV15+AW15 -> 0 | AY15: =+AX15-BA15 -> 0 | AZ15: =((AX15-AY15)*$B15) -> 0 | BC15: =+BA15+BB15 -> 0 | BD15: =+BC15-BF15 -> 0 | BE15: =((BC15-BD15)*$B15) -> 0 | BH15: =+BF15+BG15 -> 0 | BI15: =+BH15-BK15 -> 0 | BJ15: =((BH15-BI15)*$B15) -> 0
A16: KIT ALISADO ENJUAGABLE 500ML | B16: 180000 | AD16: =+AB16+AC16 -> 0 | AE16: =+AD16-AG16 -> 0 | AF16: =((AD16-AE16)*$B16) -> 0 | AG16: 0 | AI16: =+AG16+AH16 -> 0 | AJ16: =+AI16-AL16 -> 0 | AK16: =((AI16-AJ16)*$B16) -> 0 | AL16: 0 | AN16: =+AL16+AM16 -> 0 | AO16: =+AN16-AQ16 -> 0 | AP16: =((AN16-AO16)*$B16) -> 0 | AQ16: 0 | AR16: 1 | AS16: =+AQ16+AR16 -> 1 | AT16: =+AS16-AV16 -> 1 | AU16: =((AS16-AT16)*$B16) -> 0 | AX16: =+AV16+AW16 -> 0 | AY16: =+AX16-BA16 -> 0 | AZ16: =((AX16-AY16)*$B16) -> 0 | BC16: =+BA16+BB16 -> 0 | BD16: =+BC16-BF16 -> 0 | BE16: =((BC16-BD16)*$B16) -> 0 | BH16: =+BF16+BG16 -> 0 | BI16: =+BH16-BK16 -> 0 | BJ16: =((BH16-BI16)*$B16) -> 0
A17: KIT ALISADO ENJUAGABLE 1000ML | B17: 285000 | AD17: =+AB17+AC17 -> 0 | AE17: =+AD17-AG17 -> 0 | AF17: =((AD17-AE17)*$B17) -> 0 | AG17: 0 | AI17: =+AG17+AH17 -> 0 | AJ17: =+AI17-AL17 -> 0 | AK17: =((AI17-AJ17)*$B17) -> 0 | AL17: 0 | AN17: =+AL17+AM17 -> 0 | AO17: =+AN17-AQ17 -> 0 | AP17: =((AN17-AO17)*$B17) -> 0 | AQ17: 0 | AR17: 1 | AS17: =+AQ17+AR17 -> 1 | AT17: =+AS17-AV17 -> 1 | AU17: =((AS17-AT17)*$B17) -> 0 | AX17: =+AV17+AW17 -> 0 | AY17: =+AX17-BA17 -> 0 | AZ17: =((AX17-AY17)*$B17) -> 0 | BC17: =+BA17+BB17 -> 0 | BD17: =+BC17-BF17 -> 0 | BE17: =((BC17-BD17)*$B17) -> 0 | BH17: =+BF17+BG17 -> 0 | BI17: =+BH17-BK17 -> 0 | BJ17: =((BH17-BI17)*$B17) -> 0
A18: SH. ANTIRESIDUOS 500ML | B18: 33000 | AD18: =+AB18+AC18 -> 0 | AE18: =+AD18-AG18 -> 0 | AF18: =((AD18-AE18)*$B18) -> 0 | AG18: 0 | AI18: =+AG18+AH18 -> 0 | AJ18: =+AI18-AL18 -> 0 | AK18: =((AI18-AJ18)*$B18) -> 0 | AL18: 0 | AN18: =+AL18+AM18 -> 0 | AO18: =+AN18-AQ18 -> 0 | AP18: =((AN18-AO18)*$B18) -> 0 | AQ18: 0 | AS18: =+AQ18+AR18 -> 0 | AT18: =+AS18-AV18 -> 0 | AU18: =((AS18-AT18)*$B18) -> 0 | AX18: =+AV18+AW18 -> 0 | AY18: =+AX18-BA18 -> 0 | AZ18: =((AX18-AY18)*$B18) -> 0 | BC18: =+BA18+BB18 -> 0 | BD18: =+BC18-BF18 -> 0 | BE18: =((BC18-BD18)*$B18) -> 0 | BH18: =+BF18+BG18 -> 0 | BI18: =+BH18-BK18 -> 0 | BJ18: =((BH18-BI18)*$B18) -> 0
A19: SH. ANTIRESIDUOS 250ML | B19: 17000 | AD19: =+AB19+AC19 -> 0 | AE19: =+AD19-AG19 -> 0 | AF19: =((AD19-AE19)*$B19) -> 0 | AG19: 0 | AI19: =+AG19+AH19 -> 0 | AJ19: =+AI19-AL19 -> 0 | AK19: =((AI19-AJ19)*$B19) -> 0 | AL19: 0 | AN19: =+AL19+AM19 -> 0 | AO19: =+AN19-AQ19 -> 0 | AP19: =((AN19-AO19)*$B19) -> 0 | AQ19: 0 | AS19: =+AQ19+AR19 -> 0 | AT19: =+AS19-AV19 -> 0 | AU19: =((AS19-AT19)*$B19) -> 0 | AX19: =+AV19+AW19 -> 0 | AY19: =+AX19-BA19 -> 0 | AZ19: =((AX19-AY19)*$B19) -> 0 | BC19: =+BA19+BB19 -> 0 | BD19: =+BC19-BF19 -> 0 | BE19: =((BC19-BD19)*$B19) -> 0 | BH19: =+BF19+BG19 -> 0 | BI19: =+BH19-BK19 -> 0 | BJ19: =((BH19-BI19)*$B19) -> 0
A20: BRILLO DE SEDA 250ML | B20: 23000 | AD20: =+AB20+AC20 -> 0 | AE20: =+AD20-AG20 -> 0 | AF20: =((AD20-AE20)*$B20) -> 0 | AG20: 0 | AI20: =+AG20+AH20 -> 0 | AJ20: =+AI20-AL20 -> 0 | AK20: =((AI20-AJ20)*$B20) -> 0 | AL20: 0 | AN20: =+AL20+AM20 -> 0 | AO20: =+AN20-AQ20 -> 0 | AP20: =((AN20-AO20)*$B20) -> 0 | AQ20: 0 | AS20: =+AQ20+AR20 -> 0 | AT20: =+AS20-AV20 -> 0 | AU20: =((AS20-AT20)*$B20) -> 0 | AX20: =+AV20+AW20 -> 0 | AY20: =+AX20-BA20 -> 0 | AZ20: =((AX20-AY20)*$B20) -> 0 | BC20: =+BA20+BB20 -> 0 | BD20: =+BC20-BF20 -> 0 | BE20: =((BC20-BD20)*$B20) -> 0 | BH20: =+BF20+BG20 -> 0 | BI20: =+BH20-BK20 -> 0 | BJ20: =((BH20-BI20)*$B20) -> 0
A21: ALISADO 250ML | B21: 110000 | AD21: =+AB21+AC21 -> 0 | AE21: =+AD21-AG21 -> 0 | AF21: =((AD21-AE21)*$B21) -> 0 | AG21: 0 | AI21: =+AG21+AH21 -> 0 | AJ21: =+AI21-AL21 -> 0 | AK21: =((AI21-AJ21)*$B21) -> 0 | AL21: 0 | AN21: =+AL21+AM21 -> 0 | AO21: =+AN21-AQ21 -> 0 | AP21: =((AN21-AO21)*$B21) -> 0 | AQ21: 0 | AS21: =+AQ21+AR21 -> 0 | AT21: =+AS21-AV21 -> 0 | AU21: =((AS21-AT21)*$B21) -> 0 | AX21: =+AV21+AW21 -> 0 | AY21: =+AX21-BA21 -> 0 | AZ21: =((AX21-AY21)*$B21) -> 0 | BC21: =+BA21+BB21 -> 0 | BD21: =+BC21-BF21 -> 0 | BE21: =((BC21-BD21)*$B21) -> 0 | BH21: =+BF21+BG21 -> 0 | BI21: =+BH21-BK21 -> 0 | BJ21: =((BH21-BI21)*$B21) -> 0
A22: ALISADO 500ML | B22: 140000 | AD22: =+AB22+AC22 -> 0 | AE22: =+AD22-AG22 -> 0 | AF22: =((AD22-AE22)*$B22) -> 0 | AG22: 0 | AI22: =+AG22+AH22 -> 0 | AJ22: =+AI22-AL22 -> 0 | AK22: =((AI22-AJ22)*$B22) -> 0 | AL22: 0 | AN22: =+AL22+AM22 -> 0 | AO22: =+AN22-AQ22 -> 0 | AP22: =((AN22-AO22)*$B22) -> 0 | AQ22: 0 | AS22: =+AQ22+AR22 -> 0 | AT22: =+AS22-AV22 -> 0 | AU22: =((AS22-AT22)*$B22) -> 0 | AX22: =+AV22+AW22 -> 0 | AY22: =+AX22-BA22 -> 0 | AZ22: =((AX22-AY22)*$B22) -> 0 | BC22: =+BA22+BB22 -> 0 | BD22: =+BC22-BF22 -> 0 | BE22: =((BC22-BD22)*$B22) -> 0 | BH22: =+BF22+BG22 -> 0 | BI22: =+BH22-BK22 -> 0 | BJ22: =((BH22-BI22)*$B22) -> 0
A23: ALISADO 1000ML | B23: 222000 | AD23: =+AB23+AC23 -> 0 | AE23: =+AD23-AG23 -> 0 | AF23: =((AD23-AE23)*$B23) -> 0 | AG23: 0 | AI23: =+AG23+AH23 -> 0 | AJ23: =+AI23-AL23 -> 0 | AK23: =((AI23-AJ23)*$B23) -> 0 | AL23: 0 | AN23: =+AL23+AM23 -> 0 | AO23: =+AN23-AQ23 -> 0 | AP23: =((AN23-AO23)*$B23) -> 0 | AQ23: 0 | AS23: =+AQ23+AR23 -> 0 | AT23: =+AS23-AV23 -> 0 | AU23: =((AS23-AT23)*$B23) -> 0 | AX23: =+AV23+AW23 -> 0 | AY23: =+AX23-BA23 -> 0 | AZ23: =((AX23-AY23)*$B23) -> 0 | BC23: =+BA23+BB23 -> 0 | BD23: =+BC23-BF23 -> 0 | BE23: =((BC23-BD23)*$B23) -> 0 | BH23: =+BF23+BG23 -> 0 | BI23: =+BH23-BK23 -> 0 | BJ23: =((BH23-BI23)*$B23) -> 0
A24: BOTOX | B24: 11500 | AD24: =+AB24+AC24 -> 0 | AE24: =+AD24-AG24 -> -6 | AF24: =((AD24-AE24)*$B24) -> 69000 | AG24: 6 | AI24: =+AG24+AH24 -> 6 | AJ24: =+AI24-AL24 -> 0 | AK24: =((AI24-AJ24)*$B24) -> 69000 | AL24: 6 | AM24: 8 | AN24: =+AL24+AM24 -> 14 | AO24: =+AN24-AQ24 -> 0 | AP24: =((AN24-AO24)*$B24) -> 161000 | AQ24: 14 | AS24: =+AQ24+AR24 -> 14 | AT24: =+AS24-AV24 -> 14 | AU24: =((AS24-AT24)*$B24) -> 0 | AX24: =+AV24+AW24 -> 0 | AY24: =+AX24-BA24 -> 0 | AZ24: =((AX24-AY24)*$B24) -> 0 | BC24: =+BA24+BB24 -> 0 | BD24: =+BC24-BF24 -> 0 | BE24: =((BC24-BD24)*$B24) -> 0 | BH24: =+BF24+BG24 -> 0 | BI24: =+BH24-BK24 -> 0 | BJ24: =((BH24-BI24)*$B24) -> 0
G25: =+SUM(G3:G24) -> 0 | L25: =+SUM(L3:L24) -> 0 | Q25: =+SUM(Q3:Q24) -> 0 | V25: =+SUM(V3:V24) -> 0 | AA25: =+SUM(AA3:AA24) -> 0 | AF25: =+SUM(AF3:AF24) -> 967000 | AK25: =+SUM(AK6:AK24) -> 537000 | AP25: =+SUM(AP3:AP24) -> 1963000 | AU25: =+SUM(AU3:AU24) -> 0 | AZ25: =+SUM(AZ3:AZ24) -> 0 | BE25: =+SUM(BE3:BE24) -> 0 | BJ25: =+SUM(BJ3:BJ24) -> 0

Sheet PO
A1: LA POCIÓN | C1: ENERO | H1: FEBRERO | M1: MARZO | R1: ABRIL | W1: MAYO | AB1: JUNIO | AG1: JULIO | AL1: AGOSTO | AQ1: SEPTIEMBRE | AV1: OCTUBRE | BA1: NOVIEMBRE | BF1: DICIEMBRE | BK1: ENERO
A2: PRODUCTO | B2: VR. COMPRA | C2: INV.I | D2: Entra | E2: Saldo | F2: SALIDA | G2: TOTAL | H2: INV.I | I2: Entra | J2: Saldo | K2: SALIDA | L2: TOTAL | M2: INV.I | N2: Entra | O2: Saldo | P2: SALIDA | Q2: TOTAL | R2: INV.I | S2: Entra | T2: Saldo | U2: SALIDA | V2: TOTAL | W2: INV.I | X2: Entra | Y2: Saldo | Z2: SALIDA | AA2: TOTAL | AB2: INV.I | AC2: Entra | AD2: Saldo | AE2: SALIDA | AF2: TOTAL | AG2: INV.I | AH2: Entra | AI2: Saldo | AJ2: SALIDA | AK2: TOTAL | AL2: INV.I | AM2: Entra | AN2: Saldo | AO2: SALIDA | AP2: TOTAL | AQ2: INV.I | AR2: Entra | AS2: Saldo | AT2: SALIDA | AU2: TOTAL | AV2: INV.I | AW2: Entra | AX2: Saldo | AY2: SALIDA | AZ2: TOTAL | BA2: INV.I | BB2: Entra | BC2: Saldo | BD2: SALIDA | BE2: TOTAL | BF2: INV.I | BG2: Entra | BH2: Saldo | BI2: SALIDA | BJ2: TOTAL | BK2: INV.I
A3: SHAMPOO LA POCION | B3: 28387 | AE3: =+AD3-AG3 -> -67 | AF3: =((AD3-AE3)*$B3) -> 1901929 | AG3: 67 | AI3: =+AG3+AH3 -> 67 | AJ3: =+AI3-AL3 -> 0 | AK3: =((AI3-AJ3)*$B3) -> 1901929 | AL3: 67 | AN3: =+AL3+AM3 -> 67 | AO3: =+AN3-AQ3 -> 4 | AP3: =((AN3-AO3)*$B3) -> 1788381 | AQ3: 63 | AS3: =+AQ3+AR3 -> 63 | AT3: =+AS3-AV3 -> 63 | AU3: =((AS3-AT3)*$B3) -> 0 | AX3: =+AV3+AW3 -> 0 | AY3: =+AX3-BA3 -> 0 | AZ3: =((AX3-AY3)*$B3) -> 0 | BC3: =+BA3+BB3 -> 0 | BD3: =+BC3-BF3 -> 0 | BE3: =((BC3-BD3)*$B3) -> 0 | BH3: =+BF3+BG3 -> 0 | BI3: =+BH3-BK3 -> 0 | BJ3: =((BH3-BI3)*$B3) -> 0
A4: TRATAMIENTO AC LA POCION | B4: 28387 | AE4: =+AD4-AG4 -> -22 | AF4: =((AD4-AE4)*$B4) -> 624514 | AG4: 22 | AI4: =+AG4+AH4 -> 22 | AJ4: =+AI4-AL4 -> 0 | AK4: =((AI4-AJ4)*$B4) -> 624514 | AL4: 22 | AN4: =+AL4+AM4 -> 22 | AO4: =+AN4-AQ4 -> 5 | AP4: =((AN4-AO4)*$B4) -> 482579 | AQ4: 17 | AS4: =+AQ4+AR4 -> 17 | AT4: =+AS4-AV4 -> 17 | AU4: =((AS4-AT4)*$B4) -> 0 | AX4: =+AV4+AW4 -> 0 | AY4: =+AX4-BA4 -> 0 | AZ4: =((AX4-AY4)*$B4) -> 0 | BC4: =+BA4+BB4 -> 0 | BD4: =+BC4-BF4 -> 0 | BE4: =((BC4-BD4)*$B4) -> 0 | BH4: =+BF4+BG4 -> 0 | BI4: =+BH4-BK4 -> 0 | BJ4: =((BH4-BI4)*$B4) -> 0
A5: DUAL CREMA PARA PEINAR | B5: 28387 | AE5: =+AD5-AG5 -> -12 | AF5: =((AD5-AE5)*$B5) -> 340644 | AG5: 12 | AI5: =+AG5+AH5 -> 12 | AJ5: =+AI5-AL5 -> 0 | AK5: =((AI5-AJ5)*$B5) -> 340644 | AL5: 12 | AN5: =+AL5+AM5 -> 12 | AO5: =+AN5-AQ5 -> 1 | AP5: =((AN5-AO5)*$B5) -> 312257 | AQ5: 11 | AS5: =+AQ5+AR5 -> 11 | AT5: =+AS5-AV5 -> 11 | AU5: =((AS5-AT5)*$B5) -> 0 | AX5: =+AV5+AW5 -> 0 | AY5: =+AX5-BA5 -> 0 | AZ5: =((AX5-AY5)*$B5) -> 0 | BC5: =+BA5+BB5 -> 0 | BD5: =+BC5-BF5 -> 0 | BE5: =((BC5-BD5)*$B5) -> 0 | BH5: =+BF5+BG5 -> 0 | BI5: =+BH5-BK5 -> 0 | BJ5: =((BH5-BI5)*$B5) -> 0
A6: ANCESTRAL MASCARILLA | B6: 29127 | AE6: =+AD6-AG6 -> -43 | AF6: =((AD6-AE6)*$B6) -> 1252461 | AG6: 43 | AI6: =+AG6+AH6 -> 43 | AJ6: =+AI6-AL6 -> 1 | AK6: =((AI6-AJ6)*$B6) -> 1223334 | AL6: 42 | AN6: =+AL6+AM6 -> 42 | AO6: =+AN6-AQ6 -> 4 | AP6: =((AN6-AO6)*$B6) -> 1106826 | AQ6: 38 | AS6: =+AQ6+AR6 -> 38 | AT6: =+AS6-AV6 -> 38 | AU6: =((AS6-AT6)*$B6) -> 0 | AX6: =+AV6+AW6 -> 0 | AY6: =+AX6-BA6 -> 0 | AZ6: =((AX6-AY6)*$B6) -> 0 | BC6: =+BA6+BB6 -> 0 | BD6: =+BC6-BF6 -> 0 | BE6: =((BC6-BD6)*$B6) -> 0 | BH6: =+BF6+BG6 -> 0 | BI6: =+BH6-BK6 -> 0 | BJ6: =((BH6-BI6)*$B6) -> 0
A7: DOYPACK SHAMPOO | B7: 25477 | AE7: =+AD7-AG7 -> -5 | AF7: =((AD7-AE7)*$B7) -> 127385 | AG7: 5 | AI7: =+AG7+AH7 -> 5 | AJ7: =+AI7-AL7 -> 0 | AK7: =((AI7-AJ7)*$B7) -> 127385 | AL7: 5 | AN7: =+AL7+AM7 -> 5 | AO7: =+AN7-AQ7 -> 1 | AP7: =((AN7-AO7)*$B7) -> 101908 | AQ7: 4 | AS7: =+AQ7+AR7 -> 4 | AT7: =+AS7-AV7 -> 4 | AU7: =((AS7-AT7)*$B7) -> 0 | AX7: =+AV7+AW7 -> 0 | AY7: =+AX7-BA7 -> 0 | AZ7: =((AX7-AY7)*$B7) -> 0 | BC7: =+BA7+BB7 -> 0 | BD7: =+BC7-BF7 -> 0 | BE7: =((BC7-BD7)*$B7) -> 0 | BH7: =+BF7+BG7 -> 0 | BI7: =+BH7-BK7 -> 0 | BJ7: =((BH7-BI7)*$B7) -> 0
A8: OLEO BRILLO INFINITO | B8: 35697 | AE8: =+AD8-AG8 -> -4 | AF8: =((AD8-AE8)*$B8) -> 142788 | AG8: 4 | AI8: =+AG8+AH8 -> 4 | AJ8: =+AI8-AL8 -> 1 | AK8: =((AI8-AJ8)*$B8) -> 107091 | AL8: 3 | AN8: =+AL8+AM8 -> 3 | AO8: =+AN8-AQ8 -> 1 | AP8: =((AN8-AO8)*$B8) -> 71394 | AQ8: 2 | AS8: =+AQ8+AR8 -> 2 | AT8: =+AS8-AV8 -> 2 | AU8: =((AS8-AT8)*$B8) -> 0 | AX8: =+AV8+AW8 -> 0 | AY8: =+AX8-BA8 -> 0 | AZ8: =((AX8-AY8)*$B8) -> 0 | BC8: =+BA8+BB8 -> 0 | BD8: =+BC8-BF8 -> 0 | BE8: =((BC8-BD8)*$B8) -> 0 | BH8: =+BF8+BG8 -> 0 | BI8: =+BH8-BK8 -> 0 | BJ8: =((BH8-BI8)*$B8) -> 0
A9: TERMOPROTECTOR | B9: 35697 | AE9: =+AD9-AG9 -> -2 | AF9: =((AD9-AE9)*$B9) -> 71394 | AG9: 2 | AI9: =+AG9+AH9 -> 2 | AJ9: =+AI9-AL9 -> 0 | AK9: =((AI9-AJ9)*$B9) -> 71394 | AL9: 2 | AN9: =+AL9+AM9 -> 2 | AO9: =+AN9-AQ9 -> 1 | AP9: =((AN9-AO9)*$B9) -> 35697 | AQ9: 1 | AS9: =+AQ9+AR9 -> 1 | AT9: =+AS9-AV9 -> 1 | AU9: =((AS9-AT9)*$B9) -> 0 | AX9: =+AV9+AW9 -> 0 | AY9: =+AX9-BA9 -> 0 | AZ9: =((AX9-AY9)*$B9) -> 0 | BC9: =+BA9+BB9 -> 0 | BD9: =+BC9-BF9 -> 0 | BE9: =((BC9-BD9)*$B9) -> 0 | BH9: =+BF9+BG9 -> 0 | BI9: =+BH9-BK9 -> 0 | BJ9: =((BH9-BI9)*$B9) -> 0
A10: PERFUME CAPILAR PRAIA | B10: 30587 | AE10: =+AD10-AG10 -> -2 | AF10: =((AD10-AE10)*$B10) -> 61174 | AG10: 2 | AI10: =+AG10+AH10 -> 2 | AJ10: =+AI10-AL10 -> 0 | AK10: =((AI10-AJ10)*$B10) -> 61174 | AL10: 2 | AN10: =+AL10+AM10 -> 2 | AO10: =+AN10-AQ10 -> 0 | AP10: =((AN10-AO10)*$B10) -> 61174 | AQ10: 2 | AS10: =+AQ10+AR10 -> 2 | AT10: =+AS10-AV10 -> 2 | AU10: =((AS10-AT10)*$B10) -> 0 | AX10: =+AV10+AW10 -> 0 | AY10: =+AX10-BA10 -> 0 | AZ10: =((AX10-AY10)*$B10) -> 0 | BC10: =+BA10+BB10 -> 0 | BD10: =+BC10-BF10 -> 0 | BE10: =((BC10-BD10)*$B10) -> 0 | BH10: =+BF10+BG10 -> 0 | BI10: =+BH10-BK10 -> 0 | BJ10: =((BH10-BI10)*$B10) -> 0
A11: PERFUME CAPILAR BOREAL | B11: 30587 | AE11: =+AD11-AG11 -> -9 | AF11: =((AD11-AE11)*$B11) -> 275283 | AG11: 9 | AI11: =+AG11+AH11 -> 9 | AJ11: =+AI11-AL11 -> 0 | AK11: =((AI11-AJ11)*$B11) -> 275283 | AL11: 9 | AN11: =+AL11+AM11 -> 9 | AO11: =+AN11-AQ11 -> 0 | AP11: =((AN11-AO11)*$B11) -> 275283 | AQ11: 9 | AS11: =+AQ11+AR11 -> 9 | AT11: =+AS11-AV11 -> 9 | AU11: =((AS11-AT11)*$B11) -> 0 | AX11: =+AV11+AW11 -> 0 | AY11: =+AX11-BA11 -> 0 | AZ11: =((AX11-AY11)*$B11) -> 0 | BC11: =+BA11+BB11 -> 0 | BD11: =+BC11-BF11 -> 0 | BE11: =((BC11-BD11)*$B11) -> 0 | BH11: =+BF11+BG11 -> 0 | BI11: =+BH11-BK11 -> 0 | BJ11: =((BH11-BI11)*$B11) -> 0
A12: SHAMPOO TONGOLÉ | B12: 28387 | AE12: =+AD12-AG12 -> -10 | AF12: =((AD12-AE12)*$B12) -> 283870 | AG12: 10 | AI12: =+AG12+AH12 -> 10 | AJ12: =+AI12-AL12 -> 0 | AK12: =((AI12-AJ12)*$B12) -> 283870 | AL12: 10 | AN12: =+AL12+AM12 -> 10 | AO12: =+AN12-AQ12 -> 1 | AP12: =((AN12-AO12)*$B12) -> 255483 | AQ12: 9 | AS12: =+AQ12+AR12 -> 9 | AT12: =+AS12-AV12 -> 9 | AU12: =((AS12-AT12)*$B12) -> 0 | AX12: =+AV12+AW12 -> 0 | AY12: =+AX12-BA12 -> 0 | AZ12: =((AX12-AY12)*$B12) -> 0 | BC12: =+BA12+BB12 -> 0 | BD12: =+BC12-BF12 -> 0 | BE12: =((BC12-BD12)*$B12) -> 0 | BH12: =+BF12+BG12 -> 0 | BI12: =+BH12-BK12 -> 0 | BJ12: =((BH12-BI12)*$B12) -> 0
A13: TRATAMIENTO TONGOLÉ | B13: 28387 | AE13: =+AD13-AG13 -> -20 | AF13: =((AD13-AE13)*$B13) -> 567740 | AG13: 20 | AI13: =+AG13+AH13 -> 20 | AJ13: =+AI13-AL13 -> 0 | AK13: =((AI13-AJ13)*$B13) -> 567740 | AL13: 20 | AN13: =+AL13+AM13 -> 20 | AO13: =+AN13-AQ13 -> 1 | AP13: =((AN13-AO13)*$B13) -> 539353 | AQ13: 19 | AS13: =+AQ13+AR13 -> 19 | AT13: =+AS13-AV13 -> 19 | AU13: =((AS13-AT13)*$B13) -> 0 | AX13: =+AV13+AW13 -> 0 | AY13: =+AX13-BA13 -> 0 | AZ13: =((AX13-AY13)*$B13) -> 0 | BC13: =+BA13+BB13 -> 0 | BD13: =+BC13-BF13 -> 0 | BE13: =((BC13-BD13)*$B13) -> 0 | BH13: =+BF13+BG13 -> 0 | BI13: =+BH13-BK13 -> 0 | BJ13: =((BH13-BI13)*$B13) -> 0
A14: LEAVE ON TONGOLÉ CREMA PARA PEINAR | B14: 28387 | AE14: =+AD14-AG14 -> -3 | AF14: =((AD14-AE14)*$B14) -> 85161 | AG14: 3 | AI14: =+AG14+AH14 -> 3 | AJ14: =+AI14-AL14 -> 0 | AK14: =((AI14-AJ14)*$B14) -> 85161 | AL14: 3 | AN14: =+AL14+AM14 -> 3 | AO14: =+AN14-AQ14 -> 0 | AP14: =((AN14-AO14)*$B14) -> 85161 | AQ14: 3 | AS14: =+AQ14+AR14 -> 3 | AT14: =+AS14-AV14 -> 3 | AU14: =((AS14-AT14)*$B14) -> 0 | AX14: =+AV14+AW14 -> 0 | AY14: =+AX14-BA14 -> 0 | AZ14: =((AX14-AY14)*$B14) -> 0 | BC14: =+BA14+BB14 -> 0 | BD14: =+BC14-BF14 -> 0 | BE14: =((BC14-BD14)*$B14) -> 0 | BH14: =+BF14+BG14 -> 0 | BI14: =+BH14-BK14 -> 0 | BJ14: =((BH14-BI14)*$B14) -> 0
... A22: TONICO CONTROL CASPA (70 ml) | B22: 29857 | AE22: =+AD22-AG22 -> -2 | AF22: =((AD22-AE22)*$B22) -> 59714 | AG22: 2 | AI22: =+AG22+AH22 -> 2 | AJ22: =+AI22-AL22 -> 0 | AK22: =((AI22-AJ22)*$B22) -> 59714 | AL22: 2 | AN22: =+AL22+AM22 -> 2 | AO22: =+AN22-AQ22 -> 2 | AP22: =((AN22-AO22)*$B22) -> 0 | AQ22: 0 | AS22: =+AQ22+AR22 -> 0 | AT22: =+AS22-AV22 -> 0 | AU22: =((AS22-AT22)*$B22) -> 0 | AX22: =+AV22+AW22 -> 0 | AY22: =+AX22-BA22 -> 0 | AZ22: =((AX22-AY22)*$B22) -> 0 | BC22: =+BA22+BB22 -> 0 | BD22: =+BC22-BF22 -> 0 | BE22: =((BC22-BD22)*$B22) -> 0 | BH22: =+BF22+BG22 -> 0 | BI22: =+BH22-BK22 -> 0 | BJ22: =((BH22-BI22)*$B22) -> 0
A23: R3-PLEX | B23: 47450 | AE23: =+AD23-AG23 -> -3 | AF23: =((AD23-AE23)*$B23) -> 142350 | AG23: 3 | AI23: =+AG23+AH23 -> 3 | AJ23: =+AI23-AL23 -> 0 | AK23: =((AI23-AJ23)*$B23) -> 142350 | AL23: 3 | AN23: =+AL23+AM23 -> 3 | AO23: =+AN23-AQ23 -> 0 | AP23: =((AN23-AO23)*$B23) -> 142350 | AQ23: 3
A24: ANCESTRAL MASCARILLA REFILL | B24: 26207 | AE24: =+AD24-AG24 -> 0 | AF24: =((AD24-AE24)*$B24) -> 0 | AG24: 0 | AI24: =+AG24+AH24 -> 0 | AJ24: =+AI24-AL24 -> 0 | AK24: =((AI24-AJ24)*$B24) -> 0 | AL24: 0 | AN24: =+AL24+AM24 -> 0 | AO24: =+AN24-AQ24 -> 0 | AP24: =((AN24-AO24)*$B24) -> 0 | AQ24: 0
A25: MASCARILLA TONGOLÉ REFILL | B25: 26207 | AE25: =+AD25-AG25 -> -15 | AF25: =((AD25-AE25)*$B25) -> 393105 | AG25: 15 | AI25: =+AG25+AH25 -> 15 | AJ25: =+AI25-AL25 -> 2 | AK25: =((AI25-AJ25)*$B25) -> 340691 | AL25: 13 | AN25: =+AL25+AM25 -> 13 | AO25: =+AN25-AQ25 -> 0 | AP25: =((AN25-AO25)*$B25) -> 340691 | AQ25: 13
A26: BOOSTER TRATAMIENTO CAPILAR CON ÁCIDO HIALURÓNICO | B26: 27667 | AE26: =+AD26-AG26 -> 0 | AF26: =((AD26-AE26)*$B26) -> 0 | AG26: 0 | AI26: =+AG26+AH26 -> 0 | AJ26: =+AI26-AL26 -> 0 | AK26: =((AI26-AJ26)*$B26) -> 0 | AL26: 0 | AN26: =+AL26+AM26 -> 0 | AO26: =+AN26-AQ26 -> 0 | AP26: =((AN26-AO26)*$B26) -> 0 | AQ26: 0
A27: SPORT TRATAMIENTO CAPILAR DE ULTRA PROTECCIÓN | B27: 34237 | AE27: =+AD27-AG27 -> -1 | AF27: =((AD27-AE27)*$B27) -> 34237 | AG27: 1 | AI27: =+AG27+AH27 -> 1 | AJ27: =+AI27-AL27 -> 1 | AK27: =((AI27-AJ27)*$B27) -> 0 | AL27: 0 | AN27: =+AL27+AM27 -> 0 | AO27: =+AN27-AQ27 -> 0 | AP27: =((AN27-AO27)*$B27) -> 0 | AQ27: 0
A28: SHAMPOO POCIÓN KIDS NUTRICIÓN Y PROTECCIÓN | B28: 26837 | AE28: =+AD28-AG28 -> 0 | AF28: =((AD28-AE28)*$B28) -> 0 | AG28: 0 | AI28: =+AG28+AH28 -> 0 | AJ28: =+AI28-AL28 -> 0 | AK28: =((AI28-AJ28)*$B28) -> 0 | AL28: 0 | AN28: =+AL28+AM28 -> 0 | AO28: =+AN28-AQ28 -> 0 | AP28: =((AN28-AO28)*$B28) -> 0 | AQ28: 0
A29: ACONDICIONADOR POCIÓN KIDS NUTRICIÓN Y PROTECCIÓN | B29: 26837 | AE29: =+AD29-AG29 -> -1 | AF29: =((AD29-AE29)*$B29) -> 26837 | AG29: 1 | AI29: =+AG29+AH29 -> 1 | AJ29: =+AI29-AL29 -> 0 | AK29: =((AI29-AJ29)*$B29) -> 26837 | AL29: 1 | AN29: =+AL29+AM29 -> 1 | AO29: =+AN29-AQ29 -> 0 | AP29: =((AN29-AO29)*$B29) -> 26837 | AQ29: 1
A30: SPRAY POCIÓN KIDS NUTRICIÓN Y PROTECCIÓN | B30: 21097 | AE30: =+AD30-AG30 -> 0 | AF30: =((AD30-AE30)*$B30) -> 0 | AG30: 0 | AI30: =+AG30+AH30 -> 0 | AJ30: =+AI30-AL30 -> 0 | AK30: =((AI30-AJ30)*$B30) -> 0 | AL30: 0 | AN30: =+AL30+AM30 -> 0 | AO30: =+AN30-AQ30 -> 0 | AP30: =((AN30-AO30)*$B30) -> 0 | AQ30: 0
G31: =+SUM(G3:G30) -> 0 | L31: =+SUM(L3:L30) -> 0 | Q31: =+SUM(Q3:Q30) -> 0 | V31: =+SUM(V3:V30) -> 0 | AA31: =+SUM(AA3:AA30) -> 0 | AF31: =+SUM(AF3:AF30) -> 8762867 | AK31: =+SUM(AK3:AK30) -> 8611392 | AP31: =+SUM(AP3:AP30) -> 7788583 | AU31: =+SUM(AU3:AU30) -> 0 | AZ31: =+SUM(AZ3:AZ30) -> 0 | BE31: =+SUM(BE3:BE30) -> 0 | BJ31: =+SUM(BJ3:BJ30) -> 0

Sheet LL.E
A1: LLUVIA DE ESTRELLAS | C1: ENERO | H1: FEBRERO | M1: MARZO | R1: ABRIL | W1: MAYO | AB1: JUNIO | AG1: JULIO | AL1: AGOSTO | AQ1: SEPTIEMBRE | AV1: OCTUBRE | BA1: NOVIEMBRE | BF1: DICIEMBRE | BK1: ENERO
A2: PRODUCTO | B2: VR. COMPRA | C2: INV.I | D2: Entra | E2: Saldo | F2: SALIDA | G2: TOTAL | H2: INV.I | I2: Entra | J2: Saldo | K2: SALIDA | L2: TOTAL | M2: INV.I | N2: Entra | O2: Saldo | P2: SALIDA | Q2: TOTAL | R2: INV.I | S2: Entra | T2: Saldo | U2: SALIDA | V2: TOTAL | W2: INV.I | X2: Entra | Y2: Saldo | Z2: SALIDA | AA2: TOTAL | AB2: INV.I | AC2: Entra | AD2: Saldo | AE2: SALIDA | AF2: TOTAL | AG2: INV.I | AH2: Entra | AI2: Saldo | AJ2: SALIDA | AK2: TOTAL | AL2: INV.I | AM2: Entra | AN2: Saldo | AO2: SALIDA | AP2: TOTAL | AQ2: INV.I | AR2: Entra | AS2: Saldo | AT2: SALIDA | AU2: TOTAL | AV2: INV.I | AW2: Entra | AX2: Saldo | AY2: SALIDA | AZ2: TOTAL | BA2: INV.I | BB2: Entra | BC2: Saldo | BD2: SALIDA | BE2: TOTAL | BF2: INV.I | BG2: Entra | BH2: Saldo | BI2: SALIDA | BJ2: TOTAL | BK2: INV.I
A3: MANTEQUILLA CORPORAL CON DESTELLOS | B3: 20800 | AE3: =+AD3-AG3 -> -14 | AF3: =((AD3-AE3)*$B3) -> 291200 | AG3: 14 | AI3: =+AG3+AH3 -> 14 | AJ3: =+AI3-AL3 -> 0 | AK3: =((AI3-AJ3)*$B3) -> 291200 | AL3: 14 | AN3: =+AL3+AM3 -> 14 | AO3: =+AN3-AQ3 -> 0 | AP3: =((AN3-AO3)*$B3) -> 291200 | AQ3: 14 | AS3: =+AQ3+AR3 -> 14 | AT3: =+AS3-AV3 -> 14 | AU3: =((AS3-AT3)*$B3) -> 0 | AX3: =+AV3+AW3 -> 0 | AY3: =+AX3-BA3 -> 0 | AZ3: =((AX3-AY3)*$B3) -> 0 | BC3: =+BA3+BB3 -> 0 | BD3: =+BC3-BF3 -> 0 | BE3: =((BC3-BD3)*$B3) -> 0 | BH3: =+BF3+BG3 -> 0 | BI3: =+BH3-BK3 -> 0 | BJ3: =((BH3-BI3)*$B3) -> 0
A4: MANTEQUILLA CORPORAL CON COLOR | B4: 22200 | AE4: =+AD4-AG4 -> -9 | AF4: =((AD4-AE4)*$B4) -> 199800 | AG4: 9 | AI4: =+AG4+AH4 -> 9 | AJ4: =+AI4-AL4 -> 0 | AK4: =((AI4-AJ4)*$B4) -> 199800 | AL4: 9 | AN4: =+AL4+AM4 -> 9 | AO4: =+AN4-AQ4 -> 0 | AP4: =((AN4-AO4)*$B4) -> 199800 | AQ4: 9 | AS4: =+AQ4+AR4 -> 9 | AT4: =+AS4-AV4 -> 9 | AU4: =((AS4-AT4)*$B4) -> 0 | AX4: =+AV4+AW4 -> 0 | AY4: =+AX4-BA4 -> 0 | AZ4: =((AX4-AY4)*$B4) -> 0 | BC4: =+BA4+BB4 -> 0 | BD4: =+BC4-BF4 -> 0 | BE4: =((BC4-BD4)*$B4) -> 0 | BH4: =+BF4+BG4 -> 0 | BI4: =+BH4-BK4 -> 0 | BJ4: =((BH4-BI4)*$B4) -> 0
A5: ILUMINADORES CORPORALES | B5: 12700 | AE5: =+AD5-AG5 -> -11 | AF5: =((AD5-AE5)*$B5) -> 139700 | AG5: 11 | AI5: =+AG5+AH5 -> 11 | AJ5: =+AI5-AL5 -> 0 | AK5: =((AI5-AJ5)*$B5) -> 139700 | AL5: 11 | AN5: =+AL5+AM5 -> 11 | AO5: =+AN5-AQ5 -> 0 | AP5: =((AN5-AO5)*$B5) -> 139700 | AQ5: 11 | AS5: =+AQ5+AR5 -> 11 | AT5: =+AS5-AV5 -> 11 | AU5: =((AS5-AT5)*$B5) -> 0 | AX5: =+AV5+AW5 -> 0 | AY5: =+AX5-BA5 -> 0 | AZ5: =((AX5-AY5)*$B5) -> 0 | BC5: =+BA5+BB5 -> 0 | BD5: =+BC5-BF5 -> 0 | BE5: =((BC5-BD5)*$B5) -> 0 | BH5: =+BF5+BG5 -> 0 | BI5: =+BH5-BK5 -> 0 | BJ5: =((BH5-BI5)*$B5) -> 0
A6: PERFUME PARA EL CABELLO | B6: 20500 | AE6: =+AD6-AG6 -> -6 | AF6: =((AD6-AE6)*$B6) -> 123000 | AG6: 6 | AI6: =+AG6+AH6 -> 6 | AJ6: =+AI6-AL6 -> 0 | AK6: =((AI6-AJ6)*$B6) -> 123000 | AL6: 6 | AN6: =+AL6+AM6 -> 6 | AO6: =+AN6-AQ6 -> 0 | AP6: =((AN6-AO6)*$B6) -> 123000 | AQ6: 6 | AS6: =+AQ6+AR6 -> 6 | AT6: =+AS6-AV6 -> 6 | AU6: =((AS6-AT6)*$B6) -> 0 | AX6: =+AV6+AW6 -> 0 | AY6: =+AX6-BA6 -> 0 | AZ6: =((AX6-AY6)*$B6) -> 0 | BC6: =+BA6+BB6 -> 0 | BD6: =+BC6-BF6 -> 0 | BE6: =((BC6-BD6)*$B6) -> 0 | BH6: =+BF6+BG6 -> 0 | BI6: =+BH6-BK6 -> 0 | BJ6: =((BH6-BI6)*$B6) -> 0
G7: =+SUM(G3:G6) -> 0 | L7: =+SUM(L3:L6) -> 0 | Q7: =+SUM(Q3:Q6) -> 0 | V7: =+SUM(V3:V6) -> 0 | AA7: =+SUM(AA3:AA6) -> 0 | AF7: =+SUM(AF3:AF6) -> 753700 | AK7: =+SUM(AK3:AK6) -> 753700 | AP7: =+SUM(AP3:AP6) -> 753700 | AU7: =+SUM(AU3:AU6) -> 0 | AZ7: =+SUM(AZ3:AZ6) -> 0 | BE7: =+SUM(BE3:BE6) -> 0 | BJ7: =+SUM(BJ3:BJ6) -> 0

Sheet YV
A1: YAVALVA | C1: ENERO | H1: FEBRERO | M1: MARZO | R1: ABRIL | W1: MAYO | AB1: JUNIO | AG1: JULIO | AL1: AGOSTO | AQ1: SEPTIEMBRE | AV1: OCTUBRE | BA1: NOVIEMBRE | BF1: DICIEMBRE | BK1: ENERO
A2: PRODUCTO | B2: VR. COMPRA | C2: INV.I | D2: Entra | E2: Saldo | F2: SALIDA | G2: TOTAL | H2: INV.I | I2: Entra | J2: Saldo | K2: SALIDA | L2: TOTAL | M2: INV.I | N2: Entra | O2: Saldo | P2: SALIDA | Q2: TOTAL | R2: INV.I | S2: Entra | T2: Saldo | U2: SALIDA | V2: TOTAL | W2: INV.I | X2: Entra | Y2: Saldo | Z2: SALIDA | AA2: TOTAL | AB2: INV.I | AC2: Entra | AD2: Saldo | AE2: SALIDA | AF2: TOTAL | AG2: INV.I | AH2: Entra | AI2: Saldo | AJ2: SALIDA | AK2: TOTAL | AL2: INV.I | AM2: Entra | AN2: Saldo | AO2: SALIDA | AP2: TOTAL | AQ2: INV.I | AR2: Entra | AS2: Saldo | AT2: SALIDA | AU2: TOTAL | AV2: INV.I | AW2: Entra | AX2: Saldo | AY2: SALIDA | AZ2: TOTAL | BA2: INV.I | BB2: Entra | BC2: Saldo | BD2: SALIDA | BE2: TOTAL | BF2: INV.I | BG2: Entra | BH2: Saldo | BI2: SALIDA | BJ2: TOTAL | BK2: INV.I
A3: BIO REESTRUCTURANTE X450ML | B3: 39900 | AD3: =+AB3+AC3 -> 0 | AE3: =+AD3-AG3 -> -4 | AF3: =((AD3-AE3)*$B3) -> 159600 | AG3: 4 | AI3: =+AG3+AH3 -> 4 | AJ3: =+AI3-AL3 -> 0 | AK3: =((AI3-AJ3)*$B3) -> 159600 | AL3: 4 | AN3: =+AL3+AM3 -> 4 | AO3: =+AN3-AQ3 -> 1 | AP3: =((AN3-AO3)*$B3) -> 119700 | AQ3: 3 | AS3: =+AQ3+AR3 -> 3 | AT3: =+AS3-AV3 -> 3 | AU3: =((AS3-AT3)*$B3) -> 0 | AX3: =+AV3+AW3 -> 0 | AY3: =+AX3-BA3 -> 0 | AZ3: =((AX3-AY3)*$B3) -> 0 | BC3: =+BA3+BB3 -> 0 | BD3: =+BC3-BF3 -> 0 | BE3: =((BC3-BD3)*$B3) -> 0 | BH3: =+BF3+BG3 -> 0 | BI3: =+BH3-BK3 -> 0 | BJ3: =((BH3-BI3)*$B3) -> 0
A4: Shampoo Herbal | B4: 34900 | AD4: =+AB4+AC4 -> 0 | AE4: =+AD4-AG4 -> -8 | AF4: =((AD4-AE4)*$B4) -> 279200 | AG4: 8 | AI4: =+AG4+AH4 -> 8 | AJ4: =+AI4-AL4 -> 1 | AK4: =((AI4-AJ4)*$B4) -> 244300 | AL4: 7 | AN4: =+AL4+AM4 -> 7 | AO4: =+AN4-AQ4 -> 0 | AP4: =((AN4-AO4)*$B4) -> 244300 | AQ4: 7 | AS4: =+AQ4+AR4 -> 7 | AT4: =+AS4-AV4 -> 7 | AU4: =((AS4-AT4)*$B4) -> 0 | AX4: =+AV4+AW4 -> 0 | AY4: =+AX4-BA4 -> 0 | AZ4: =((AX4-AY4)*$B4) -> 0 | BC4: =+BA4+BB4 -> 0 | BD4: =+BC4-BF4 -> 0 | BE4: =((BC4-BD4)*$B4) -> 0 | BH4: =+BF4+BG4 -> 0 | BI4: =+BH4-BK4 -> 0 | BJ4: =((BH4-BI4)*$B4) -> 0
A5: Tratamiento Natural | B5: 31900 | AD5: =+AB5+AC5 -> 0 | AE5: =+AD5-AG5 -> 0 | AF5: =((AD5-AE5)*$B5) -> 0 | AG5: 0 | AI5: =+AG5+AH5 -> 0 | AJ5: =+AI5-AL5 -> 0 | AK5: =((AI5-AJ5)*$B5) -> 0 | AL5: 0 | AN5: =+AL5+AM5 -> 0 | AO5: =+AN5-AQ5 -> 0 | AP5: =((AN5-AO5)*$B5) -> 0 | AQ5: 0 | AS5: =+AQ5+AR5 -> 0 | AT5: =+AS5-AV5 -> 0 | AU5: =((AS5-AT5)*$B5) -> 0 | AX5: =+AV5+AW5 -> 0 | AY5: =+AX5-BA5 -> 0 | AZ5: =((AX5-AY5)*$B5) -> 0 | BC5: =+BA5+BB5 -> 0 | BD5: =+BC5-BF5 -> 0 | BE5: =((BC5-BD5)*$B5) -> 0 | BH5: =+BF5+BG5 -> 0 | BI5: =+BH5-BK5 -> 0 | BJ5: =((BH5-BI5)*$B5) -> 0
A6: Serum Reestructurador Capilar | B6: 25500 | AD6: =+AB6+AC6 -> 0 | AE6: =+AD6-AG6 -> -6 | AF6: =((AD6-AE6)*$B6) -> 153000 | AG6: 6 | AI6: =+AG6+AH6 -> 6 | AJ6: =+AI6-AL6 -> 0 | AK6: =((AI6-AJ6)*$B6) -> 153000 | AL6: 6 | AN6: =+AL6+AM6 -> 6 | AO6: =+AN6-AQ6 -> 1 | AP6: =((AN6-AO6)*$B6) -> 127500 | AQ6: 5 | AS6: =+AQ6+AR6 -> 5 | AT6: =+AS6-AV6 -> 5 | AU6: =((AS6-AT6)*$B6) -> 0 | AX6: =+AV6+AW6 -> 0 | AY6: =+AX6-BA6 -> 0 | AZ6: =((AX6-AY6)*$B6) -> 0 | BC6: =+BA6+BB6 -> 0 | BD6: =+BC6-BF6 -> 0 | BE6: =((BC6-BD6)*$B6) -> 0 | BH6: =+BF6+BG6 -> 0 | BI6: =+BH6-BK6 -> 0 | BJ6: =((BH6-BI6)*$B6) -> 0
A7: Loción Bio fertilizante Cabello Rubio | B7: 32500 | AD7: =+AB7+AC7 -> 0 | AE7: =+AD7-AG7 -> -4 | AF7: =((AD7-AE7)*$B7) -> 130000 | AG7: 4 | AI7: =+AG7+AH7 -> 4 | AJ7: =+AI7-AL7 -> 2 | AK7: =((AI7-AJ7)*$B7) -> 65000 | AL7: 2 | AN7: =+AL7+AM7 -> 2 | AO7: =+AN7-AQ7 -> 0 | AP7: =((AN7-AO7)*$B7) -> 65000 | AQ7: 2 | AS7: =+AQ7+AR7 -> 2 | AT7: =+AS7-AV7 -> 2 | AU7: =((AS7-AT7)*$B7) -> 0 | AX7: =+AV7+AW7 -> 0 | AY7: =+AX7-BA7 -> 0 | AZ7: =((AX7-AY7)*$B7) -> 0 | BC7: =+BA7+BB7 -> 0 | BD7: =+BC7-BF7 -> 0 | BE7: =((BC7-BD7)*$B7) -> 0 | BH7: =+BF7+BG7 -> 0 | BI7: =+BH7-BK7 -> 0 | BJ7: =((BH7-BI7)*$B7) -> 0
A8: Loción Bio fertilizante Todo Tipo | B8: 32500 | AD8: =+AB8+AC8 -> 0 | AE8: =+AD8-AG8 -> -4 | AF8: =((AD8-AE8)*$B8) -> 130000 | AG8: 4 | AI8: =+AG8+AH8 -> 4 | AJ8: =+AI8-AL8 -> 0 | AK8: =((AI8-AJ8)*$B8) -> 130000 | AL8: 4 | AN8: =+AL8+AM8 -> 4 | AO8: =+AN8-AQ8 -> 2 | AP8: =((AN8-AO8)*$B8) -> 65000 | AQ8: 2 | AS8: =+AQ8+AR8 -> 2 | AT8: =+AS8-AV8 -> 2 | AU8: =((AS8-AT8)*$B8) -> 0 | AX8: =+AV8+AW8 -> 0 | AY8: =+AX8-BA8 -> 0 | AZ8: =((AX8-AY8)*$B8) -> 0 | BC8: =+BA8+BB8 -> 0 | BD8: =+BC8-BF8 -> 0 | BE8: =((BC8-BD8)*$B8) -> 0 | BH8: =+BF8+BG8 -> 0 | BI8: =+BH8-BK8 -> 0 | BJ8: =((BH8-BI8)*$B8) -> 0
A9: Locion bioferilizante graso | B9: 32500 | AD9: 0 | AE9: =+AD9-AG9 -> -3 | AG9: 3 | AI9: =+AG9+AH9 -> 3 | AJ9: =+AI9-AL9 -> 1 | AK9: =((AI9-AJ9)*$B9) -> 65000 | AL9: 2 | AN9: =+AL9+AM9 -> 2 | AO9: =+AN9-AQ9 -> 0 | AP9: =((AN9-AO9)*$B9) -> 65000 | AQ9: 2 | AS9: =+AQ9+AR9 -> 2 | AT9: =+AS9-AV9 -> 2 | AU9: =((AS9-AT9)*$B9) -> 0
A10: Loción Brisa Celestial | B10: 26500 | AD10: =+AB10+AC10 -> 0 | AE10: =+AD10-AG10 -> -13 | AF10: =((AD10-AE10)*$B10) -> 344500 | AG10: 13 | AI10: =+AG10+AH10 -> 13 | AJ10: =+AI10-AL10 -> 0 | AK10: =((AI10-AJ10)*$B10) -> 344500 | AL10: 13 | AN10: =+AL10+AM10 -> 13 | AO10: =+AN10-AQ10 -> 0 | AP10: =((AN10-AO10)*$B10) -> 344500 | AQ10: 13 | AS10: =+AQ10+AR10 -> 13 | AT10: =+AS10-AV10 -> 13 | AU10: =((AS10-AT10)*$B10) -> 0 | AX10: =+AV10+AW10 -> 0 | AY10: =+AX10-BA10 -> 0 | AZ10: =((AX10-AY10)*$B10) -> 0 | BC10: =+BA10+BB10 -> 0 | BD10: =+BC10-BF10 -> 0 | BE10: =((BC10-BD10)*$B10) -> 0 | BH10: =+BF10+BG10 -> 0 | BI10: =+BH10-BK10 -> 0 | BJ10: =((BH10-BI10)*$B10) -> 0
A11: Kit 3x3 Avanzado | B11: 179900 | AD11: =+AB11+AC11 -> 0 | AE11: =+AD11-AG11 -> 0 | AF11: =((AD11-AE11)*$B11) -> 0 | AG11: 0 | AI11: =+AG11+AH11 -> 0 | AJ11: =+AI11-AL11 -> 0 | AK11: =((AI11-AJ11)*$B11) -> 0 | AL11: 0 | AN11: =+AL11+AM11 -> 0 | AO11: =+AN11-AQ11 -> 0 | AP11: =((AN11-AO11)*$B11) -> 0 | AQ11: 0 | AS11: =+AQ11+AR11 -> 0 | AT11: =+AS11-AV11 -> 0 | AU11: =((AS11-AT11)*$B11) -> 0 | AX11: =+AV11+AW11 -> 0 | AY11: =+AX11-BA11 -> 0 | AZ11: =((AX11-AY11)*$B11) -> 0 | BC11: =+BA11+BB11 -> 0 | BD11: =+BC11-BF11 -> 0 | BE11: =((BC11-BD11)*$B11) -> 0 | BH11: =+BF11+BG11 -> 0 | BI11: =+BH11-BK11 -> 0 | BJ11: =((BH11-BI11)*$B11) -> 0
A12: Kit 3x3 Básico | B12: 88900 | AD12: =+AB12+AC12 -> 0 | AE12: =+AD12-AG12 -> -4 | AF12: =((AD12-AE12)*$B12) -> 355600 | AG12: 4 | AI12: =+AG12+AH12 -> 4 | AJ12: =+AI12-AL12 -> 3 | AK12: =((AI12-AJ12)*$B12) -> 88900 | AL12: 1 | AN12: =+AL12+AM12 -> 1 | AO12: =+AN12-AQ12 -> 1 | AP12: =((AN12-AO12)*$B12) -> 0 | AQ12: 0 | AS12: =+AQ12+AR12 -> 0 | AT12: =+AS12-AV12 -> 0 | AU12: =((AS12-AT12)*$B12) -> 0 | AX12: =+AV12+AW12 -> 0 | AY12: =+AX12-BA12 -> 0 | AZ12: =((AX12-AY12)*$B12) -> 0 | BC12: =+BA12+BB12 -> 0 | BD12: =+BC12-BF12 -> 0 | BE12: =((BC12-BD12)*$B12) -> 0 | BH12: =+BF12+BG12 -> 0 | BI12: =+BH12-BK12 -> 0 | BJ12: =((BH12-BI12)*$B12) -> 0
A13: Kit 3x3 Clásico | B13: 122900 | AD13: =+AB13+AC13 -> 0 | AE13: =+AD13-AG13 -> 0 | AF13: =((AD13-AE13)*$B13) -> 0 | AG13: 0 | AI13: =+AG13+AH13 -> 0 | AJ13: =+AI13-AL13 -> 0 | AK13: =((AI13-AJ13)*$B13) -> 0 | AL13: 0 | AN13: =+AL13+AM13 -> 0 | AO13: =+AN13-AQ13 -> 0 | AP13: =((AN13-AO13)*$B13) -> 0 | AQ13: 0 | AS13: =+AQ13+AR13 -> 0 | AT13: =+AS13-AV13 -> 0 | AU13: =((AS13-AT13)*$B13) -> 0 | AX13: =+AV13+AW13 -> 0 | AY13: =+AX13-BA13 -> 0 | AZ13: =((AX13-AY13)*$B13) -> 0 | BC13: =+BA13+BB13 -> 0 | BD13: =+BC13-BF13 -> 0 | BE13: =((BC13-BD13)*$B13) -> 0 | BH13: =+BF13+BG13 -> 0 | BI13: =+BH13-BK13 -> 0 | BJ13: =((BH13-BI13)*$B13) -> 0
G14: =SUM(G3:G13) -> 0 | L14: =SUM(L3:L13) -> 0 | Q14: =SUM(Q3:Q13) -> 0 | V14: =SUM(V3:V13) -> 0 | AA14: =SUM(AA3:AA13) -> 0 | AF14: =SUM(AF3:AF13) -> 1551900 | AK14: =SUM(AK3:AK13) -> 1250300 | AP14: =+SUM(AP3:AP13) -> 1031000 | AU14: =+SUM(AU3:AU13) -> 0 | AZ14: =+SUM(AZ3:AZ13) -> 0 | BE14: =+SUM(BE3:BE13) -> 0 | BJ14: =+SUM(BJ3:BJ13) -> 0

Sheet SEN
A1: SENSE | C1: ENERO | H1: FEBRERO | M1: MARZO | R1: ABRIL | W1: MAYO | AB1: JUNIO | AG1: JULIO | AL1: AGOSTO | AQ1: SEPTIEMBRE | AV1: OCTUBRE | BA1: NOVIEMBRE | BF1: DICIEMBRE | BK1: ENERO
A2: PRODUCTO | B2: VR. COMPRA | C2: INV.I | D2: Entra | E2: Saldo | F2: SALIDA | G2: TOTAL | H2: INV.I | I2: Entra | J2: Saldo | K2: SALIDA | L2: TOTAL | M2: INV.I | N2: Entra | O2: Saldo | P2: SALIDA | Q2: TOTAL | R2: INV.I | S2: Entra | T2: Saldo | U2: SALIDA | V2: TOTAL | W2: INV.I | X2: Entra | Y2: Saldo | Z2: SALIDA | AA2: TOTAL | AB2: INV.I | AC2: Entra | AD2: Saldo | AE2: SALIDA | AF2: TOTAL | AG2: INV.I | AH2: Entra | AI2: Saldo | AJ2: SALIDA | AK2: TOTAL | AL2: INV.I | AM2: Entra | AN2: Saldo | AO2: SALIDA | AP2: TOTAL | AQ2: INV.I | AR2: Entra | AS2: Saldo | AT2: SALIDA | AU2: TOTAL | AV2: INV.I | AW2: Entra | AX2: Saldo | AY2: SALIDA | AZ2: TOTAL | BA2: INV.I | BB2: Entra | BC2: Saldo | BD2: SALIDA | BE2: TOTAL | BF2: INV.I | BG2: Entra | BH2: Saldo | BI2: SALIDA | BJ2: TOTAL | BK2: INV.I
A3: SHAMPOO GRANATE | B3: 30000 | AE3: =+AD3-AG3 -> 0 | AF3: =((AD3-AE3)*$B3) -> 0 | AI3: =+AG3+AH3 -> 0 | AJ3: =+AI3-AL3 -> 0 | AK3: =((AI3-AJ3)*$B3) -> 0 | AM3: 6 | AN3: =+AL3+AM3 -> 6 | AO3: =+AN3-AQ3 -> 1 | AP3: =((AN3-AO3)*$B3) -> 150000 | AQ3: 5 | AS3: =+AQ3+AR3 -> 5 | AT3: =+AS3-AV3 -> 5 | AU3: =((AS3-AT3)*$B3) -> 0 | AX3: =+AV3+AW3 -> 0 | AY3: =+AX3-BA3 -> 0 | AZ3: =((AX3-AY3)*$B3) -> 0 | BC3: =+BA3+BB3 -> 0 | BD3: =+BC3-BF3 -> 0 | BE3: =((BC3-BD3)*$B3) -> 0 | BH3: =+BF3+BG3 -> 0 | BI3: =+BH3-BK3 -> 0 | BJ3: =((BH3-BI3)*$B3) -> 0
A4: SHAMPOO MANGO | B4: 30000 | AE4: =+AD4-AG4 -> 0 | AF4: =((AD4-AE4)*$B4) -> 0 | AI4: =+AG4+AH4 -> 0 | AJ4: =+AI4-AL4 -> 0 | AK4: =((AI4-AJ4)*$B4) -> 0 | AM4: 6 | AN4: =+AL4+AM4 -> 6 | AO4: =+AN4-AQ4 -> 1 | AP4: =((AN4-AO4)*$B4) -> 150000 | AQ4: 5 | AS4: =+AQ4+AR4 -> 5 | AT4: =+AS4-AV4 -> 5 | AU4: =((AS4-AT4)*$B4) -> 0 | AX4: =+AV4+AW4 -> 0 | AY4: =+AX4-BA4 -> 0 | AZ4: =((AX4-AY4)*$B4) -> 0 | BC4: =+BA4+BB4 -> 0 | BD4: =+BC4-BF4 -> 0 | BE4: =((BC4-BD4)*$B4) -> 0 | BH4: =+BF4+BG4 -> 0 | BI4: =+BH4-BK4 -> 0 | BJ4: =((BH4-BI4)*$B4) -> 0
A5: SHAMPOO TURQUESA | B5: 30000 | AE5: =+AD5-AG5 -> 0 | AF5: =((AD5-AE5)*$B5) -> 0 | AI5: =+AG5+AH5 -> 0 | AJ5: =+AI5-AL5 -> 0 | AK5: =((AI5-AJ5)*$B5) -> 0 | AM5: 6 | AN5: =+AL5+AM5 -> 6 | AO5: =+AN5-AQ5 -> 0 | AP5: =((AN5-AO5)*$B5) -> 180000 | AQ5: 6 | AS5: =+AQ5+AR5 -> 6 | AT5: =+AS5-AV5 -> 6 | AU5: =((AS5-AT5)*$B5) -> 0 | AX5: =+AV5+AW5 -> 0 | AY5: =+AX5-BA5 -> 0 | AZ5: =((AX5-AY5)*$B5) -> 0 | BC5: =+BA5+BB5 -> 0 | BD5: =+BC5-BF5 -> 0 | BE5: =((BC5-BD5)*$B5) -> 0 | BH5: =+BF5+BG5 -> 0 | BI5: =+BH5-BK5 -> 0 | BJ5: =((BH5-BI5)*$B5) -> 0
A6: SHAMPOO NANOTECNOLOGÍA | B6: 33000 | AE6: =+AD6-AG6 -> 0 | AF6: =((AD6-AE6)*$B6) -> 0 | AI6: =+AG6+AH6 -> 0 | AJ6: =+AI6-AL6 -> 0 | AK6: =((AI6-AJ6)*$B6) -> 0 | AM6: 6 | AN6: =+AL6+AM6 -> 6 | AO6: =+AN6-AQ6 -> 3 | AP6: =((AN6-AO6)*$B6) -> 99000 | AQ6: 3 | AS6: =+AQ6+AR6 -> 3 | AT6: =+AS6-AV6 -> 3 | AU6: =((AS6-AT6)*$B6) -> 0 | AX6: =+AV6+AW6 -> 0 | AY6: =+AX6-BA6 -> 0 | AZ6: =((AX6-AY6)*$B6) -> 0 | BC6: =+BA6+BB6 -> 0 | BD6: =+BC6-BF6 -> 0 | BE6: =((BC6-BD6)*$B6) -> 0 | BH6: =+BF6+BG6 -> 0 | BI6: =+BH6-BK6 -> 0 | BJ6: =((BH6-BI6)*$B6) -> 0
A7: ACONDICIONADOR AMATISTA | B7: 30000 | AE7: =+AD7-AG7 -> 0 | AF7: =((AD7-AE7)*$B7) -> 0 | AI7: =+AG7+AH7 -> 0 | AJ7: =+AI7-AL7 -> 0 | AK7: =((AI7-AJ7)*$B7) -> 0 | AM7: 6 | AN7: =+AL7+AM7 -> 6 | AO7: =+AN7-AQ7 -> 1 | AP7: =((AN7-AO7)*$B7) -> 150000 | AQ7: 5 | AS7: =+AQ7+AR7 -> 5 | AT7: =+AS7-AV7 -> 5 | AU7: =((AS7-AT7)*$B7) -> 0 | AX7: =+AV7+AW7 -> 0 | AY7: =+AX7-BA7 -> 0 | AZ7: =((AX7-AY7)*$B7) -> 0 | BC7: =+BA7+BB7 -> 0 | BD7: =+BC7-BF7 -> 0 | BE7: =((BC7-BD7)*$B7) -> 0 | BH7: =+BF7+BG7 -> 0 | BI7: =+BH7-BK7 -> 0 | BJ7: =((BH7-BI7)*$B7) -> 0
A8: ACONDICIONADOR MANGO | B8: 30000 | AE8: =+AD8-AG8 -> 0 | AF8: =((AD8-AE8)*$B8) -> 0 | AI8: =+AG8+AH8 -> 0 | AJ8: =+AI8-AL8 -> 0 | AK8: =((AI8-AJ8)*$B8) -> 0 | AM8: 6 | AN8: =+AL8+AM8 -> 6 | AO8: =+AN8-AQ8 -> 0 | AP8: =((AN8-AO8)*$B8) -> 180000 | AQ8: 6 | AS8: =+AQ8+AR8 -> 6 | AT8: =+AS8-AV8 -> 6 | AU8: =((AS8-AT8)*$B8) -> 0 | AX8: =+AV8+AW8 -> 0 | AY8: =+AX8-BA8 -> 0 | AZ8: =((AX8-AY8)*$B8) -> 0 | BC8: =+BA8+BB8 -> 0 | BD8: =+BC8-BF8 -> 0 | BE8: =((BC8-BD8)*$B8) -> 0 | BH8: =+BF8+BG8 -> 0 | BI8: =+BH8-BK8 -> 0 | BJ8: =((BH8-BI8)*$B8) -> 0
A9: ACONDICIONADOR TURQUESA | B9: 30000 | AE9: =+AD9-AG9 -> 0 | AF9: =((AD9-AE9)*$B9) -> 0 | AI9: =+AG9+AH9 -> 0 | AJ9: =+AI9-AL9 -> 0 | AK9: =((AI9-AJ9)*$B9) -> 0 | AM9: 6 | AN9: =+AL9+AM9 -> 6 | AO9: =+AN9-AQ9 -> 0 | AP9: =((AN9-AO9)*$B9) -> 180000 | AQ9: 6 | AS9: =+AQ9+AR9 -> 6 | AT9: =+AS9-AV9 -> 6 | AU9: =((AS9-AT9)*$B9) -> 0 | AX9: =+AV9+AW9 -> 0 | AY9: =+AX9-BA9 -> 0 | AZ9: =((AX9-AY9)*$B9) -> 0 | BC9: =+BA9+BB9 -> 0 | BD9: =+BC9-BF9 -> 0 | BE9: =((BC9-BD9)*$B9) -> 0 | BH9: =+BF9+BG9 -> 0 | BI9: =+BH9-BK9 -> 0 | BJ9: =((BH9-BI9)*$B9) -> 0
A10: TRATAMIENTO NANOTECNOLOGÍA | B10: 33000 | AE10: =+AD10-AG10 -> 0 | AF10: =((AD10-AE10)*$B10) -> 0 | AI10: =+AG10+AH10 -> 0 | AJ10: =+AI10-AL10 -> 0 | AK10: =((AI10-AJ10)*$B10) -> 0 | AM10: 6 | AN10: =+AL10+AM10 -> 6 | AO10: =+AN10-AQ10 -> 3 | AP10: =((AN10-AO10)*$B10) -> 99000 | AQ10: 3 | AS10: =+AQ10+AR10 -> 3 | AT10: =+AS10-AV10 -> 3 | AU10: =((AS10-AT10)*$B10) -> 0 | AX10: =+AV10+AW10 -> 0 | AY10: =+AX10-BA10 -> 0 | AZ10: =((AX10-AY10)*$B10) -> 0 | BC10: =+BA10+BB10 -> 0 | BD10: =+BC10-BF10 -> 0 | BE10: =((BC10-BD10)*$B10) -> 0 | BH10: =+BF10+BG10 -> 0 | BI10: =+BH10-BK10 -> 0 | BJ10: =((BH10-BI10)*$B10) -> 0
A11: MASCARILLA RESCUE 21 | B11: 53000 | AE11: =+AD11-AG11 -> 0 | AF11: =((AD11-AE11)*$B11) -> 0 | AI11: =+AG11+AH11 -> 0 | AJ11: =+AI11-AL11 -> 0 | AK11: =((AI11-AJ11)*$B11) -> 0 | AM11: 6 | AN11: =+AL11+AM11 -> 6 | AO11: =+AN11-AQ11 -> 2 | AP11: =((AN11-AO11)*$B11) -> 212000 | AQ11: 4 | AS11: =+AQ11+AR11 -> 4 | AT11: =+AS11-AV11 -> 4 | AU11: =((AS11-AT11)*$B11) -> 0 | AX11: =+AV11+AW11 -> 0 | AY11: =+AX11-BA11 -> 0 | AZ11: =((AX11-AY11)*$B11) -> 0 | BC11: =+BA11+BB11 -> 0 | BD11: =+BC11-BF11 -> 0 | BE11: =((BC11-BD11)*$B11) -> 0 | BH11: =+BF11+BG11 -> 0 | BI11: =+BH11-BK11 -> 0 | BJ11: =((BH11-BI11)*$B11) -> 0
A12: CREMA PARA PEINAR SENSE | B12: 30000 | AE12: =+AD12-AG12 -> 0 | AF12: =((AD12-AE12)*$B12) -> 0 | AI12: =+AG12+AH12 -> 0 | AJ12: =+AI12-AL12 -> 0 | AK12: =((AI12-AJ12)*$B12) -> 0 | AM12: 6 | AN12: =+AL12+AM12 -> 6 | AO12: =+AN12-AQ12 -> 1 | AP12: =((AN12-AO12)*$B12) -> 150000 | AQ12: 5 | AS12: =+AQ12+AR12 -> 5 | AT12: =+AS12-AV12 -> 5 | AU12: =((AS12-AT12)*$B12) -> 0 | AX12: =+AV12+AW12 -> 0 | AY12: =+AX12-BA12 -> 0 | AZ12: =((AX12-AY12)*$B12) -> 0 | BC12: =+BA12+BB12 -> 0 | BD12: =+BC12-BF12 -> 0 | BE12: =((BC12-BD12)*$B12) -> 0 | BH12: =+BF12+BG12 -> 0 | BI12: =+BH12-BK12 -> 0 | BJ12: =((BH12-BI12)*$B12) -> 0
A13: TÓNICO CAPILAR SENSE | B13: 50800 | AE13: =+AD13-AG13 -> 0 | AF13: =((AD13-AE13)*$B13) -> 0 | AI13: =+AG13+AH13 -> 0 | AJ13: =+AI13-AL13 -> 0 | AK13: =((AI13-AJ13)*$B13) -> 0 | AM13: 2 | AN13: =+AL13+AM13 -> 2 | AO13: =+AN13-AQ13 -> 1 | AP13: =((AN13-AO13)*$B13) -> 50800 | AQ13: 1 | AS13: =+AQ13+AR13 -> 1 | AT13: =+AS13-AV13 -> 1 | AU13: =((AS13-AT13)*$B13) -> 0 | AX13: =+AV13+AW13 -> 0 | AY13: =+AX13-BA13 -> 0 | AZ13: =((AX13-AY13)*$B13) -> 0 | BC13: =+BA13+BB13 -> 0 | BD13: =+BC13-BF13 -> 0 | BE13: =((BC13-BD13)*$B13) -> 0 | BH13: =+BF13+BG13 -> 0 | BI13: =+BH13-BK13 -> 0 | BJ13: =((BH13-BI13)*$B13) -> 0
AE14: =+AD14-AG14 -> 0 | AF14: =((AD14-AE14)*$B14) -> 0 | AI14: =+AG14+AH14 -> 0 | AJ14: =+AI14-AL14 -> 0 | AK14: =((AI14-AJ14)*$B14) -> 0 | AN14: =+AL14+AM14 -> 0 | AO14: =+AN14-AQ14 -> 0 | AP14: =((AN14-AO14)*$B14) -> 0
AE15: =+AD15-AG15 -> 0 | AF15: =((AD15-AE15)*$B15) -> 0 | AI15: =+AG15+AH15 -> 0 | AJ15: =+AI15-AL15 -> 0 | AK15: =((AI15-AJ15)*$B15) -> 0 | AN15: =+AL15+AM15 -> 0 | AO15: =+AN15-AQ15 -> 0 | AP15: =((AN15-AO15)*$B15) -> 0
G16: =+SUM(G3:G15) -> 0 | L16: =+SUM(L3:L15) -> 0 | Q16: =+SUM(Q3:Q15) -> 0 | V16: =+SUM(V3:V15) -> 0 | AA16: =+SUM(AA3:AA15) -> 0 | AF16: =+SUM(AF3:AF15) -> 0 | AK16: =+SUM(AK3:AK15) -> 0 | AP16: =+SUM(AP3:AP15) -> 1600800 | AU16: =+SUM(AU3:AU15) -> 0 | AZ16: =+SUM(AZ3:AZ15) -> 0 | BE16: =+SUM(BE3:BE15) -> 0 | BJ16: =+SUM(BJ3:BJ15) -> 0

Sheet KE
A1: KARINA ESCOBAR | C1: ENERO | H1: FEBRERO | M1: MARZO | R1: ABRIL | W1: MAYO | AB1: JUNIO | AG1: JULIO | AL1: AGOSTO | AQ1: SEPTIEMBRE | AV1: OCTUBRE | BA1: NOVIEMBRE | BF1: DICIEMBRE | BK1: ENERO
A2: PRODUCTO | B2: VR. COMPRA | C2: INV.I | D2: Entra | E2: Saldo | F2: SALIDA | G2: TOTAL | H2: INV.I | I2: Entra | J2: Saldo | K2: SALIDA | L2: TOTAL | M2: INV.I | N2: Entra | O2: Saldo | P2: SALIDA | Q2: TOTAL | R2: INV.I | S2: Entra | T2: Saldo | U2: SALIDA | V2: TOTAL | W2: INV.I | X2: Entra | Y2: Saldo | Z2: SALIDA | AA2: TOTAL | AB2: INV.I | AC2: Entra | AD2: Saldo | AE2: SALIDA | AF2: TOTAL | AG2: INV.I | AH2: Entra | AI2: Saldo | AJ2: SALIDA | AK2: TOTAL | AL2: INV.I | AM2: Entra | AN2: Saldo | AO2: SALIDA | AP2: TOTAL | AQ2: INV.I | AR2: Entra | AS2: Saldo | AT2: SALIDA | AU2: TOTAL | AV2: INV.I | AW2: Entra | AX2: Saldo | AY2: SALIDA | AZ2: TOTAL | BA2: INV.I | BB2: Entra | BC2: Saldo | BD2: SALIDA | BE2: TOTAL | BF2: INV.I | BG2: Entra | BH2: Saldo | BI2: SALIDA | BJ2: TOTAL | BK2: INV.I
A3: ÓLEO | B3: 29500 | AD3: =+AB3+AC3 -> 0 | AE3: =+AD3-AG3 -> -33 | AF3: =((AD3-AE3)*$B3) -> 973500 | AG3: 33 | AI3: =+AG3+AH3 -> 33 | AJ3: =+AI3-AL3 -> 13 | AK3: =((AI3-AJ3)*$B3) -> 590000 | AL3: 20 | AN3: =+AL3+AM3 -> 20 | AO3: =+AN3-AQ3 -> 10 | AP3: =((AN3-AO3)*$B3) -> 295000 | AQ3: 10 | AR3: 39 | AS3: =+AQ3+AR3 -> 49 | AT3: =+AS3-AV3 -> 49 | AU3: =((AS3-AT3)*$B3) -> 0 | AX3: =+AV3+AW3 -> 0 | AY3: =+AX3-BA3 -> 0 | AZ3: =((AX3-AY3)*$B3) -> 0 | BC3: =+BA3+BB3 -> 0 | BD3: =+BC3-BF3 -> 0 | BE3: =((BC3-BD3)*$B3) -> 0 | BH3: =+BF3+BG3 -> 0 | BI3: =+BH3-BK3 -> 0 | BJ3: =((BH3-BI3)*$B3) -> 0
A4: REPOLARIZADOR | B4: 26000 | AD4: =+AB4+AC4 -> 0 | AE4: =+AD4-AG4 -> -6 | AF4: =((AD4-AE4)*$B4) -> 156000 | AG4: 6 | AI4: =+AG4+AH4 -> 6 | AJ4: =+AI4-AL4 -> 2 | AK4: =((AI4-AJ4)*$B4) -> 104000 | AL4: 4 | AN4: =+AL4+AM4 -> 4 | AO4: =+AN4-AQ4 -> 1 | AP4: =((AN4-AO4)*$B4) -> 78000 | AQ4: 3 | AS4: =+AQ4+AR4 -> 3 | AT4: =+AS4-AV4 -> 3 | AU4: =((AS4-AT4)*$B4) -> 0 | AX4: =+AV4+AW4 -> 0 | AY4: =+AX4-BA4 -> 0 | AZ4: =((AX4-AY4)*$B4) -> 0 | BC4: =+BA4+BB4 -> 0 | BD4: =+BC4-BF4 -> 0 | BE4: =((BC4-BD4)*$B4) -> 0 | BH4: =+BF4+BG4 -> 0 | BI4: =+BH4-BK4 -> 0 | BJ4: =((BH4-BI4)*$B4) -> 0
A5: TERAPIA ANTI FRIZZ | B5: 80000 | AD5: =+AB5+AC5 -> 0 | AE5: =+AD5-AG5 -> -4 | AF5: =((AD5-AE5)*$B5) -> 320000 | AG5: 4 | AI5: =+AG5+AH5 -> 4 | AJ5: =+AI5-AL5 -> 1 | AK5: =((AI5-AJ5)*$B5) -> 240000 | AL5: 3 | AN5: =+AL5+AM5 -> 3 | AO5: =+AN5-AQ5 -> 0 | AP5: =((AN5-AO5)*$B5) -> 240000 | AQ5: 3 | AS5: =+AQ5+AR5 -> 3 | AT5: =+AS5-AV5 -> 3 | AU5: =((AS5-AT5)*$B5) -> 0 | AX5: =+AV5+AW5 -> 0 | AY5: =+AX5-BA5 -> 0 | AZ5: =((AX5-AY5)*$B5) -> 0 | BC5: =+BA5+BB5 -> 0 | BD5: =+BC5-BF5 -> 0 | BE5: =((BC5-BD5)*$B5) -> 0 | BH5: =+BF5+BG5 -> 0 | BI5: =+BH5-BK5 -> 0 | BJ5: =((BH5-BI5)*$B5) -> 0
A6: ALISADO 120ML | B6: 40625 | AD6: =+AB6+AC6 -> 0 | AE6: =+AD6-AG6 -> 0 | AG6: 0 | AH6: 8 | AI6: =+AG6+AH6 -> 8 | AJ6: =+AI6-AL6 -> 1 | AK6: =((AI6-AJ6)*$B6) -> 284375 | AL6: 7 | AN6: =+AL6+AM6 -> 7 | AO6: =+AN6-AQ6 -> 0 | AP6: =((AN6-AO6)*$B6) -> 284375 | AQ6: 7
A7: ALISADO | B7: 325000 | AD7: =+AB7+AC7 -> 0 | AE7: =+AD7-AG7 -> -1 | AF7: =((AD7-AE7)*$B7) -> 325000 | AG7: 1 | AH7: 3 | AI7: =+AG7+AH7 -> 4 | AJ7: =+AI7-AL7 -> 1 | AK7: =((AI7-AJ7)*$B7) -> 975000 | AL7: 3 | AN7: =+AL7+AM7 -> 3 | AO7: =+AN7-AQ7 -> 2 | AP7: =((AN7-AO7)*$B7) -> 325000 | AQ7: 1 | AR7: 4 | AS7: =+AQ7+AR7 -> 5 | AT7: =+AS7-AV7 -> 5 | AU7: =((AS7-AT7)*$B7) -> 0 | AX7: =+AV7+AW7 -> 0 | AY7: =+AX7-BA7 -> 0 | AZ7: =((AX7-AY7)*$B7) -> 0 | BC7: =+BA7+BB7 -> 0 | BD7: =+BC7-BF7 -> 0 | BE7: =((BC7-BD7)*$B7) -> 0 | BH7: =+BF7+BG7 -> 0 | BI7: =+BH7-BK7 -> 0 | BJ7: =((BH7-BI7)*$B7) -> 0
G8: =SUM(G3:G7) -> 0 | L8: =SUM(L3:L7) -> 0 | Q8: =SUM(Q3:Q7) -> 0 | V8: =SUM(V3:V7) -> 0 | AA8: =SUM(AA3:AA7) -> 0 | AF8: =SUM(AF3:AF7) -> 1774500 | AK8: =SUM(AK3:AK7) -> 2193375 | AP8: =+SUM(AP3:AP7) -> 1222375 | AU8: =+SUM(AU3:AU7) -> 0 | AZ8: =+SUM(AZ3:AZ7) -> 0 | BE8: =+SUM(BE3:BE7) -> 0 | BJ8: =+SUM(BJ3:BJ7) -> 0

Sheet CL.H
A1: CLICK HAIR | C1: ENERO | H1: FEBRERO | M1: MARZO | R1: ABRIL | W1: MAYO | AB1: JUNIO | AG1: JULIO | AL1: AGOSTO | AQ1: SEPTIEMBRE | AV1: OCTUBRE | BA1: NOVIEMBRE | BF1: DICIEMBRE | BK1: ENERO
A2: PRODUCTO | B2: VR. COMPRA | C2: INV.I | D2: Entra | E2: Saldo | F2: SALIDA | G2: TOTAL | H2: INV.I | I2: Entra | J2: Saldo | K2: SALIDA | L2: TOTAL | M2: INV.I | N2: Entra | O2: Saldo | P2: SALIDA | Q2: TOTAL | R2: INV.I | S2: Entra | T2: Saldo | U2: SALIDA | V2: TOTAL | W2: INV.I | X2: Entra | Y2: Saldo | Z2: SALIDA | AA2: TOTAL | AB2: INV.I | AC2: Entra | AD2: Saldo | AE2: SALIDA | AF2: TOTAL | AG2: INV.I | AH2: Entra | AI2: Saldo | AJ2: SALIDA | AK2: TOTAL | AL2: INV.I | AM2: Entra | AN2: Saldo | AO2: SALIDA | AP2: TOTAL | AQ2: INV.I | AR2: Entra | AS2: Saldo | AT2: SALIDA | AU2: TOTAL | AV2: INV.I | AW2: Entra | AX2: Saldo | AY2: SALIDA | AZ2: TOTAL | BA2: INV.I | BB2: Entra | BC2: Saldo | BD2: SALIDA | BE2: TOTAL | BF2: INV.I | BG2: Entra | BH2: Saldo | BI2: SALIDA | BJ2: TOTAL | BK2: INV.I
A3: MASC. DE MIEL | B3: 38000 | AD3: =+AB3+AC3 -> 0 | AE3: =+AD3-AG3 -> -3 | AF3: =((AD3-AE3)*$B3) -> 114000 | AG3: 3 | AI3: =+AG3+AH3 -> 3 | AJ3: =+AI3-AL3 -> 0 | AK3: =((AI3-AJ3)*$B3) -> 114000 | AL3: 3 | AN3: =+AL3+AM3 -> 3 | AO3: =+AN3-AQ3 -> 1 | AP3: =((AN3-AO3)*$B3) -> 76000 | AQ3: 2 | AS3: =+AQ3+AR3 -> 2 | AT3: =+AS3-AV3 -> 2 | AU3: =((AS3-AT3)*$B3) -> 0 | AX3: =+AV3+AW3 -> 0 | AY3: =+AX3-BA3 -> 0 | AZ3: =((AX3-AY3)*$B3) -> 0 | BC3: =+BA3+BB3 -> 0 | BD3: =+BC3-BF3 -> 0 | BE3: =((BC3-BD3)*$B3) -> 0 | BH3: =+BF3+BG3 -> 0 | BI3: =+BH3-BK3 -> 0 | BJ3: =((BH3-BI3)*$B3) -> 0
A4: PERFUMES PISTACHO/MASMELO/MIEL | B4: 44000 | AD4: =+AB4+AC4 -> 0 | AE4: =+AD4-AG4 -> -11 | AF4: =((AD4-AE4)*$B4) -> 484000 | AG4: 11 | AI4: =+AG4+AH4 -> 11 | AJ4: =+AI4-AL4 -> 4 | AK4: =((AI4-AJ4)*$B4) -> 308000 | AL4: 7 | AN4: =+AL4+AM4 -> 7 | AO4: =+AN4-AQ4 -> 1 | AP4: =((AN4-AO4)*$B4) -> 264000 | AQ4: 6 | AS4: =+AQ4+AR4 -> 6 | AT4: =+AS4-AV4 -> 6 | AU4: =((AS4-AT4)*$B4) -> 0 | AX4: =+AV4+AW4 -> 0 | AY4: =+AX4-BA4 -> 0 | AZ4: =((AX4-AY4)*$B4) -> 0 | BC4: =+BA4+BB4 -> 0 | BD4: =+BC4-BF4 -> 0 | BE4: =((BC4-BD4)*$B4) -> 0 | BH4: =+BF4+BG4 -> 0 | BI4: =+BH4-BK4 -> 0 | BJ4: =((BH4-BI4)*$B4) -> 0
A5: SUERO RECONSTRUCTOR | B5: 29000 | AD5: =+AB5+AC5 -> 0 | AE5: =+AD5-AG5 -> -1 | AF5: =((AD5-AE5)*$B5) -> 29000 | AG5: 1 | AH5: 2 | AI5: =+AG5+AH5 -> 3 | AJ5: =+AI5-AL5 -> 1 | AK5: =((AI5-AJ5)*$B5) -> 58000 | AL5: 2 | AN5: =+AL5+AM5 -> 2 | AO5: =+AN5-AQ5 -> 1 | AP5: =((AN5-AO5)*$B5) -> 29000 | AQ5: 1 | AS5: =+AQ5+AR5 -> 1 | AT5: =+AS5-AV5 -> 1 | AU5: =((AS5-AT5)*$B5) -> 0 | AX5: =+AV5+AW5 -> 0 | AY5: =+AX5-BA5 -> 0 | AZ5: =((AX5-AY5)*$B5) -> 0 | BC5: =+BA5+BB5 -> 0 | BD5: =+BC5-BF5 -> 0 | BE5: =((BC5-BD5)*$B5) -> 0 | BH5: =+BF5+BG5 -> 0 | BI5: =+BH5-BK5 -> 0 | BJ5: =((BH5-BI5)*$B5) -> 0
A6: TÓNICO CAPILAR CLICK 120ML | B6: 45000 | AD6: =+AB6+AC6 -> 0 | AE6: =+AD6-AG6 -> 0 | AF6: =((AD6-AE6)*$B6) -> 0 | AG6: 0 | AI6: =+AG6+AH6 -> 0 | AJ6: =+AI6-AL6 -> 0 | AK6: =((AI6-AJ6)*$B6) -> 0 | AL6: 0 | AN6: =+AL6+AM6 -> 0 | AO6: =+AN6-AQ6 -> 0 | AP6: =((AN6-AO6)*$B6) -> 0 | AQ6: 0 | AS6: =+AQ6+AR6 -> 0 | AT6: =+AS6-AV6 -> 0
A7: TÓNICO CAPILAR CLICK 60 ML | B7: 27000 | AD7: =+AB7+AC7 -> 0 | AE7: =+AD7-AG7 -> 0 | AF7: =((AD7-AE7)*$B7) -> 0 | AG7: 0 | AH7: 2 | AI7: =+AG7+AH7 -> 2 | AJ7: =+AI7-AL7 -> 0 | AK7: =((AI7-AJ7)*$B7) -> 54000 | AL7: 2 | AN7: =+AL7+AM7 -> 2 | AO7: =+AN7-AQ7 -> 0 | AP7: =((AN7-AO7)*$B7) -> 54000 | AQ7: 2 | AS7: =+AQ7+AR7 -> 2 | AT7: =+AS7-AV7 -> 2
A8: PERFUMES AZUL/ROSADO/AMARILO/MORADO/NARANJA/VERDE/TRANSPARENTE | B8: 36000 | AD8: =+AB8+AC8 -> 0 | AE8: =+AD8-AG8 -> -7 | AF8: =((AD8-AE8)*$B8) -> 252000 | AG8: 7 | AI8: =+AG8+AH8 -> 7 | AJ8: =+AI8-AL8 -> 1 | AK8: =((AI8-AJ8)*$B8) -> 216000 | AL8: 6 | AN8: =+AL8+AM8 -> 6 | AO8: =+AN8-AQ8 -> 0 | AP8: =((AN8-AO8)*$B8) -> 216000 | AQ8: 6 | AS8: =+AQ8+AR8 -> 6 | AT8: =+AS8-AV8 -> 6
A9: ENERGIZANTE CAPILAR | B9: 34000 | AD9: =+AB9+AC9 -> 0 | AE9: =+AD9-AG9 -> -2 | AF9: =((AD9-AE9)*$B9) -> 68000 | AG9: 2 | AI9: =+AG9+AH9 -> 2 | AJ9: =+AI9-AL9 -> 0 | AK9: =((AI9-AJ9)*$B9) -> 68000 | AL9: 2 | AN9: =+AL9+AM9 -> 2 | AO9: =+AN9-AQ9 -> 1 | AP9: =((AN9-AO9)*$B9) -> 34000 | AQ9: 1 | AS9: =+AQ9+AR9 -> 1 | AT9: =+AS9-AV9 -> 1
A10: SH. AJÍ | B10: 34000 | AD10: =+AB10+AC10 -> 0 | AE10: =+AD10-AG10 -> -1 | AF10: =((AD10-AE10)*$B10) -> 34000 | AG10: 1 | AH10: 4 | AI10: =+AG10+AH10 -> 5 | AJ10: =+AI10-AL10 -> 4 | AK10: =((AI10-AJ10)*$B10) -> 34000 | AL10: 1 | AM10: 3 | AN10: =+AL10+AM10 -> 4 | AO10: =+AN10-AQ10 -> 2 | AP10: =((AN10-AO10)*$B10) -> 68000 | AQ10: 2 | AS10: =+AQ10+AR10 -> 2 | AT10: =+AS10-AV10 -> 2
A11: SH. MIEL | B11: 34000 | AD11: =+AB11+AC11 -> 0 | AE11: =+AD11-AG11 -> -3 | AF11: =((AD11-AE11)*$B11) -> 102000 | AG11: 3 | AI11: =+AG11+AH11 -> 3 | AJ11: =+AI11-AL11 -> 0 | AK11: =((AI11-AJ11)*$B11) -> 102000 | AL11: 3 | AN11: =+AL11+AM11 -> 3 | AO11: =+AN11-AQ11 -> 0 | AP11: =((AN11-AO11)*$B11) -> 102000 | AQ11: 3 | AS11: =+AQ11+AR11 -> 3 | AT11: =+AS11-AV11 -> 3
A12: MIEL CAPILAR | B12: 45000 | AD12: =+AB12+AC12 -> 0 | AE12: =+AD12-AG12 -> -1 | AF12: =((AD12-AE12)*$B12) -> 45000 | AG12: 1 | AI12: =+AG12+AH12 -> 1 | AJ12: =+AI12-AL12 -> 0 | AK12: =((AI12-AJ12)*$B12) -> 45000 | AL12: 1 | AN12: =+AL12+AM12 -> 1 | AO12: =+AN12-AQ12 -> 0 | AP12: =((AN12-AO12)*$B12) -> 45000 | AQ12: 1 | AS12: =+AQ12+AR12 -> 1 | AT12: =+AS12-AV12 -> 1
A13: AC. MIEL | B13: 33000 | AD13: =+AB13+AC13 -> 0 | AE13: =+AD13-AG13 -> -1 | AF13: =((AD13-AE13)*$B13) -> 33000 | AG13: 1 | AI13: =+AG13+AH13 -> 1 | AJ13: =+AI13-AL13 -> 0 | AK13: =((AI13-AJ13)*$B13) -> 33000 | AL13: 1 | AN13: =+AL13+AM13 -> 1 | AO13: =+AN13-AQ13 -> 1 | AP13: =((AN13-AO13)*$B13) -> 0 | AQ13: 0 | AS13: =+AQ13+AR13 -> 0 | AT13: =+AS13-AV13 -> 0
A14: AC 4 EN 1 | B14: 33000 | AD14: =+AB14+AC14 -> 0 | AE14: =+AD14-AG14 -> -3 | AF14: =((AD14-AE14)*$B14) -> 99000 | AG14: 3 | AI14: =+AG14+AH14 -> 3 | AJ14: =+AI14-AL14 -> 0 | AK14: =((AI14-AJ14)*$B14) -> 99000 | AL14: 3 | AN14: =+AL14+AM14 -> 3 | AO14: =+AN14-AQ14 -> 1 | AP14: =((AN14-AO14)*$B14) -> 66000 | AQ14: 2 | AS14: =+AQ14+AR14 -> 2 | AT14: =+AS14-AV14 -> 2
A15: TERMORPROTETOR LECHE Y MIEL | B15: 36000 | AD15: =+AB15+AC15 -> 0 | AE15: =+AD15-AG15 -> -2 | AF15: =((AD15-AE15)*$B15) -> 72000 | AG15: 2 | AI15: =+AG15+AH15 -> 2 | AJ15: =+AI15-AL15 -> 0 | AK15: =((AI15-AJ15)*$B15) -> 72000 | AL15: 2 | AN15: =+AL15+AM15 -> 2 | AO15: =+AN15-AQ15 -> 1 | AP15: =((AN15-AO15)*$B15) -> 36000 | AQ15: 1 | AS15: =+AQ15+AR15 -> 1 | AT15: =+AS15-AV15 -> 1
A16: PERFUME MINI X 3 | B16: 36700 | AD16: =+AB16+AC16 -> 0 | AE16: =+AD16-AG16 -> -1 | AF16: =((AD16-AE16)*$B16) -> 36700 | AG16: 1 | AH16: =2+2 -> 4 | AI16: =+AG16+AH16 -> 5 | AJ16: =+AI16-AL16 -> 2 | AK16: =((AI16-AJ16)*$B16) -> 110100 | AL16: 3 | AN16: =+AL16+AM16 -> 3 | AO16: =+AN16-AQ16 -> 1 | AP16: =((AN16-AO16)*$B16) -> 73400 | AQ16: 2 | AS16: =+AQ16+AR16 -> 2 | AT16: =+AS16-AV16 -> 2 | AU16: =((AS16-AT16)*$B16) -> 0 | AX16: =+AV16+AW16 -> 0 | AY16: =+AX16-BA16 -> 0 | AZ16: =((AX16-AY16)*$B16) -> 0 | BC16: =+BA16+BB16 -> 0 | BD16: =+BC16-BF16 -> 0 | BE16: =((BC16-BD16)*$B16) -> 0 | BH16: =+BF16+BG16 -> 0 | BI16: =+BH16-BK16 -> 0 | BJ16: =((BH16-BI16)*$B16) -> 0
G17: =SUM(G3:G16) -> 0 | L17: =SUM(L3:L16) -> 0 | Q17: =SUM(Q3:Q16) -> 0 | V17: =SUM(V3:V16) -> 0 | AA17: =SUM(AA3:AA16) -> 0 | AF17: =SUM(AF3:AF16) -> 1368700 | AK17: =SUM(AK3:AK16) -> 1313100 | AP17: =+SUM(AP3:AP16) -> 1063400 | AU17: =+SUM(AU3:AU16) -> 0 | AZ17: =+SUM(AZ3:AZ16) -> 0 | BE17: =+SUM(BE3:BE16) -> 0 | BJ17: =+SUM(BJ3:BJ16) -> 0

Sheet SATIN
A1: SATIN | C1: ENERO | H1: FEBRERO | M1: MARZO | R1: ABRIL | W1: MAYO | AB1: JUNIO | AG1: JULIO | AL1: AGOSTO | AQ1: SEPTIEMBRE | AV1: OCTUBRE | BA1: NOVIEMBRE | BF1: DICIEMBRE | BK1: ENERO
A2: PRODUCTO | B2: VR. COMPRA | C2: INV.I | D2: Entra | E2: Saldo | F2: SALIDA | G2: TOTAL | H2: INV.I | I2: Entra | J2: Saldo | K2: SALIDA | L2: TOTAL | M2: INV.I | N2: Entra | O2: Saldo | P2: SALIDA | Q2: TOTAL | R2: INV.I | S2: Entra | T2: Saldo | U2: SALIDA | V2: TOTAL | W2: INV.I | X2: Entra | Y2: Saldo | Z2: SALIDA | AA2: TOTAL | AB2: INV.I | AC2: Entra | AD2: Saldo | AE2: SALIDA | AF2: TOTAL | AG2: INV.I | AH2: Entra | AI2: Saldo | AJ2: SALIDA | AK2: TOTAL | AL2: INV.I | AM2: Entra | AN2: Saldo | AO2: SALIDA | AP2: TOTAL | AQ2: INV.I | AR2: Entra | AS2: Saldo | AT2: SALIDA | AU2: TOTAL | AV2: INV.I | AW2: Entra | AX2: Saldo | AY2: SALIDA | AZ2: TOTAL | BA2: INV.I | BB2: Entra | BC2: Saldo | BD2: SALIDA | BE2: TOTAL | BF2: INV.I | BG2: Entra | BH2: Saldo | BI2: SALIDA | BJ2: TOTAL | BK2: INV.I
A3: SCRUNCHIS PEQ | B3: 3500 | AD3: =+AB3+AC3 -> 0 | AE3: =+AD3-AG3 -> -12 | AF3: =((AD3-AE3)*$B3) -> 42000 | AG3: 12 | AI3: =+AG3+AH3 -> 12 | AJ3: =+AI3-AL3 -> 4 | AK3: =((AI3-AJ3)*$B3) -> 28000 | AL3: 8 | AM3: 3 | AN3: =+AL3+AM3 -> 11 | AO3: =+AN3-AQ3 -> 2 | AP3: =((AN3-AO3)*$B3) -> 31500 | AQ3: 9 | AS3: =+AQ3+AR3 -> 9 | AT3: =+AS3-AV3 -> 9 | AU3: =((AS3-AT3)*$B3) -> 0 | AX3: =+AV3+AW3 -> 0 | AY3: =+AX3-BA3 -> 0 | AZ3: =((AX3-AY3)*$B3) -> 0 | BC3: =+BA3+BB3 -> 0 | BD3: =+BC3-BF3 -> 0 | BE3: =((BC3-BD3)*$B3) -> 0 | BH3: =+BF3+BG3 -> 0 | BI3: =+BH3-BK3 -> 0 | BJ3: =((BH3-BI3)*$B3) -> 0
A4: SCRUNCHIS GRANDE | B4: 4000 | AD4: =+AB4+AC4 -> 0 | AE4: =+AD4-AG4 -> -12 | AF4: =((AD4-AE4)*$B4) -> 48000 | AG4: 12 | AI4: =+AG4+AH4 -> 12 | AJ4: =+AI4-AL4 -> 2 | AK4: =((AI4-AJ4)*$B4) -> 40000 | AL4: 10 | AN4: =+AL4+AM4 -> 10 | AO4: =+AN4-AQ4 -> 3 | AP4: =((AN4-AO4)*$B4) -> 28000 | AQ4: 7 | AS4: =+AQ4+AR4 -> 7 | AT4: =+AS4-AV4 -> 7 | AU4: =((AS4-AT4)*$B4) -> 0 | AX4: =+AV4+AW4 -> 0 | AY4: =+AX4-BA4 -> 0 | AZ4: =((AX4-AY4)*$B4) -> 0 | BC4: =+BA4+BB4 -> 0 | BD4: =+BC4-BF4 -> 0 | BE4: =((BC4-BD4)*$B4) -> 0 | BH4: =+BF4+BG4 -> 0 | BI4: =+BH4-BK4 -> 0 | BJ4: =((BH4-BI4)*$B4) -> 0
A5: GORROS DE SATÍN | B5: 18000 | AD5: =+AB5+AC5 -> 0 | AE5: =+AD5-AG5 -> -6 | AF5: =((AD5-AE5)*$B5) -> 108000 | AG5: 6 | AI5: =+AG5+AH5 -> 6 | AJ5: =+AI5-AL5 -> 5 | AK5: =((AI5-AJ5)*$B5) -> 18000 | AL5: 1 | AM5: 6 | AN5: =+AL5+AM5 -> 7 | AO5: =+AN5-AQ5 -> 1 | AP5: =((AN5-AO5)*$B5) -> 108000 | AQ5: 6 | AS5: =+AQ5+AR5 -> 6 | AT5: =+AS5-AV5 -> 6 | AU5: =((AS5-AT5)*$B5) -> 0 | AX5: =+AV5+AW5 -> 0 | AY5: =+AX5-BA5 -> 0 | AZ5: =((AX5-AY5)*$B5) -> 0 | BC5: =+BA5+BB5 -> 0 | BD5: =+BC5-BF5 -> 0 | BE5: =((BC5-BD5)*$B5) -> 0 | BH5: =+BF5+BG5 -> 0 | BI5: =+BH5-BK5 -> 0 | BJ5: =((BH5-BI5)*$B5) -> 0
G6: =SUM(G3:G5) -> 0 | L6: =SUM(L3:L5) -> 0 | Q6: =SUM(Q3:Q5) -> 0 | V6: =SUM(V3:V5) -> 0 | AA6: =SUM(AA3:AA5) -> 0 | AF6: =SUM(AF3:AF5) -> 198000 | AK6: =SUM(AK3:AK5) -> 86000 | AP6: =+SUM(AP3:AP5) -> 167500 | AU6: =+SUM(AU3:AU5) -> 0 | AZ6: =+SUM(AZ3:AZ5) -> 0 | BE6: =+SUM(BE3:BE5) -> 0 | BJ6: =+SUM(BJ3:BJ5) -> 0

Sheet KB
A1: KABA | C1: ENERO | H1: FEBRERO | M1: MARZO | R1: ABRIL | W1: MAYO | AB1: JUNIO | AG1: JULIO | AL1: AGOSTO | AQ1: SEPTIEMBRE | AV1: OCTUBRE | BA1: NOVIEMBRE | BF1: DICIEMBRE | BK1: ENERO
A2: PRODUCTO | B2: VR. COMPRA | C2: INV.I | D2: Entra | E2: Saldo | F2: SALIDA | G2: TOTAL | H2: INV.I | I2: Entra | J2: Saldo | K2: SALIDA | L2: TOTAL | M2: INV.I | N2: Entra | O2: Saldo | P2: SALIDA | Q2: TOTAL | R2: INV.I | S2: Entra | T2: Saldo | U2: SALIDA | V2: TOTAL | W2: INV.I | X2: Entra | Y2: Saldo | Z2: SALIDA | AA2: TOTAL | AB2: INV.I | AC2: Entra | AD2: Saldo | AE2: SALIDA | AF2: TOTAL | AG2: INV.I | AH2: Entra | AI2: Saldo | AJ2: SALIDA | AK2: TOTAL | AL2: INV.I | AM2: Entra | AN2: Saldo | AO2: SALIDA | AP2: TOTAL | AQ2: INV.I | AR2: Entra | AS2: Saldo | AT2: SALIDA | AU2: TOTAL | AV2: INV.I | AW2: Entra | AX2: Saldo | AY2: SALIDA | AZ2: TOTAL | BA2: INV.I | BB2: Entra | BC2: Saldo | BD2: SALIDA | BE2: TOTAL | BF2: INV.I | BG2: Entra | BH2: Saldo | BI2: SALIDA | BJ2: TOTAL | BK2: INV.I
A3: SH CEBOLLA | B3: 40000 | AD3: =+AB3+AC3 -> 0 | AE3: =+AD3-AG3 -> -1 | AF3: =((AD3-AE3)*$B3) -> 40000 | AG3: 1 | AI3: =+AG3+AH3 -> 1 | AJ3: =+AI3-AL3 -> 1 | AK3: =((AI3-AJ3)*$B3) -> 0 | AL3: 0 | AN3: =+AL3+AM3 -> 0 | AO3: =+AN3-AQ3 -> 0 | AP3: =((AN3-AO3)*$B3) -> 0 | AQ3: 0 | AS3: =+AQ3+AR3 -> 0 | AT3: =+AS3-AV3 -> 0 | AU3: =((AS3-AT3)*$B3) -> 0 | AX3: =+AV3+AW3 -> 0 | AY3: =+AX3-BA3 -> 0 | AZ3: =((AX3-AY3)*$B3) -> 0 | BC3: =+BA3+BB3 -> 0 | BD3: =+BC3-BF3 -> 0 | BE3: =((BC3-BD3)*$B3) -> 0 | BH3: =+BF3+BG3 -> 0 | BI3: =+BH3-BK3 -> 0 | BJ3: =((BH3-BI3)*$B3) -> 0
A4: ACONDICIONADOR | B4: 36000 | AD4: =+AB4+AC4 -> 0 | AE4: =+AD4-AG4 -> -1 | AF4: =((AD4-AE4)*$B4) -> 36000 | AG4: 1 | AI4: =+AG4+AH4 -> 1 | AJ4: =+AI4-AL4 -> 1 | AK4: =((AI4-AJ4)*$B4) -> 0 | AL4: 0 | AN4: =+AL4+AM4 -> 0 | AO4: =+AN4-AQ4 -> 0 | AP4: =((AN4-AO4)*$B4) -> 0 | AQ4: 0 | AS4: =+AQ4+AR4 -> 0 | AT4: =+AS4-AV4 -> 0 | AU4: =((AS4-AT4)*$B4) -> 0 | AX4: =+AV4+AW4 -> 0 | AY4: =+AX4-BA4 -> 0 | AZ4: =((AX4-AY4)*$B4) -> 0 | BC4: =+BA4+BB4 -> 0 | BD4: =+BC4-BF4 -> 0 | BE4: =((BC4-BD4)*$B4) -> 0 | BH4: =+BF4+BG4 -> 0 | BI4: =+BH4-BK4 -> 0 | BJ4: =((BH4-BI4)*$B4) -> 0
A5: BIOMASCARILLA | B5: 40000 | AD5: =+AB5+AC5 -> 0 | AE5: =+AD5-AG5 -> -10 | AF5: =((AD5-AE5)*$B5) -> 400000 | AG5: 10 | AI5: =+AG5+AH5 -> 10 | AJ5: =+AI5-AL5 -> 1 | AK5: =((AI5-AJ5)*$B5) -> 360000 | AL5: 9 | AN5: =+AL5+AM5 -> 9 | AO5: =+AN5-AQ5 -> 0 | AP5: =((AN5-AO5)*$B5) -> 360000 | AQ5: 9 | AS5: =+AQ5+AR5 -> 9 | AT5: =+AS5-AV5 -> 9 | AU5: =((AS5-AT5)*$B5) -> 0 | AX5: =+AV5+AW5 -> 0 | AY5: =+AX5-BA5 -> 0 | AZ5: =((AX5-AY5)*$B5) -> 0 | BC5: =+BA5+BB5 -> 0 | BD5: =+BC5-BF5 -> 0 | BE5: =((BC5-BD5)*$B5) -> 0 | BH5: =+BF5+BG5 -> 0 | BI5: =+BH5-BK5 -> 0 | BJ5: =((BH5-BI5)*$B5) -> 0
A6: REPOLARIZADOR | B6: 40000 | AD6: =+AB6+AC6 -> 0 | AE6: =+AD6-AG6 -> 0 | AF6: =((AD6-AE6)*$B6) -> 0 | AG6: 0 | AI6: =+AG6+AH6 -> 0 | AJ6: =+AI6-AL6 -> 0 | AK6: =((AI6-AJ6)*$B6) -> 0 | AL6: 0 | AN6: =+AL6+AM6 -> 0 | AO6: =+AN6-AQ6 -> 0 | AP6: =((AN6-AO6)*$B6) -> 0 | AQ6: 0 | AS6: =+AQ6+AR6 -> 0 | AT6: =+AS6-AV6 -> 0 | AU6: =((AS6-AT6)*$B6) -> 0 | AX6: =+AV6+AW6 -> 0 | AY6: =+AX6-BA6 -> 0 | AZ6: =((AX6-AY6)*$B6) -> 0 | BC6: =+BA6+BB6 -> 0 | BD6: =+BC6-BF6 -> 0 | BE6: =((BC6-BD6)*$B6) -> 0 | BH6: =+BF6+BG6 -> 0 | BI6: =+BH6-BK6 -> 0 | BJ6: =((BH6-BI6)*$B6) -> 0
A7: ACEITE DE PUNTAS CBD | B7: 28000 | AD7: =+AB7+AC7 -> 0 | AE7: =+AD7-AG7 -> -3 | AF7: =((AD7-AE7)*$B7) -> 84000 | AG7: 3 | AI7: =+AG7+AH7 -> 3 | AJ7: =+AI7-AL7 -> 0 | AK7: =((AI7-AJ7)*$B7) -> 84000 | AL7: 3 | AN7: =+AL7+AM7 -> 3 | AO7: =+AN7-AQ7 -> 0 | AP7: =((AN7-AO7)*$B7) -> 84000 | AQ7: 3 | AS7: =+AQ7+AR7 -> 3 | AT7: =+AS7-AV7 -> 3 | AU7: =((AS7-AT7)*$B7) -> 0 | AX7: =+AV7+AW7 -> 0 | AY7: =+AX7-BA7 -> 0 | AZ7: =((AX7-AY7)*$B7) -> 0 | BC7: =+BA7+BB7 -> 0 | BD7: =+BC7-BF7 -> 0 | BE7: =((BC7-BD7)*$B7) -> 0 | BH7: =+BF7+BG7 -> 0 | BI7: =+BH7-BK7 -> 0 | BJ7: =((BH7-BI7)*$B7) -> 0
A8: EXFOLIANTE CBD | B8: 52000 | AD8: =+AB8+AC8 -> 0 | AE8: =+AD8-AG8 -> -3 | AF8: =((AD8-AE8)*$B8) -> 156000 | AG8: 3 | AI8: =+AG8+AH8 -> 3 | AJ8: =+AI8-AL8 -> 0 | AK8: =((AI8-AJ8)*$B8) -> 156000 | AL8: 3 | AN8: =+AL8+AM8 -> 3 | AO8: =+AN8-AQ8 -> 0 | AP8: =((AN8-AO8)*$B8) -> 156000 | AQ8: 3 | AS8: =+AQ8+AR8 -> 3 | AT8: =+AS8-AV8 -> 3 | AU8: =((AS8-AT8)*$B8) -> 0 | AX8: =+AV8+AW8 -> 0 | AY8: =+AX8-BA8 -> 0 | AZ8: =((AX8-AY8)*$B8) -> 0 | BC8: =+BA8+BB8 -> 0 | BD8: =+BC8-BF8 -> 0 | BE8: =((BC8-BD8)*$B8) -> 0 | BH8: =+BF8+BG8 -> 0 | BI8: =+BH8-BK8 -> 0 | BJ8: =((BH8-BI8)*$B8) -> 0
A9: TONICO DE CRECIMIENTO | B9: 40000 | AD9: =+AB9+AC9 -> 0 | AE9: =+AD9-AG9 -> -3 | AF9: =((AD9-AE9)*$B9) -> 120000 | AG9: 3 | AI9: =+AG9+AH9 -> 3 | AJ9: =+AI9-AL9 -> 0 | AK9: =((AI9-AJ9)*$B9) -> 120000 | AL9: 3 | AN9: =+AL9+AM9 -> 3 | AO9: =+AN9-AQ9 -> 2 | AP9: =((AN9-AO9)*$B9) -> 40000 | AQ9: 1 | AS9: =+AQ9+AR9 -> 1 | AT9: =+AS9-AV9 -> 1 | AU9: =((AS9-AT9)*$B9) -> 0 | AX9: =+AV9+AW9 -> 0 | AY9: =+AX9-BA9 -> 0 | AZ9: =((AX9-AY9)*$B9) -> 0 | BC9: =+BA9+BB9 -> 0 | BD9: =+BC9-BF9 -> 0 | BE9: =((BC9-BD9)*$B9) -> 0 | BH9: =+BF9+BG9 -> 0 | BI9: =+BH9-BK9 -> 0 | BJ9: =((BH9-BI9)*$B9) -> 0
G10: =SUM(G3:G9) -> 0 | L10: =SUM(L3:L9) -> 0 | Q10: =SUM(Q3:Q9) -> 0 | V10: =SUM(V3:V9) -> 0 | AA10: =SUM(AA3:AA9) -> 0 | AF10: =SUM(AF3:AF9) -> 836000 | AK10: =SUM(AK3:AK9) -> 720000 | AP10: =+SUM(AP3:AP9) -> 640000 | AU10: =+SUM(AU3:AU9) -> 0 | AZ10: 3037000 | BE10: =+SUM(BE3:BE9) -> 0 | BJ10: =+SUM(BJ3:BJ9) -> 0

Sheet BL.SH
A1: BLOOM SHELL | C1: ENERO | H1: FEBRERO | M1: MARZO | R1: ABRIL | W1: MAYO | AB1: JUNIO | AG1: JULIO | AL1: AGOSTO | AQ1: SEPTIEMBRE | AV1: OCTUBRE | BA1: NOVIEMBRE | BF1: DICIEMBRE | BK1: ENERO
A2: PRODUCTO | B2: VR. COMPRA | C2: INV.I | D2: Entra | E2: Saldo | F2: SALIDA | G2: TOTAL | H2: INV.I | I2: Entra | J2: Saldo | K2: SALIDA | L2: TOTAL | M2: INV.I | N2: Entra | O2: Saldo | P2: SALIDA | Q2: TOTAL | R2: INV.I | S2: Entra | T2: Saldo | U2: SALIDA | V2: TOTAL | W2: INV.I | X2: Entra | Y2: Saldo | Z2: SALIDA | AA2: TOTAL | AB2: INV.I | AC2: Entra | AD2: Saldo | AE2: SALIDA | AF2: TOTAL | AG2: INV.I | AH2: Entra | AI2: Saldo | AJ2: SALIDA | AK2: TOTAL | AL2: INV.I | AM2: Entra | AN2: Saldo | AO2: SALIDA | AP2: TOTAL | AQ2: INV.I | AR2: Entra | AS2: Saldo | AT2: SALIDA | AU2: TOTAL | AV2: INV.I | AW2: Entra | AX2: Saldo | AY2: SALIDA | AZ2: TOTAL | BA2: INV.I | BB2: Entra | BC2: Saldo | BD2: SALIDA | BE2: TOTAL | BF2: INV.I | BG2: Entra | BH2: Saldo | BI2: SALIDA | BJ2: TOTAL | BK2: INV.I
A3: Bloom dolce bouquet x 9 | B3: 24000 | AD3: =+AB3+AC3 -> 0 | AE3: =+AD3-AG3 -> -2 | AF3: =((AD3-AE3)*$B3) -> 48000 | AG3: 2 | AI3: =+AG3+AH3 -> 2 | AJ3: =+AI3-AL3 -> 0 | AK3: =((AI3-AJ3)*$B3) -> 48000 | AL3: 2 | AN3: =+AL3+AM3 -> 2 | AO3: =+AN3-AQ3 -> 0 | AP3: =((AN3-AO3)*$B3) -> 48000 | AQ3: 2 | AS3: =+AQ3+AR3 -> 2 | AT3: =+AS3-AV3 -> 2 | AU3: =((AS3-AT3)*$B3) -> 0 | AX3: =+AV3+AW3 -> 0 | AY3: =+AX3-BA3 -> 0 | AZ3: =((AX3-AY3)*$B3) -> 0 | BC3: =+BA3+BB3 -> 0 | BD3: =+BC3-BF3 -> 0 | BE3: =((BC3-BD3)*$B3) -> 0 | BH3: =+BF3+BG3 -> 0 | BI3: =+BH3-BK3 -> 0 | BJ3: =((BH3-BI3)*$B3) -> 0
A4: Corrector my concealer | B4: 15000 | AD4: =+AB4+AC4 -> 0 | AE4: =+AD4-AG4 -> -12 | AF4: =((AD4-AE4)*$B4) -> 180000 | AG4: 12 | AI4: =+AG4+AH4 -> 12 | AJ4: =+AI4-AL4 -> 2 | AK4: =((AI4-AJ4)*$B4) -> 150000 | AL4: 10 | AN4: =+AL4+AM4 -> 10 | AO4: =+AN4-AQ4 -> 1 | AP4: =((AN4-AO4)*$B4) -> 135000 | AQ4: 9 | AS4: =+AQ4+AR4 -> 9 | AT4: =+AS4-AV4 -> 9 | AU4: =((AS4-AT4)*$B4) -> 0 | AX4: =+AV4+AW4 -> 0 | AY4: =+AX4-BA4 -> 0 | AZ4: =((AX4-AY4)*$B4) -> 0 | BC4: =+BA4+BB4 -> 0 | BD4: =+BC4-BF4 -> 0 | BE4: =((BC4-BD4)*$B4) -> 0 | BH4: =+BF4+BG4 -> 0 | BI4: =+BH4-BK4 -> 0 | BJ4: =((BH4-BI4)*$B4) -> 0
A5: My foundation 2 en 1 (base lÍquida) | B5: 23000 | AD5: =+AB5+AC5 -> 0 | AE5: =+AD5-AG5 -> -6 | AF5: =((AD5-AE5)*$B5) -> 138000 | AG5: 6 | AI5: =+AG5+AH5 -> 6 | AJ5: =+AI5-AL5 -> 1 | AK5: =((AI5-AJ5)*$B5) -> 115000 | AL5: 5 | AN5: =+AL5+AM5 -> 5 | AO5: =+AN5-AQ5 -> 0 | AP5: =((AN5-AO5)*$B5) -> 115000 | AQ5: 5 | AS5: =+AQ5+AR5 -> 5 | AT5: =+AS5-AV5 -> 5 | AU5: =((AS5-AT5)*$B5) -> 0 | AX5: =+AV5+AW5 -> 0 | AY5: =+AX5-BA5 -> 0 | AZ5: =((AX5-AY5)*$B5) -> 0 | BC5: =+BA5+BB5 -> 0 | BD5: =+BC5-BF5 -> 0 | BE5: =((BC5-BD5)*$B5) -> 0 | BH5: =+BF5+BG5 -> 0 | BI5: =+BH5-BK5 -> 0 | BJ5: =((BH5-BI5)*$B5) -> 0
A6: Bloom fresh mini | B6: 14000 | AD6: =+AB6+AC6 -> 0 | AE6: =+AD6-AG6 -> -2 | AF6: =((AD6-AE6)*$B6) -> 28000 | AG6: 2 | AI6: =+AG6+AH6 -> 2 | AJ6: =+AI6-AL6 -> 0 | AK6: =((AI6-AJ6)*$B6) -> 28000 | AL6: 2 | AN6: =+AL6+AM6 -> 2 | AO6: =+AN6-AQ6 -> 1 | AP6: =((AN6-AO6)*$B6) -> 14000 | AQ6: 1 | AS6: =+AQ6+AR6 -> 1 | AT6: =+AS6-AV6 -> 1 | AU6: =((AS6-AT6)*$B6) -> 0
A7: Duo shell tint + mini mimosa | B7: 16000 | AD7: =+AB7+AC7 -> 0 | AE7: =+AD7-AG7 -> -3 | AF7: =((AD7-AE7)*$B7) -> 48000 | AG7: 3 | AI7: =+AG7+AH7 -> 3 | AJ7: =+AI7-AL7 -> 2 | AK7: =((AI7-AJ7)*$B7) -> 16000 | AL7: 1 | AM7: 3 | AN7: =+AL7+AM7 -> 4 | AO7: =+AN7-AQ7 -> 1 | AP7: =((AN7-AO7)*$B7) -> 48000 | AQ7: 3 | AS7: =+AQ7+AR7 -> 3 | AT7: =+AS7-AV7 -> 3 | AU7: =((AS7-AT7)*$B7) -> 0
A8: Bloom honey | B8: 9000 | AD8: =+AB8+AC8 -> 0 | AE8: =+AD8-AG8 -> -2 | AF8: =((AD8-AE8)*$B8) -> 18000 | AG8: 2 | AI8: =+AG8+AH8 -> 2 | AJ8: =+AI8-AL8 -> 2 | AK8: =((AI8-AJ8)*$B8) -> 0 | AL8: 0 | AN8: =+AL8+AM8 -> 0 | AO8: =+AN8-AQ8 -> 0 | AP8: =((AN8-AO8)*$B8) -> 0 | AQ8: 0 | AS8: =+AQ8+AR8 -> 0 | AT8: =+AS8-AV8 -> 0 | AU8: =((AS8-AT8)*$B8) -> 0
A9: Bloom fusion brillo hidratante | B9: 10000 | AD9: =+AB9+AC9 -> 0 | AE9: =+AD9-AG9 -> -3 | AF9: =((AD9-AE9)*$B9) -> 30000 | AG9: 3 | AI9: =+AG9+AH9 -> 3 | AJ9: =+AI9-AL9 -> 1 | AK9: =((AI9-AJ9)*$B9) -> 20000 | AL9: 2 | AM9: 2 | AN9: =+AL9+AM9 -> 4 | AO9: =+AN9-AQ9 -> 0 | AP9: =((AN9-AO9)*$B9) -> 40000 | AQ9: 4 | AS9: =+AQ9+AR9 -> 4 | AT9: =+AS9-AV9 -> 4 | AU9: =((AS9-AT9)*$B9) -> 0
A10: Lash resistente water proof | B10: 14000 | AD10: =+AB10+AC10 -> 0 | AE10: =+AD10-AG10 -> -3 | AF10: =((AD10-AE10)*$B10) -> 42000 | AG10: 3 | AI10: =+AG10+AH10 -> 3 | AJ10: =+AI10-AL10 -> 0 | AK10: =((AI10-AJ10)*$B10) -> 42000 | AL10: 3 | AN10: =+AL10+AM10 -> 3 | AO10: =+AN10-AQ10 -> 0 | AP10: =((AN10-AO10)*$B10) -> 42000 | AQ10: 3 | AS10: =+AQ10+AR10 -> 3 | AT10: =+AS10-AV10 -> 3 | AU10: =((AS10-AT10)*$B10) -> 0
A11: Bloom oil control | B11: 15000 | AD11: =+AB11+AC11 -> 0 | AE11: =+AD11-AG11 -> -2 | AF11: =((AD11-AE11)*$B11) -> 30000 | AG11: 2 | AI11: =+AG11+AH11 -> 2 | AJ11: =+AI11-AL11 -> 1 | AK11: =((AI11-AJ11)*$B11) -> 15000 | AL11: 1 | AN11: =+AL11+AM11 -> 1 | AO11: =+AN11-AQ11 -> 0 | AP11: =((AN11-AO11)*$B11) -> 15000 | AQ11: 1 | AS11: =+AQ11+AR11 -> 1 | AT11: =+AS11-AV11 -> 1 | AU11: =((AS11-AT11)*$B11) -> 0
A12: Bloom powder paper papel absorbente | B12: 16000 | AD12: =+AB12+AC12 -> 0 | AE12: =+AD12-AG12 -> -3 | AF12: =((AD12-AE12)*$B12) -> 48000 | AG12: 3 | AI12: =+AG12+AH12 -> 3 | AJ12: =+AI12-AL12 -> 0 | AK12: =((AI12-AJ12)*$B12) -> 48000 | AL12: 3 | AN12: =+AL12+AM12 -> 3 | AO12: =+AN12-AQ12 -> 1 | AP12: =((AN12-AO12)*$B12) -> 32000 | AQ12: 2 | AS12: =+AQ12+AR12 -> 2 | AT12: =+AS12-AV12 -> 2 | AU12: =((AS12-AT12)*$B12) -> 0
A13: Bloom cleanser lumi gel | B13: 26000 | AD13: =+AB13+AC13 -> 0 | AE13: =+AD13-AG13 -> -2 | AF13: =((AD13-AE13)*$B13) -> 52000 | AG13: 2 | AI13: =+AG13+AH13 -> 2 | AJ13: =+AI13-AL13 -> 0 | AK13: =((AI13-AJ13)*$B13) -> 52000 | AL13: 2 | AN13: =+AL13+AM13 -> 2 | AO13: =+AN13-AQ13 -> 0 | AP13: =((AN13-AO13)*$B13) -> 52000 | AQ13: 2 | AS13: =+AQ13+AR13 -> 2 | AT13: =+AS13-AV13 -> 2 | AU13: =((AS13-AT13)*$B13) -> 0
A14: Mini bloom fix fijador | B14: 20000 | AE14: =+AD14-AG14 -> -2 | AF14: =((AD14-AE14)*$B14) -> 40000 | AG14: 2 | AI14: =+AG14+AH14 -> 2 | AJ14: =+AI14-AL14 -> 0 | AK14: =((AI14-AJ14)*$B14) -> 40000 | AL14: 2 | AN14: =+AL14+AM14 -> 2 | AO14: =+AN14-AQ14 -> 1 | AP14: =((AN14-AO14)*$B14) -> 20000 | AQ14: 1 | AS14: =+AQ14+AR14 -> 1 | AT14: =+AS14-AV14 -> 1 | AU14: =((AS14-AT14)*$B14) -> 0
A15: Bloom aqua fruit (brillo labial) | B15: 11000 | AE15: =+AD15-AG15 -> -4 | AF15: =((AD15-AE15)*$B15) -> 44000 | AG15: 4 | AI15: =+AG15+AH15 -> 4 | AJ15: =+AI15-AL15 -> 3 | AK15: =((AI15-AJ15)*$B15) -> 11000 | AL15: 1 | AN15: =+AL15+AM15 -> 1 | AO15: =+AN15-AQ15 -> 0 | AP15: =((AN15-AO15)*$B15) -> 11000 | AQ15: 1 | AS15: =+AQ15+AR15 -> 1 | AT15: =+AS15-AV15 -> 1 | AU15: =((AS15-AT15)*$B15) -> 0
A16: Bloom essential cream | B16: 36000 | AE16: =+AD16-AG16 -> -1 | AF16: =((AD16-AE16)*$B16) -> 36000 | AG16: 1 | AI16: =+AG16+AH16 -> 1 | AJ16: =+AI16-AL16 -> 0 | AK16: =((AI16-AJ16)*$B16) -> 36000 | AL16: 1 | AN16: =+AL16+AM16 -> 1 | AO16: =+AN16-AQ16 -> 0 | AP16: =((AN16-AO16)*$B16) -> 36000 | AQ16: 1 | AS16: =+AQ16+AR16 -> 1 | AT16: =+AS16-AV16 -> 1 | AU16: =((AS16-AT16)*$B16) -> 0
A17: Bloom repair cream | B17: 36000 | AE17: =+AD17-AG17 -> -1 | AF17: =((AD17-AE17)*$B17) -> 36000 | AG17: 1 | AI17: =+AG17+AH17 -> 1 | AJ17: =+AI17-AL17 -> 0 | AK17: =((AI17-AJ17)*$B17) -> 36000 | AL17: 1 | AN17: =+AL17+AM17 -> 1 | AO17: =+AN17-AQ17 -> 1 | AP17: =((AN17-AO17)*$B17) -> 0 | AQ17: 0 | AS17: =+AQ17+AR17 -> 0 | AT17: =+AS17-AV17 -> 0 | AU17: =((AS17-AT17)*$B17) -> 0
A18: Bloom latte lip balm /brillo hidratante | B18: 12000 | AE18: =+AD18-AG18 -> -3 | AF18: =((AD18-AE18)*$B18) -> 36000 | AG18: 3 | AI18: =+AG18+AH18 -> 3 | AJ18: =+AI18-AL18 -> 0 | AK18: =((AI18-AJ18)*$B18) -> 36000 | AL18: 3 | AN18: =+AL18+AM18 -> 3 | AO18: =+AN18-AQ18 -> 0 | AP18: =((AN18-AO18)*$B18) -> 36000 | AQ18: 3 | AS18: =+AQ18+AR18 -> 3 | AT18: =+AS18-AV18 -> 3 | AU18: =((AS18-AT18)*$B18) -> 0
A19: Hydra Bloom | B19: 9000 | AE19: =+AD19-AG19 -> 0 | AF19: =((AD19-AE19)*$B19) -> 0 | AG19: 0 | AI19: =+AG19+AH19 -> 0 | AJ19: =+AI19-AL19 -> 0 | AK19: =((AI19-AJ19)*$B19) -> 0 | AL19: 0 | AM19: 4 | AN19: =+AL19+AM19 -> 4 | AO19: =+AN19-AQ19 -> 0 | AP19: =((AN19-AO19)*$B19) -> 36000 | AQ19: 4 | AS19: =+AQ19+AR19 -> 4 | AT19: =+AS19-AV19 -> 4 | AU19: =((AS19-AT19)*$B19) -> 0
A20: Shine Bloomsiren | B20: 10000 | AE20: =+AD20-AG20 -> 0 | AF20: =((AD20-AE20)*$B20) -> 0 | AG20: 0 | AI20: =+AG20+AH20 -> 0 | AJ20: =+AI20-AL20 -> 0 | AK20: =((AI20-AJ20)*$B20) -> 0 | AL20: 0 | AM20: 3 | AN20: =+AL20+AM20 -> 3 | AO20: =+AN20-AQ20 -> 0 | AP20: =((AN20-AO20)*$B20) -> 30000 | AQ20: 3 | AS20: =+AQ20+AR20 -> 3 | AT20: =+AS20-AV20 -> 3 | AU20: =((AS20-AT20)*$B20) -> 0
A21: Bloom Meow | B21: 10000 | AE21: =+AD21-AG21 -> 0 | AF21: =((AD21-AE21)*$B21) -> 0 | AG21: 0 | AI21: =+AG21+AH21 -> 0 | AJ21: =+AI21-AL21 -> 0 | AK21: =((AI21-AJ21)*$B21) -> 0 | AL21: 0 | AM21: 3 | AN21: =+AL21+AM21 -> 3 | AO21: =+AN21-AQ21 -> 0 | AP21: =((AN21-AO21)*$B21) -> 30000 | AQ21: 3 | AS21: =+AQ21+AR21 -> 3 | AT21: =+AS21-AV21 -> 3 | AU21: =((AS21-AT21)*$B21) -> 0
A22: Bloom latte kiss (brillo labial) | B22: 13000 | AE22: =+AD22-AG22 -> -3 | AF22: =((AD22-AE22)*$B22) -> 39000 | AG22: 3 | AI22: =+AG22+AH22 -> 3 | AJ22: =+AI22-AL22 -> 0 | AK22: =((AI22-AJ22)*$B22) -> 39000 | AL22: 3 | AN22: =+AL22+AM22 -> 3 | AO22: =+AN22-AQ22 -> 0 | AP22: =((AN22-AO22)*$B22) -> 39000 | AQ22: 3 | AS22: =+AQ22+AR22 -> 3 | AT22: =+AS22-AV22 -> 3 | AU22: =((AS22-AT22)*$B22) -> 0
G23: =SUM(G3:G22) -> 0 | L23: =SUM(L3:L22) -> 0 | Q23: =SUM(Q3:Q22) -> 0 | V23: =SUM(V3:V22) -> 0 | AA23: =SUM(AA3:AA22) -> 0 | AF23: =SUM(AF3:AF22) -> 893000 | AK23: =SUM(AK3:AK22) -> 732000 | AP23: =+SUM(AP3:AP22) -> 779000 | AU23: =+SUM(AU3:AU22) -> 0 | AZ23: =+SUM(AZ3:AZ22) -> 0 | BE23: =+SUM(BE3:BE22) -> 0 | BJ23: =+SUM(BJ3:BJ22) -> 0

Sheet LULA
A1: LULA | C1: ENERO | H1: FEBRERO | M1: MARZO | R1: ABRIL | W1: MAYO | AB1: JUNIO | AG1: JULIO | AL1: AGOSTO | AQ1: SEPTIEMBRE | AV1: OCTUBRE | BA1: NOVIEMBRE | BF1: DICIEMBRE | BK1: ENERO
A2: PRODUCTO | B2: VR. COMPRA | C2: INV.I | D2: Entra | E2: Saldo | F2: SALIDA | G2: TOTAL | H2: INV.I | I2: Entra | J2: Saldo | K2: SALIDA | L2: TOTAL | M2: INV.I | N2: Entra | O2: Saldo | P2: SALIDA | Q2: TOTAL | R2: INV.I | S2: Entra | T2: Saldo | U2: SALIDA | V2: TOTAL | W2: INV.I | X2: Entra | Y2: Saldo | Z2: SALIDA | AA2: TOTAL | AB2: INV.I | AC2: Entra | AD2: Saldo | AE2: SALIDA | AF2: TOTAL | AG2: INV.I | AH2: Entra | AI2: Saldo | AJ2: SALIDA | AK2: TOTAL | AL2: INV.I | AM2: Entra | AN2: Saldo | AO2: SALIDA | AP2: TOTAL | AQ2: INV.I | AR2: Entra | AS2: Saldo | AT2: SALIDA | AU2: TOTAL | AV2: INV.I | AW2: Entra | AX2: Saldo | AY2: SALIDA | AZ2: TOTAL | BA2: INV.I | BB2: Entra | BC2: Saldo | BD2: SALIDA | BE2: TOTAL | BF2: INV.I | BG2: Entra | BH2: Saldo | BI2: SALIDA | BJ2: TOTAL | BK2: INV.I
A3: Polvo Suelto Traslúcido Banana | B3: 11000 | AD3: =+AB3+AC3 -> 0 | AE3: =+AD3-AG3 -> -3 | AF3: =((AD3-AE3)*$B3) -> 33000 | AG3: 3 | AI3: =+AG3+AH3 -> 3 | AJ3: =+AI3-AL3 -> 1 | AK3: =((AI3-AJ3)*$B3) -> 22000 | AL3: 2 | AM3: 3 | AN3: =+AL3+AM3 -> 5 | AO3: =+AN3-AQ3 -> 1 | AP3: =((AN3-AO3)*$B3) -> 44000 | AQ3: 4 | AS3: =+AQ3+AR3 -> 4 | AT3: =+AS3-AV3 -> 4 | AU3: =((AS3-AT3)*$B3) -> 0 | AX3: =+AV3+AW3 -> 0 | AY3: =+AX3-BA3 -> 0 | AZ3: =((AX3-AY3)*$B3) -> 0 | BC3: =+BA3+BB3 -> 0 | BD3: =+BC3-BF3 -> 0 | BE3: =((BC3-BD3)*$B3) -> 0 | BH3: =+BF3+BG3 -> 0 | BI3: =+BH3-BK3 -> 0 | BJ3: =((BH3-BI3)*$B3) -> 0
A4: Primer Facial Suavizante | B4: 16000 | AD4: =+AB4+AC4 -> 0 | AE4: =+AD4-AG4 -> -2 | AF4: =((AD4-AE4)*$B4) -> 32000 | AG4: 2 | AI4: =+AG4+AH4 -> 2 | AJ4: =+AI4-AL4 -> 1 | AK4: =((AI4-AJ4)*$B4) -> 16000 | AL4: 1 | AN4: =+AL4+AM4 -> 1 | AO4: =+AN4-AQ4 -> 0 | AP4: =((AN4-AO4)*$B4) -> 16000 | AQ4: 1 | AS4: =+AQ4+AR4 -> 1 | AT4: =+AS4-AV4 -> 1 | AU4: =((AS4-AT4)*$B4) -> 0 | AX4: =+AV4+AW4 -> 0 | AY4: =+AX4-BA4 -> 0 | AZ4: =((AX4-AY4)*$B4) -> 0 | BC4: =+BA4+BB4 -> 0 | BD4: =+BC4-BF4 -> 0 | BE4: =((BC4-BD4)*$B4) -> 0 | BH4: =+BF4+BG4 -> 0 | BI4: =+BH4-BK4 -> 0 | BJ4: =((BH4-BI4)*$B4) -> 0
A5: Agua Micelar | B5: 18000 | AD5: =+AB5+AC5 -> 0 | AE5: =+AD5-AG5 -> -1 | AF5: =((AD5-AE5)*$B5) -> 18000 | AG5: 1 | AI5: =+AG5+AH5 -> 1 | AJ5: =+AI5-AL5 -> 0 | AK5: =((AI5-AJ5)*$B5) -> 18000 | AL5: 1 | AM5: 2 | AN5: =+AL5+AM5 -> 3 | AO5: =+AN5-AQ5 -> 1 | AP5: =((AN5-AO5)*$B5) -> 36000 | AQ5: 2 | AS5: =+AQ5+AR5 -> 2 | AT5: =+AS5-AV5 -> 2 | AU5: =((AS5-AT5)*$B5) -> 0 | AX5: =+AV5+AW5 -> 0 | AY5: =+AX5-BA5 -> 0 | AZ5: =((AX5-AY5)*$B5) -> 0 | BC5: =+BA5+BB5 -> 0 | BD5: =+BC5-BF5 -> 0 | BE5: =((BC5-BD5)*$B5) -> 0 | BH5: =+BF5+BG5 -> 0 | BI5: =+BH5-BK5 -> 0 | BJ5: =((BH5-BI5)*$B5) -> 0
A6: Aceite para labios con charm | B6: 13000 | AD6: =+AB6+AC6 -> 0 | AE6: =+AD6-AG6 -> -7 | AF6: =((AD6-AE6)*$B6) -> 91000 | AG6: 7 | AI6: =+AG6+AH6 -> 7 | AJ6: =+AI6-AL6 -> 3 | AK6: =((AI6-AJ6)*$B6) -> 52000 | AL6: 4 | AN6: =+AL6+AM6 -> 4 | AO6: =+AN6-AQ6 -> 0 | AP6: =((AN6-AO6)*$B6) -> 52000 | AQ6: 4 | AS6: =+AQ6+AR6 -> 4 | AT6: =+AS6-AV6 -> 4 | AU6: =((AS6-AT6)*$B6) -> 0 | AX6: =+AV6+AW6 -> 0 | AY6: =+AX6-BA6 -> 0 | AZ6: =((AX6-AY6)*$B6) -> 0 | BC6: =+BA6+BB6 -> 0 | BD6: =+BC6-BF6 -> 0 | BE6: =((BC6-BD6)*$B6) -> 0 | BH6: =+BF6+BG6 -> 0 | BI6: =+BH6-BK6 -> 0 | BJ6: =((BH6-BI6)*$B6) -> 0
A7: Tinta para labios y mejillas | B7: 8000 | AD7: =+AB7+AC7 -> 0 | AE7: =+AD7-AG7 -> -4 | AF7: =((AD7-AE7)*$B7) -> 32000 | AG7: 4 | AI7: =+AG7+AH7 -> 4 | AJ7: =+AI7-AL7 -> 1 | AK7: =((AI7-AJ7)*$B7) -> 24000 | AL7: 3 | AN7: =+AL7+AM7 -> 3 | AO7: =+AN7-AQ7 -> 0 | AP7: =((AN7-AO7)*$B7) -> 24000 | AQ7: 3 | AS7: =+AQ7+AR7 -> 3 | AT7: =+AS7-AV7 -> 3 | AU7: =((AS7-AT7)*$B7) -> 0 | AX7: =+AV7+AW7 -> 0 | AY7: =+AX7-BA7 -> 0 | AZ7: =((AX7-AY7)*$B7) -> 0 | BC7: =+BA7+BB7 -> 0 | BD7: =+BC7-BF7 -> 0 | BE7: =((BC7-BD7)*$B7) -> 0 | BH7: =+BF7+BG7 -> 0 | BI7: =+BH7-BK7 -> 0 | BJ7: =((BH7-BI7)*$B7) -> 0
A8: Esponja de Maquillaje | B8: 4000 | AD8: =+AB8+AC8 -> 0 | AE8: =+AD8-AG8 -> -4 | AF8: =((AD8-AE8)*$B8) -> 16000 | AG8: 4 | AI8: =+AG8+AH8 -> 4 | AJ8: =+AI8-AL8 -> 1 | AK8: =((AI8-AJ8)*$B8) -> 12000 | AL8: 3 | AN8: =+AL8+AM8 -> 3 | AO8: =+AN8-AQ8 -> 2 | AP8: =((AN8-AO8)*$B8) -> 4000 | AQ8: 1 | AS8: =+AQ8+AR8 -> 1 | AT8: =+AS8-AV8 -> 1 | AU8: =((AS8-AT8)*$B8) -> 0 | AX8: =+AV8+AW8 -> 0 | AY8: =+AX8-BA8 -> 0 | AZ8: =((AX8-AY8)*$B8) -> 0 | BC8: =+BA8+BB8 -> 0 | BD8: =+BC8-BF8 -> 0 | BE8: =((BC8-BD8)*$B8) -> 0 | BH8: =+BF8+BG8 -> 0 | BI8: =+BH8-BK8 -> 0 | BJ8: =((BH8-BI8)*$B8) -> 0
A9: Limpiador de Brochas | B9: 17000 | AD9: =+AB9+AC9 -> 0 | AE9: =+AD9-AG9 -> 0 | AF9: =((AD9-AE9)*$B9) -> 0 | AI9: =+AG9+AH9 -> 0 | AJ9: =+AI9-AL9 -> 0 | AK9: =((AI9-AJ9)*$B9) -> 0 | AL9: 0 | AM9: 2 | AN9: =+AL9+AM9 -> 2 | AO9: =+AN9-AQ9 -> 0 | AP9: =((AN9-AO9)*$B9) -> 34000 | AQ9: 2 | AS9: =+AQ9+AR9 -> 2 | AT9: =+AS9-AV9 -> 2 | AU9: =((AS9-AT9)*$B9) -> 0 | AX9: =+AV9+AW9 -> 0 | AY9: =+AX9-BA9 -> 0 | AZ9: =((AX9-AY9)*$B9) -> 0 | BC9: =+BA9+BB9 -> 0 | BD9: =+BC9-BF9 -> 0 | BE9: =((BC9-BD9)*$B9) -> 0 | BH9: =+BF9+BG9 -> 0 | BI9: =+BH9-BK9 -> 0 | BJ9: =((BH9-BI9)*$B9) -> 0
A10: Limpiador bifásico | B10: 18000 | AD10: =+AB10+AC10 -> 0 | AE10: =+AD10-AG10 -> -1 | AF10: =((AD10-AE10)*$B10) -> 18000 | AG10: 1 | AI10: =+AG10+AH10 -> 1 | AJ10: =+AI10-AL10 -> 0 | AK10: =((AI10-AJ10)*$B10) -> 18000 | AL10: 1 | AN10: =+AL10+AM10 -> 1 | AO10: =+AN10-AQ10 -> 1 | AP10: =((AN10-AO10)*$B10) -> 0 | AQ10: 0 | AS10: =+AQ10+AR10 -> 0 | AT10: =+AS10-AV10 -> 0 | AU10: =((AS10-AT10)*$B10) -> 0 | AX10: =+AV10+AW10 -> 0 | AY10: =+AX10-BA10 -> 0 | AZ10: =((AX10-AY10)*$B10) -> 0 | BC10: =+BA10+BB10 -> 0 | BD10: =+BC10-BF10 -> 0 | BE10: =((BC10-BD10)*$B10) -> 0 | BH10: =+BF10+BG10 -> 0 | BI10: =+BH10-BK10 -> 0 | BJ10: =((BH10-BI10)*$B10) -> 0
G11: =SUM(G3:G10) -> 0 | L11: =SUM(L3:L10) -> 0 | Q11: =SUM(Q3:Q10) -> 0 | V11: =SUM(V3:V10) -> 0 | AA11: =SUM(AA3:AA10) -> 0 | AF11: =SUM(AF3:AF10) -> 240000 | AK11: =SUM(AK3:AK10) -> 162000 | AP11: =+SUM(AP3:AP10) -> 210000 | AU11: =+SUM(AU3:AU10) -> 0 | AZ11: 3037000 | BE11: =+SUM(BE3:BE10) -> 0 | BJ11: =+SUM(BJ3:BJ10) -> 0

Sheet ANIK
A1: ANI-K | C1: ENERO | H1: FEBRERO | M1: MARZO | R1: ABRIL | W1: MAYO | AB1: JUNIO | AG1: JULIO | AL1: AGOSTO | AQ1: SEPTIEMBRE | AV1: OCTUBRE | BA1: NOVIEMBRE | BF1: DICIEMBRE | BK1: ENERO
A2: PRODUCTO | B2: VR. COMPRA | C2: INV.I | D2: Entra | E2: Saldo | F2: SALIDA | G2: TOTAL | H2: INV.I | I2: Entra | J2: Saldo | K2: SALIDA | L2: TOTAL | M2: INV.I | N2: Entra | O2: Saldo | P2: SALIDA | Q2: TOTAL | R2: INV.I | S2: Entra | T2: Saldo | U2: SALIDA | V2: TOTAL | W2: INV.I | X2: Entra | Y2: Saldo | Z2: SALIDA | AA2: TOTAL | AB2: INV.I | AC2: Entra | AD2: Saldo | AE2: SALIDA | AF2: TOTAL | AG2: INV.I | AH2: Entra | AI2: Saldo | AJ2: SALIDA | AK2: TOTAL | AL2: INV.I | AM2: Entra | AN2: Saldo | AO2: SALIDA | AP2: TOTAL | AQ2: INV.I | AR2: Entra | AS2: Saldo | AT2: SALIDA | AU2: TOTAL | AV2: INV.I | AW2: Entra | AX2: Saldo | AY2: SALIDA | AZ2: TOTAL | BA2: INV.I | BB2: Entra | BC2: Saldo | BD2: SALIDA | BE2: TOTAL | BF2: INV.I | BG2: Entra | BH2: Saldo | BI2: SALIDA | BJ2: TOTAL | BK2: INV.I
A3: Iluminador Radiante | B3: 15500 | AD3: =+AB3+AC3 -> 0 | AE3: =+AD3-AG3 -> -2 | AF3: =((AD3-AE3)*$B3) -> 31000 | AG3: 2 | AI3: =+AG3+AH3 -> 2 | AJ3: =+AI3-AL3 -> 1 | AK3: =((AI3-AJ3)*$B3) -> 15500 | AL3: 1 | AN3: =+AL3+AM3 -> 1 | AO3: =+AN3-AQ3 -> 0 | AP3: =((AN3-AO3)*$B3) -> 15500 | AQ3: 1 | AS3: =+AQ3+AR3 -> 1 | AT3: =+AS3-AV3 -> 1 | AU3: =((AS3-AT3)*$B3) -> 0 | AX3: =+AV3+AW3 -> 0 | AY3: =+AX3-BA3 -> 0 | AZ3: =((AX3-AY3)*$B3) -> 0 | BC3: =+BA3+BB3 -> 0 | BD3: =+BC3-BF3 -> 0 | BE3: =((BC3-BD3)*$B3) -> 0 | BH3: =+BF3+BG3 -> 0 | BI3: =+BH3-BK3 -> 0 | BJ3: =((BH3-BI3)*$B3) -> 0
A4: Rubor Bonita | B4: 10500 | AD4: =+AB4+AC4 -> 0 | AE4: =+AD4-AG4 -> -3 | AF4: =((AD4-AE4)*$B4) -> 31500 | AG4: 3 | AI4: =+AG4+AH4 -> 3 | AJ4: =+AI4-AL4 -> 2 | AK4: =((AI4-AJ4)*$B4) -> 10500 | AL4: 1 | AN4: =+AL4+AM4 -> 1 | AO4: =+AN4-AQ4 -> 0 | AP4: =((AN4-AO4)*$B4) -> 10500 | AQ4: 1 | AS4: =+AQ4+AR4 -> 1 | AT4: =+AS4-AV4 -> 1 | AU4: =((AS4-AT4)*$B4) -> 0 | AX4: =+AV4+AW4 -> 0 | AY4: =+AX4-BA4 -> 0 | AZ4: =((AX4-AY4)*$B4) -> 0 | BC4: =+BA4+BB4 -> 0 | BD4: =+BC4-BF4 -> 0 | BE4: =((BC4-BD4)*$B4) -> 0 | BH4: =+BF4+BG4 -> 0 | BI4: =+BH4-BK4 -> 0 | BJ4: =((BH4-BI4)*$B4) -> 0
A5: Rubor Mineralizado | B5: 13500 | AD5: =+AB5+AC5 -> 0 | AE5: =+AD5-AG5 -> -2 | AF5: =((AD5-AE5)*$B5) -> 27000 | AG5: 2 | AI5: =+AG5+AH5 -> 2 | AJ5: =+AI5-AL5 -> 0 | AK5: =((AI5-AJ5)*$B5) -> 27000 | AL5: 2 | AN5: =+AL5+AM5 -> 2 | AO5: =+AN5-AQ5 -> 0 | AP5: =((AN5-AO5)*$B5) -> 27000 | AQ5: 2 | AS5: =+AQ5+AR5 -> 2 | AT5: =+AS5-AV5 -> 2 | AU5: =((AS5-AT5)*$B5) -> 0 | AX5: =+AV5+AW5 -> 0 | AY5: =+AX5-BA5 -> 0 | AZ5: =((AX5-AY5)*$B5) -> 0 | BC5: =+BA5+BB5 -> 0 | BD5: =+BC5-BF5 -> 0 | BE5: =((BC5-BD5)*$B5) -> 0 | BH5: =+BF5+BG5 -> 0 | BI5: =+BH5-BK5 -> 0 | BJ5: =((BH5-BI5)*$B5) -> 0
A6: Kit de Cejas | B6: 15500 | AD6: =+AB6+AC6 -> 0 | AE6: =+AD6-AG6 -> -2 | AF6: =((AD6-AE6)*$B6) -> 31000 | AG6: 2 | AI6: =+AG6+AH6 -> 2 | AJ6: =+AI6-AL6 -> 1 | AK6: =((AI6-AJ6)*$B6) -> 15500 | AL6: 1 | AN6: =+AL6+AM6 -> 1 | AO6: =+AN6-AQ6 -> 0 | AP6: =((AN6-AO6)*$B6) -> 15500 | AQ6: 1 | AS6: =+AQ6+AR6 -> 1 | AT6: =+AS6-AV6 -> 1 | AU6: =((AS6-AT6)*$B6) -> 0
A7: Rubor Líquido Bonita | B7: 16000 | AD7: =+AB7+AC7 -> 0 | AE7: =+AD7-AG7 -> -4 | AF7: =((AD7-AE7)*$B7) -> 64000 | AG7: 4 | AI7: =+AG7+AH7 -> 4 | AJ7: =+AI7-AL7 -> 1 | AK7: =((AI7-AJ7)*$B7) -> 48000 | AL7: 3 | AN7: =+AL7+AM7 -> 3 | AO7: =+AN7-AQ7 -> 0 | AP7: =((AN7-AO7)*$B7) -> 48000 | AQ7: 3 | AS7: =+AQ7+AR7 -> 3 | AT7: =+AS7-AV7 -> 3 | AU7: =((AS7-AT7)*$B7) -> 0
A8: Serum Blush Flushy Blushy | B8: 18000 | AD8: =+AB8+AC8 -> 0 | AE8: =+AD8-AG8 -> -2 | AF8: =((AD8-AE8)*$B8) -> 36000 | AG8: 2 | AI8: =+AG8+AH8 -> 2 | AJ8: =+AI8-AL8 -> 2 | AK8: =((AI8-AJ8)*$B8) -> 0 | AL8: 0 | AM8: 4 | AN8: =+AL8+AM8 -> 4 | AO8: =+AN8-AQ8 -> 0 | AP8: =((AN8-AO8)*$B8) -> 72000 | AQ8: 4 | AS8: =+AQ8+AR8 -> 4 | AT8: =+AS8-AV8 -> 4 | AU8: =((AS8-AT8)*$B8) -> 0
A9: Contorno líquido | B9: 16000 | AD9: =+AB9+AC9 -> 0 | AE9: =+AD9-AG9 -> -3 | AF9: =((AD9-AE9)*$B9) -> 48000 | AG9: 3 | AI9: =+AG9+AH9 -> 3 | AJ9: =+AI9-AL9 -> 0 | AK9: =((AI9-AJ9)*$B9) -> 48000 | AL9: 3 | AN9: =+AL9+AM9 -> 3 | AO9: =+AN9-AQ9 -> 0 | AP9: =((AN9-AO9)*$B9) -> 48000 | AQ9: 3 | AS9: =+AQ9+AR9 -> 3 | AT9: =+AS9-AV9 -> 3 | AU9: =((AS9-AT9)*$B9) -> 0
A10: Base Bonita | B10: 26000 | AD10: =+AB10+AC10 -> 0 | AE10: =+AD10-AG10 -> -3 | AF10: =((AD10-AE10)*$B10) -> 78000 | AG10: 3 | AH10: 1 | AI10: =+AG10+AH10 -> 4 | AJ10: =+AI10-AL10 -> 1 | AK10: =((AI10-AJ10)*$B10) -> 78000 | AL10: 3 | AM10: 5 | AN10: =+AL10+AM10 -> 8 | AO10: =+AN10-AQ10 -> 0 | AP10: =((AN10-AO10)*$B10) -> 208000 | AQ10: 8 | AS10: =+AQ10+AR10 -> 8 | AT10: =+AS10-AV10 -> 8 | AU10: =((AS10-AT10)*$B10) -> 0
A11: Iluminador Suelto | B11: 14000 | AD11: =+AB11+AC11 -> 0 | AE11: =+AD11-AG11 -> -3 | AF11: =((AD11-AE11)*$B11) -> 42000 | AG11: 3 | AI11: =+AG11+AH11 -> 3 | AJ11: =+AI11-AL11 -> 1 | AK11: =((AI11-AJ11)*$B11) -> 28000 | AL11: 2 | AN11: =+AL11+AM11 -> 2 | AO11: =+AN11-AQ11 -> 0 | AP11: =((AN11-AO11)*$B11) -> 28000 | AQ11: 2 | AS11: =+AQ11+AR11 -> 2 | AT11: =+AS11-AV11 -> 2 | AU11: =((AS11-AT11)*$B11) -> 0
A12: Lapiz Doble para Cejas | B12: 9500 | AD12: =+AB12+AC12 -> 0 | AE12: =+AD12-AG12 -> -2 | AF12: =((AD12-AE12)*$B12) -> 19000 | AG12: 2 | AI12: =+AG12+AH12 -> 2 | AJ12: =+AI12-AL12 -> 0 | AK12: =((AI12-AJ12)*$B12) -> 19000 | AL12: 2 | AN12: =+AL12+AM12 -> 2 | AO12: =+AN12-AQ12 -> 1 | AP12: =((AN12-AO12)*$B12) -> 9500 | AQ12: 1 | AS12: =+AQ12+AR12 -> 1 | AT12: =+AS12-AV12 -> 1 | AU12: =((AS12-AT12)*$B12) -> 0
A13: Lip Gloss Bonita Brillo labial | B13: 12500 | AD13: =+AB13+AC13 -> 0 | AE13: =+AD13-AG13 -> -2 | AF13: =((AD13-AE13)*$B13) -> 25000 | AG13: 2 | AI13: =+AG13+AH13 -> 2 | AJ13: =+AI13-AL13 -> 0 | AK13: =((AI13-AJ13)*$B13) -> 25000 | AL13: 2 | AN13: =+AL13+AM13 -> 2 | AO13: =+AN13-AQ13 -> 0 | AP13: =((AN13-AO13)*$B13) -> 25000 | AQ13: 2 | AS13: =+AQ13+AR13 -> 2 | AT13: =+AS13-AV13 -> 2 | AU13: =((AS13-AT13)*$B13) -> 0
A14: Delineador Radiante | B14: 12000 | AD14: =+AB14+AC14 -> 0 | AE14: =+AD14-AG14 -> -4 | AF14: =((AD14-AE14)*$B14) -> 48000 | AG14: 4 | AI14: =+AG14+AH14 -> 4 | AJ14: =+AI14-AL14 -> 1 | AK14: =((AI14-AJ14)*$B14) -> 36000 | AL14: 3 | AN14: =+AL14+AM14 -> 3 | AO14: =+AN14-AQ14 -> 0 | AP14: =((AN14-AO14)*$B14) -> 36000 | AQ14: 3 | AS14: =+AQ14+AR14 -> 3 | AT14: =+AS14-AV14 -> 3 | AU14: =((AS14-AT14)*$B14) -> 0
A15: Pestañina Café Brown Paradise a Prueba de Agua | B15: 14000 | AD15: =+AB15+AC15 -> 0 | AE15: =+AD15-AG15 -> -1 | AF15: =((AD15-AE15)*$B15) -> 14000 | AG15: 1 | AI15: =+AG15+AH15 -> 1 | AJ15: =+AI15-AL15 -> 0 | AK15: =((AI15-AJ15)*$B15) -> 14000 | AL15: 1 | AN15: =+AL15+AM15 -> 1 | AO15: =+AN15-AQ15 -> 0 | AP15: =((AN15-AO15)*$B15) -> 14000 | AQ15: 1 | AS15: =+AQ15+AR15 -> 1 | AT15: =+AS15-AV15 -> 1 | AU15: =((AS15-AT15)*$B15) -> 0
A16: Pestañina Café Brown Paradise | B16: 13000 | AD16: =+AB16+AC16 -> 0 | AE16: =+AD16-AG16 -> -1 | AF16: =((AD16-AE16)*$B16) -> 13000 | AG16: 1 | AI16: =+AG16+AH16 -> 1 | AJ16: =+AI16-AL16 -> 0 | AK16: =((AI16-AJ16)*$B16) -> 13000 | AL16: 1 | AN16: =+AL16+AM16 -> 1 | AO16: =+AN16-AQ16 -> 0 | AP16: =((AN16-AO16)*$B16) -> 13000 | AQ16: 1 | AS16: =+AQ16+AR16 -> 1 | AT16: =+AS16-AV16 -> 1 | AU16: =((AS16-AT16)*$B16) -> 0
A17: Pestañina Flash Lash | B17: 13000 | AD17: =+AB17+AC17 -> 0 | AE17: =+AD17-AG17 -> -1 | AF17: =((AD17-AE17)*$B17) -> 13000 | AG17: 1 | AI17: =+AG17+AH17 -> 1 | AJ17: =+AI17-AL17 -> 0 | AK17: =((AI17-AJ17)*$B17) -> 13000 | AL17: 1 | AN17: =+AL17+AM17 -> 1 | AO17: =+AN17-AQ17 -> 0 | AP17: =((AN17-AO17)*$B17) -> 13000 | AQ17: 1 | AS17: =+AQ17+AR17 -> 1 | AT17: =+AS17-AV17 -> 1 | AU17: =((AS17-AT17)*$B17) -> 0
A18: Brocha para Base AK2 | B18: 13000 | AD18: =+AB18+AC18 -> 0 | AE18: =+AD18-AG18 -> -1 | AF18: =((AD18-AE18)*$B18) -> 13000 | AG18: 1 | AI18: =+AG18+AH18 -> 1 | AJ18: =+AI18-AL18 -> 0 | AK18: =((AI18-AJ18)*$B18) -> 13000 | AL18: 1 | AN18: =+AL18+AM18 -> 1 | AO18: =+AN18-AQ18 -> 0 | AP18: =((AN18-AO18)*$B18) -> 13000 | AQ18: 1 | AS18: =+AQ18+AR18 -> 1 | AT18: =+AS18-AV18 -> 1 | AU18: =((AS18-AT18)*$B18) -> 0
A19: Brocha para corrector AK22 | B19: 11000 | AD19: =+AB19+AC19 -> 0 | AE19: =+AD19-AG19 -> -1 | AF19: =((AD19-AE19)*$B19) -> 11000 | AG19: 1 | AI19: =+AG19+AH19 -> 1 | AJ19: =+AI19-AL19 -> 1 | AK19: =((AI19-AJ19)*$B19) -> 0 | AL19: 0 | AN19: =+AL19+AM19 -> 0 | AO19: =+AN19-AQ19 -> 0 | AP19: =((AN19-AO19)*$B19) -> 0 | AQ19: 0 | AS19: =+AQ19+AR19 -> 0 | AT19: =+AS19-AV19 -> 0 | AU19: =((AS19-AT19)*$B19) -> 0
A20: Pincel ANI-K AK8 | B20: 7000 | AD20: =+AB20+AC20 -> 0 | AE20: =+AD20-AG20 -> -1 | AF20: =((AD20-AE20)*$B20) -> 7000 | AG20: 1 | AI20: =+AG20+AH20 -> 1 | AJ20: =+AI20-AL20 -> 0 | AK20: =((AI20-AJ20)*$B20) -> 7000 | AL20: 1 | AN20: =+AL20+AM20 -> 1 | AO20: =+AN20-AQ20 -> 0 | AP20: =((AN20-AO20)*$B20) -> 7000 | AQ20: 1 | AS20: =+AQ20+AR20 -> 1 | AT20: =+AS20-AV20 -> 1 | AU20: =((AS20-AT20)*$B20) -> 0
A21: BROCHA GLOBO MODELO AK5 | B21: 9500 | AD21: =+AB21+AC21 -> 0 | AE21: =+AD21-AG21 -> -1 | AF21: =((AD21-AE21)*$B21) -> 9500 | AG21: 1 | AI21: =+AG21+AH21 -> 1 | AJ21: =+AI21-AL21 -> 0 | AK21: =((AI21-AJ21)*$B21) -> 9500 | AL21: 1 | AN21: =+AL21+AM21 -> 1 | AO21: =+AN21-AQ21 -> 0 | AP21: =((AN21-AO21)*$B21) -> 9500 | AQ21: 1 | AS21: =+AQ21+AR21 -> 1 | AT21: =+AS21-AV21 -> 1 | AU21: =((AS21-AT21)*$B21) -> 0
A22: Brocha Mini Iconi-K x Juanito | B22: 15000 | AD22: =+AB22+AC22 -> 0 | AE22: =+AD22-AG22 -> -1 | AF22: =((AD22-AE22)*$B22) -> 15000 | AG22: 1 | AI22: =+AG22+AH22 -> 1 | AJ22: =+AI22-AL22 -> 1 | AK22: =((AI22-AJ22)*$B22) -> 0 | AL22: 0 | AM22: 2 | AN22: =+AL22+AM22 -> 2 | AO22: =+AN22-AQ22 -> 1 | AP22: =((AN22-AO22)*$B22) -> 15000 | AQ22: 1 | AS22: =+AQ22+AR22 -> 1 | AT22: =+AS22-AV22 -> 1 | AU22: =((AS22-AT22)*$B22) -> 0
A23: Brocha Iconi-K Ani-K x Juanito | B23: 15000 | AD23: =+AB23+AC23 -> 0 | AE23: =+AD23-AG23 -> -1 | AF23: =((AD23-AE23)*$B23) -> 15000 | AG23: 1 | AI23: =+AG23+AH23 -> 1 | AJ23: =+AI23-AL23 -> 0 | AK23: =((AI23-AJ23)*$B23) -> 15000 | AL23: 1 | AN23: =+AL23+AM23 -> 1 | AO23: =+AN23-AQ23 -> 0 | AP23: =((AN23-AO23)*$B23) -> 15000 | AQ23: 1 | AS23: =+AQ23+AR23 -> 1 | AT23: =+AS23-AV23 -> 1 | AU23: =((AS23-AT23)*$B23) -> 0
A24: Brocha para Rubor AK3 | B24: 12500 | AD24: =+AB24+AC24 -> 0 | AE24: =+AD24-AG24 -> 0 | AF24: =((AD24-AE24)*$B24) -> 0 | AG24: 0 | AI24: =+AG24+AH24 -> 0 | AJ24: =+AI24-AL24 -> 0 | AK24: =((AI24-AJ24)*$B24) -> 0 | AL24: 0 | AM24: 2 | AN24: =+AL24+AM24 -> 2 | AO24: =+AN24-AQ24 -> 0 | AP24: =((AN24-AO24)*$B24) -> 25000 | AQ24: 2 | AS24: =+AQ24+AR24 -> 2 | AT24: =+AS24-AV24 -> 2 | AU24: =((AS24-AT24)*$B24) -> 0
A25: Brocha para Polvo AK1 | B25: 12500 | AD25: =+AB25+AC25 -> 0 | AE25: =+AD25-AG25 -> 0 | AF25: =((AD25-AE25)*$B25) -> 0 | AG25: 0 | AI25: =+AG25+AH25 -> 0 | AJ25: =+AI25-AL25 -> 0 | AK25: =((AI25-AJ25)*$B25) -> 0 | AL25: 0 | AM25: 2 | AN25: =+AL25+AM25 -> 2 | AO25: =+AN25-AQ25 -> 0 | AP25: =((AN25-AO25)*$B25) -> 25000 | AQ25: 2 | AS25: =+AQ25+AR25 -> 2 | AT25: =+AS25-AV25 -> 2 | AU25: =((AS25-AT25)*$B25) -> 0
A26: GEL DE CEJAS | B26: 13500 | AD26: =+AB26+AC26 -> 0 | AE26: =+AD26-AG26 -> 0 | AF26: =((AD26-AE26)*$B26) -> 0 | AG26: 0 | AI26: =+AG26+AH26 -> 0 | AJ26: =+AI26-AL26 -> 0 | AK26: =((AI26-AJ26)*$B26) -> 0 | AL26: 0 | AM26: 6 | AN26: =+AL26+AM26 -> 6 | AO26: =+AN26-AQ26 -> 1 | AP26: =((AN26-AO26)*$B26) -> 67500 | AQ26: 5 | AS26: =+AQ26+AR26 -> 5 | AT26: =+AS26-AV26 -> 5 | AU26: =((AS26-AT26)*$B26) -> 0
A27: Corrector de ojeras | B27: 14500 | AD27: =+AB27+AC27 -> 0 | AE27: =+AD27-AG27 -> -2 | AF27: =((AD27-AE27)*$B27) -> 29000 | AG27: 2 | AI27: =+AG27+AH27 -> 2 | AJ27: =+AI27-AL27 -> 0 | AK27: =((AI27-AJ27)*$B27) -> 29000 | AL27: 2 | AN27: =+AL27+AM27 -> 2 | AO27: =+AN27-AQ27 -> 0 | AP27: =((AN27-AO27)*$B27) -> 29000 | AQ27: 2 | AS27: =+AQ27+AR27 -> 2 | AT27: =+AS27-AV27 -> 2 | AU27: =((AS27-AT27)*$B27) -> 0
G28: =SUM(G3:G27) -> 0 | L28: =SUM(L3:L27) -> 0 | Q28: =SUM(Q3:Q27) -> 0 | V28: =SUM(V3:V27) -> 0 | AA28: =SUM(AA3:AA27) -> 0 | AF28: =SUM(AF3:AF27) -> 620000 | AK28: =SUM(AK3:AK27) -> 464000 | AP28: =+SUM(AP3:AP27) -> 789000 | AU28: =+SUM(AU3:AU27) -> 0 | AZ28: =+SUM(AZ3:AZ27) -> 0 | BE28: =+SUM(BE3:BE27) -> 0 | BJ28: =+SUM(BJ3:BJ27) -> 0

Sheet FEBBLE
A1: FEBBLE | C1: ENERO | H1: FEBRERO | M1: MARZO | R1: ABRIL | W1: MAYO | AB1: JUNIO | AG1: JULIO | AL1: AGOSTO | AQ1: SEPTIEMBRE | AV1: OCTUBRE | BA1: NOVIEMBRE | BF1: DICIEMBRE | BK1: ENERO
A2: PRODUCTO | B2: VR. COMPRA | C2: INV.I | D2: Entra | E2: Saldo | F2: SALIDA | G2: TOTAL | H2: INV.I | I2: Entra | J2: Saldo | K2: SALIDA | L2: TOTAL | M2: INV.I | N2: Entra | O2: Saldo | P2: SALIDA | Q2: TOTAL | R2: INV.I | S2: Entra | T2: Saldo | U2: SALIDA | V2: TOTAL | W2: INV.I | X2: Entra | Y2: Saldo | Z2: SALIDA | AA2: TOTAL | AB2: INV.I | AC2: Entra | AD2: Saldo | AE2: SALIDA | AF2: TOTAL | AG2: INV.I | AH2: Entra | AI2: Saldo | AJ2: SALIDA | AK2: TOTAL | AL2: INV.I | AM2: Entra | AN2: Saldo | AO2: SALIDA | AP2: TOTAL | AQ2: INV.I | AR2: Entra | AS2: Saldo | AT2: SALIDA | AU2: TOTAL | AV2: INV.I | AW2: Entra | AX2: Saldo | AY2: SALIDA | AZ2: TOTAL | BA2: INV.I | BB2: Entra | BC2: Saldo | BD2: SALIDA | BE2: TOTAL | BF2: INV.I | BG2: Entra | BH2: Saldo | BI2: SALIDA | BJ2: TOTAL | BK2: INV.I
A3: Polvo Compacto Sedoso para Sellar y Fijar | B3: 27000 | AD3: =+AB3+AC3 -> 0 | AE3: =+AD3-AG3 -> -4 | AF3: =((AD3-AE3)*$B3) -> 108000 | AG3: 4 | AI3: =+AG3+AH3 -> 4 | AJ3: =+AI3-AL3 -> 2 | AK3: =((AI3-AJ3)*$B3) -> 54000 | AL3: 2 | AM3: 5 | AN3: =+AL3+AM3 -> 7 | AO3: =+AN3-AQ3 -> 2 | AP3: =((AN3-AO3)*$B3) -> 135000 | AQ3: 5 | AS3: =+AQ3+AR3 -> 5 | AT3: =+AS3-AV3 -> 5 | AU3: =((AS3-AT3)*$B3) -> 0 | AX3: =+AV3+AW3 -> 0 | AY3: =+AX3-BA3 -> 0 | AZ3: =((AX3-AY3)*$B3) -> 0 | BC3: =+BA3+BB3 -> 0 | BD3: =+BC3-BF3 -> 0 | BE3: =((BC3-BD3)*$B3) -> 0 | BH3: =+BF3+BG3 -> 0 | BI3: =+BH3-BK3 -> 0 | BJ3: =((BH3-BI3)*$B3) -> 0
A4: Contorno de Ojos con Cafeína | B4: 15000 | AD4: =+AB4+AC4 -> 0 | AE4: =+AD4-AG4 -> -3 | AF4: =((AD4-AE4)*$B4) -> 45000 | AG4: 3 | AI4: =+AG4+AH4 -> 3 | AJ4: =+AI4-AL4 -> 0 | AK4: =((AI4-AJ4)*$B4) -> 45000 | AL4: 3 | AN4: =+AL4+AM4 -> 3 | AO4: =+AN4-AQ4 -> 1 | AP4: =((AN4-AO4)*$B4) -> 30000 | AQ4: 2 | AS4: =+AQ4+AR4 -> 2 | AT4: =+AS4-AV4 -> 2 | AU4: =((AS4-AT4)*$B4) -> 0 | AX4: =+AV4+AW4 -> 0 | AY4: =+AX4-BA4 -> 0 | AZ4: =((AX4-AY4)*$B4) -> 0 | BC4: =+BA4+BB4 -> 0 | BD4: =+BC4-BF4 -> 0 | BE4: =((BC4-BD4)*$B4) -> 0 | BH4: =+BF4+BG4 -> 0 | BI4: =+BH4-BK4 -> 0 | BJ4: =((BH4-BI4)*$B4) -> 0
A5: Lip Balm voluminizador Fruits | B5: 10000 | AD5: =+AB5+AC5 -> 0 | AE5: =+AD5-AG5 -> -3 | AF5: =((AD5-AE5)*$B5) -> 30000 | AG5: 3 | AI5: =+AG5+AH5 -> 3 | AJ5: =+AI5-AL5 -> 0 | AK5: =((AI5-AJ5)*$B5) -> 30000 | AL5: 3 | AN5: =+AL5+AM5 -> 3 | AO5: =+AN5-AQ5 -> 1 | AP5: =((AN5-AO5)*$B5) -> 20000 | AQ5: 2 | AS5: =+AQ5+AR5 -> 2 | AT5: =+AS5-AV5 -> 2 | AU5: =((AS5-AT5)*$B5) -> 0 | AX5: =+AV5+AW5 -> 0 | AY5: =+AX5-BA5 -> 0 | AZ5: =((AX5-AY5)*$B5) -> 0 | BC5: =+BA5+BB5 -> 0 | BD5: =+BC5-BF5 -> 0 | BE5: =((BC5-BD5)*$B5) -> 0 | BH5: =+BF5+BG5 -> 0 | BI5: =+BH5-BK5 -> 0 | BJ5: =((BH5-BI5)*$B5) -> 0
A6: Lip Balm Mágico Flowers | B6: 10000 | AD6: =+AB6+AC6 -> 0 | AE6: =+AD6-AG6 -> -2 | AF6: =((AD6-AE6)*$B6) -> 20000 | AG6: 2 | AI6: =+AG6+AH6 -> 2 | AJ6: =+AI6-AL6 -> 1 | AK6: =((AI6-AJ6)*$B6) -> 10000 | AL6: 1 | AN6: =+AL6+AM6 -> 1 | AO6: =+AN6-AQ6 -> 0 | AP6: =((AN6-AO6)*$B6) -> 10000 | AQ6: 1 | AS6: =+AQ6+AR6 -> 1 | AT6: =+AS6-AV6 -> 1 | AU6: =((AS6-AT6)*$B6) -> 0 | AX6: =+AV6+AW6 -> 0 | AY6: =+AX6-BA6 -> 0 | AZ6: =((AX6-AY6)*$B6) -> 0 | BC6: =+BA6+BB6 -> 0 | BD6: =+BC6-BF6 -> 0 | BE6: =((BC6-BD6)*$B6) -> 0 | BH6: =+BF6+BG6 -> 0 | BI6: =+BH6-BK6 -> 0 | BJ6: =((BH6-BI6)*$B6) -> 0
G7: =SUM(G3:G6) -> 0 | L7: =SUM(L3:L6) -> 0 | Q7: =SUM(Q3:Q6) -> 0 | V7: =SUM(V3:V6) -> 0 | AA7: =SUM(AA3:AA6) -> 0 | AF7: =SUM(AF3:AF6) -> 203000 | AK7: =SUM(AK3:AK6) -> 139000 | AP7: =+SUM(AP3:AP6) -> 195000 | AU7: =+SUM(AU3:AU6) -> 0 | AZ7: 3037000 | BE7: =+SUM(BE3:BE6) -> 0 | BJ7: =+SUM(BJ3:BJ6) -> 0

Sheet PROSA
A1: PROSA | C1: ENERO | H1: FEBRERO | M1: MARZO | R1: ABRIL | W1: MAYO | AB1: JUNIO | AG1: JULIO | AL1: AGOSTO | AQ1: SEPTIEMBRE | AV1: OCTUBRE | BA1: NOVIEMBRE | BF1: DICIEMBRE | BK1: ENERO
A2: PRODUCTO | B2: VR. COMPRA | C2: INV.I | D2: Entra | E2: Saldo | F2: SALIDA | G2: TOTAL | H2: INV.I | I2: Entra | J2: Saldo | K2: SALIDA | L2: TOTAL | M2: INV.I | N2: Entra | O2: Saldo | P2: SALIDA | Q2: TOTAL | R2: INV.I | S2: Entra | T2: Saldo | U2: SALIDA | V2: TOTAL | W2: INV.I | X2: Entra | Y2: Saldo | Z2: SALIDA | AA2: TOTAL | AB2: INV.I | AC2: Entra | AD2: Saldo | AE2: SALIDA | AF2: TOTAL | AG2: INV.I | AH2: Entra | AI2: Saldo | AJ2: SALIDA | AK2: TOTAL | AL2: INV.I | AM2: Entra | AN2: Saldo | AO2: SALIDA | AP2: TOTAL | AQ2: INV.I | AR2: Entra | AS2: Saldo | AT2: SALIDA | AU2: TOTAL | AV2: INV.I | AW2: Entra | AX2: Saldo | AY2: SALIDA | AZ2: TOTAL | BA2: INV.I | BB2: Entra | BC2: Saldo | BD2: SALIDA | BE2: TOTAL | BF2: INV.I | BG2: Entra | BH2: Saldo | BI2: SALIDA | BJ2: TOTAL | BK2: INV.I
A3: PESTAÑINA PROSA | B3: 12000 | AD3: =+AB3+AC3 -> 0 | AE3: =+AD3-AG3 -> -11 | AF3: =((AD3-AE3)*$B3) -> 132000 | AG3: 11 | AH3: 2 | AI3: =+AG3+AH3 -> 13 | AJ3: =+AI3-AL3 -> 9 | AK3: =((AI3-AJ3)*$B3) -> 48000 | AL3: 4 | AM3: 15 | AN3: =+AL3+AM3 -> 19 | AO3: =+AN3-AQ3 -> 2 | AP3: =((AN3-AO3)*$B3) -> 204000 | AQ3: 17 | AS3: =+AQ3+AR3 -> 17 | AT3: =+AS3-AV3 -> 17 | AU3: =((AS3-AT3)*$B3) -> 0 | AX3: =+AV3+AW3 -> 0 | AY3: =+AX3-BA3 -> 0 | AZ3: =((AX3-AY3)*$B3) -> 0 | BC3: =+BA3+BB3 -> 0 | BD3: =+BC3-BF3 -> 0 | BE3: =((BC3-BD3)*$B3) -> 0 | BH3: =+BF3+BG3 -> 0 | BI3: =+BH3-BK3 -> 0 | BJ3: =((BH3-BI3)*$B3) -> 0
A4: ACEITE DE PROSA | B4: 19000 | AD4: =+AB4+AC4 -> 0 | AE4: =+AD4-AG4 -> -4 | AF4: =((AD4-AE4)*$B4) -> 76000 | AG4: 4 | AI4: =+AG4+AH4 -> 4 | AJ4: =+AI4-AL4 -> 1 | AK4: =((AI4-AJ4)*$B4) -> 57000 | AL4: 3 | AN4: =+AL4+AM4 -> 3 | AO4: =+AN4-AQ4 -> 1 | AP4: =((AN4-AO4)*$B4) -> 38000 | AQ4: 2 | AS4: =+AQ4+AR4 -> 2 | AT4: =+AS4-AV4 -> 2
A5: PESTAÑINA PROSA ACG | B5: 11197
A6: ACEITE DE PROSA ACG | B6: 12897 | AD6: =+AB6+AC6 -> 0 | AE6: =+AD6-AG6 -> 0 | AF6: =((AD6-AE6)*$B6) -> 0 | AI6: =+AG6+AH6 -> 0 | AJ6: =+AI6-AL6 -> 0 | AK6: =((AI6-AJ6)*$B6) -> 0 | AN6: =+AL6+AM6 -> 0 | AO6: =+AN6-AQ6 -> 0 | AP6: =((AN6-AO6)*$B6) -> 0 | AS6: =+AQ6+AR6 -> 0 | AT6: =+AS6-AV6 -> 0 | AU6: =((AS6-AT6)*$B6) -> 0 | AX6: =+AV6+AW6 -> 0 | AY6: =+AX6-BA6 -> 0 | AZ6: =((AX6-AY6)*$B6) -> 0 | BC6: =+BA6+BB6 -> 0 | BD6: =+BC6-BF6 -> 0 | BE6: =((BC6-BD6)*$B6) -> 0 | BH6: =+BF6+BG6 -> 0 | BI6: =+BH6-BK6 -> 0 | BJ6: =((BH6-BI6)*$B6) -> 0
G7: =SUM(G3:G6) -> 0 | L7: =SUM(L3:L6) -> 0 | Q7: =SUM(Q3:Q6) -> 0 | V7: =SUM(V3:V6) -> 0 | AA7: =SUM(AA3:AA6) -> 0 | AF7: =SUM(AF3:AF6) -> 208000 | AK7: =SUM(AK3:AK6) -> 105000 | AP7: =+SUM(AP3:AP6) -> 242000 | AU7: =+SUM(AU3:AU6) -> 0 | AZ7: 3037000 | BE7: =+SUM(BE3:BE6) -> 0 | BJ7: =+SUM(BJ3:BJ6) -> 0

Sheet LA
A1: L'amour | C1: ENERO | H1: FEBRERO | M1: MARZO | R1: ABRIL | W1: MAYO | AB1: JUNIO | AG1: JULIO | AL1: AGOSTO | AQ1: SEPTIEMBRE | AV1: OCTUBRE | BA1: NOVIEMBRE | BF1: DICIEMBRE | BK1: ENERO
A2: PRODUCTO | B2: VR. COMPRA | C2: INV.I | D2: Entra | E2: Saldo | F2: SALIDA | G2: TOTAL | H2: INV.I | I2: Entra | J2: Saldo | K2: SALIDA | L2: TOTAL | M2: INV.I | N2: Entra | O2: Saldo | P2: SALIDA | Q2: TOTAL | R2: INV.I | S2: Entra | T2: Saldo | U2: SALIDA | V2: TOTAL | W2: INV.I | X2: Entra | Y2: Saldo | Z2: SALIDA | AA2: TOTAL | AB2: INV.I | AC2: Entra | AD2: Saldo | AE2: SALIDA | AF2: TOTAL | AG2: INV.I | AH2: Entra | AI2: Saldo | AJ2: SALIDA | AK2: TOTAL | AL2: INV.I | AM2: Entra | AN2: Saldo | AO2: SALIDA | AP2: TOTAL | AQ2: INV.I | AR2: Entra | AS2: Saldo | AT2: SALIDA | AU2: TOTAL | AV2: INV.I | AW2: Entra | AX2: Saldo | AY2: SALIDA | AZ2: TOTAL | BA2: INV.I | BB2: Entra | BC2: Saldo | BD2: SALIDA | BE2: TOTAL | BF2: INV.I | BG2: Entra | BH2: Saldo | BI2: SALIDA | BJ2: TOTAL | BK2: INV.I
A3: Ac. Boitina | B3: 30000 | AD3: =+AB3+AC3 -> 0 | AE3: =+AD3-AG3 -> -9 | AF3: =((AD3-AE3)*$B3) -> 270000 | AG3: 9 | AI3: =+AG3+AH3 -> 9 | AJ3: =+AI3-AL3 -> 0 | AK3: =((AI3-AJ3)*$B3) -> 270000 | AL3: 9 | AN3: =+AL3+AM3 -> 9 | AO3: =+AN3-AQ3 -> 0 | AP3: =((AN3-AO3)*$B3) -> 270000 | AQ3: 9 | AS3: =+AQ3+AR3 -> 9 | AT3: =+AS3-AV3 -> 9 | AU3: =((AS3-AT3)*$B3) -> 0 | AX3: =+AV3+AW3 -> 0 | AY3: =+AX3-BA3 -> 0 | AZ3: =((AX3-AY3)*$B3) -> 0 | BC3: =+BA3+BB3 -> 0 | BD3: =+BC3-BF3 -> 0 | BE3: =((BC3-BD3)*$B3) -> 0 | BH3: =+BF3+BG3 -> 0 | BI3: =+BH3-BK3 -> 0 | BJ3: =((BH3-BI3)*$B3) -> 0
A4: Agua Micelar | B4: 25500 | AD4: =+AB4+AC4 -> 0 | AE4: =+AD4-AG4 -> -2 | AF4: =((AD4-AE4)*$B4) -> 51000 | AG4: 2 | AI4: =+AG4+AH4 -> 2 | AJ4: =+AI4-AL4 -> 0 | AK4: =((AI4-AJ4)*$B4) -> 51000 | AL4: 2 | AN4: =+AL4+AM4 -> 2 | AO4: =+AN4-AQ4 -> 0 | AP4: =((AN4-AO4)*$B4) -> 51000 | AQ4: 2 | AS4: =+AQ4+AR4 -> 2 | AT4: =+AS4-AV4 -> 2 | AU4: =((AS4-AT4)*$B4) -> 0 | AX4: =+AV4+AW4 -> 0 | AY4: =+AX4-BA4 -> 0 | AZ4: =((AX4-AY4)*$B4) -> 0 | BC4: =+BA4+BB4 -> 0 | BD4: =+BC4-BF4 -> 0 | BE4: =((BC4-BD4)*$B4) -> 0 | BH4: =+BF4+BG4 -> 0 | BI4: =+BH4-BK4 -> 0 | BJ4: =((BH4-BI4)*$B4) -> 0
G5: =SUM(G3:G4) -> 0 | L5: =SUM(L3:L4) -> 0 | Q5: =SUM(Q3:Q4) -> 0 | V5: =SUM(V3:V4) -> 0 | AA5: =SUM(AA3:AA4) -> 0 | AF5: =SUM(AF3:AF4) -> 321000 | AK5: =+SUM(AK3:AK4) -> 321000 | AP5: =+SUM(AP3:AP4) -> 321000 | AU5: =+SUM(AU3:AU4) -> 0 | AZ5: =+SUM(AZ3:AZ4) -> 0 | BE5: =+SUM(BE3:BE4) -> 0 | BJ5: =+SUM(BJ3:BJ4) -> 0

Sheet OTROS
A1: OTROS | C1: ENERO | H1: FEBRERO | M1: MARZO | R1: ABRIL | W1: MAYO | AB1: JUNIO | AG1: JULIO | AL1: AGOSTO | AQ1: SEPTIEMBRE | AV1: OCTUBRE | BA1: NOVIEMBRE | BF1: DICIEMBRE | BK1: ENERO
A2: PRODUCTO | B2: VR. COMPRA | C2: INV.I | D2: Entra | E2: Saldo | F2: SALIDA | G2: TOTAL | H2: INV.I | I2: Entra | J2: Saldo | K2: SALIDA | L2: TOTAL | M2: INV.I | N2: Entra | O2: Saldo | P2: SALIDA | Q2: TOTAL | R2: INV.I | S2: Entra | T2: Saldo | U2: SALIDA | V2: TOTAL | W2: INV.I | X2: Entra | Y2: Saldo | Z2: SALIDA | AA2: TOTAL | AB2: INV.I | AC2: Entra | AD2: Saldo | AE2: SALIDA | AF2: TOTAL | AG2: INV.I | AH2: Entra | AI2: Saldo | AJ2: SALIDA | AK2: TOTAL | AL2: INV.I | AM2: Entra | AN2: Saldo | AO2: SALIDA | AP2: TOTAL | AQ2: INV.I | AR2: Entra | AS2: Saldo | AT2: SALIDA | AU2: TOTAL | AV2: INV.I | AW2: Entra | AX2: Saldo | AY2: SALIDA | AZ2: TOTAL | BA2: INV.I | BB2: Entra | BC2: Saldo | BD2: SALIDA | BE2: TOTAL | BF2: INV.I | BG2: Entra | BH2: Saldo | BI2: SALIDA | BJ2: TOTAL | BK2: INV.I
A3: SERUN HIDRATENTE PESTAÑAS | B3: 11000 | AD3: =+AB3+AC3 -> 0 | AE3: =+AD3-AG3 -> -8 | AF3: =((AD3-AE3)*$B3) -> 88000 | AG3: 8 | AI3: =+AG3+AH3 -> 8 | AJ3: =+AI3-AL3 -> 0 | AK3: =((AI3-AJ3)*$B3) -> 88000 | AL3: 8 | AN3: =+AL3+AM3 -> 8 | AO3: =+AN3-AQ3 -> 2 | AP3: =((AN3-AO3)*$B3) -> 66000 | AQ3: 6 | AS3: =+AQ3+AR3 -> 6 | AT3: =+AS3-AV3 -> 6 | AU3: =((AS3-AT3)*$B3) -> 0 | AX3: =+AV3+AW3 -> 0 | AY3: =+AX3-BA3 -> 0 | AZ3: =((AX3-AY3)*$B3) -> 0 | BC3: =+BA3+BB3 -> 0 | BD3: =+BC3-BF3 -> 0 | BE3: =((BC3-BD3)*$B3) -> 0 | BH3: =+BF3+BG3 -> 0 | BI3: =+BH3-BK3 -> 0 | BJ3: =((BH3-BI3)*$B3) -> 0
A4: BAÑO DE ORO COCO LINDO | B4: 10800 | AD4: =+AB4+AC4 -> 0 | AE4: =+AD4-AG4 -> -3 | AF4: =((AD4-AE4)*$B4) -> 32400 | AG4: 3 | AI4: =+AG4+AH4 -> 3 | AJ4: =+AI4-AL4 -> 0 | AK4: =((AI4-AJ4)*$B4) -> 32400 | AL4: 3 | AN4: =+AL4+AM4 -> 3 | AO4: =+AN4-AQ4 -> 0 | AP4: =((AN4-AO4)*$B4) -> 32400 | AQ4: 3 | AS4: =+AQ4+AR4 -> 3 | AT4: =+AS4-AV4 -> 3 | AU4: =((AS4-AT4)*$B4) -> 0 | AX4: =+AV4+AW4 -> 0 | AY4: =+AX4-BA4 -> 0 | AZ4: =((AX4-AY4)*$B4) -> 0 | BC4: =+BA4+BB4 -> 0 | BD4: =+BC4-BF4 -> 0 | BE4: =((BC4-BD4)*$B4) -> 0 | BH4: =+BF4+BG4 -> 0 | BI4: =+BH4-BK4 -> 0 | BJ4: =((BH4-BI4)*$B4) -> 0
A5: FEM | B5: 85000 | AD5: =+AB5+AC5 -> 0 | AE5: =+AD5-AG5 -> -4 | AF5: =((AD5-AE5)*$B5) -> 340000 | AG5: 4 | AI5: =+AG5+AH5 -> 4 | AJ5: =+AI5-AL5 -> 2 | AK5: =((AI5-AJ5)*$B5) -> 170000 | AL5: 2 | AN5: =+AL5+AM5 -> 2 | AO5: =+AN5-AQ5 -> 0 | AP5: =((AN5-AO5)*$B5) -> 170000 | AQ5: 2 | AS5: =+AQ5+AR5 -> 2 | AT5: =+AS5-AV5 -> 2 | AU5: =((AS5-AT5)*$B5) -> 0 | AX5: =+AV5+AW5 -> 0 | AY5: =+AX5-BA5 -> 0 | AZ5: =((AX5-AY5)*$B5) -> 0 | BC5: =+BA5+BB5 -> 0 | BD5: =+BC5-BF5 -> 0 | BE5: =((BC5-BD5)*$B5) -> 0 | BH5: =+BF5+BG5 -> 0 | BI5: =+BH5-BK5 -> 0 | BJ5: =((BH5-BI5)*$B5) -> 0
A6: CLASS GOLD BLOQUEADOR CON Y SIN COLOR | B6: 51000 | AD6: =+AB6+AC6 -> 0 | AE6: =+AD6-AG6 -> -1 | AF6: =((AD6-AE6)*$B6) -> 51000 | AG6: 1 | AI6: =+AG6+AH6 -> 1 | AJ6: =+AI6-AL6 -> 0 | AK6: =((AI6-AJ6)*$B6) -> 51000 | AL6: 1 | AN6: =+AL6+AM6 -> 1 | AO6: =+AN6-AQ6 -> 0 | AP6: =((AN6-AO6)*$B6) -> 51000 | AQ6: 1 | AS6: =+AQ6+AR6 -> 1 | AT6: =+AS6-AV6 -> 1 | AU6: =((AS6-AT6)*$B6) -> 0 | AX6: =+AV6+AW6 -> 0 | AY6: =+AX6-BA6 -> 0 | AZ6: =((AX6-AY6)*$B6) -> 0 | BC6: =+BA6+BB6 -> 0 | BD6: =+BC6-BF6 -> 0 | BE6: =((BC6-BD6)*$B6) -> 0 | BH6: =+BF6+BG6 -> 0 | BI6: =+BH6-BK6 -> 0 | BJ6: =((BH6-BI6)*$B6) -> 0
A7: YASUM FIBRA | B7: 33000 | AD7: =+AB7+AC7 -> 0 | AE7: =+AD7-AG7 -> -9 | AF7: =((AD7-AE7)*$B7) -> 297000 | AG7: 9 | AI7: =+AG7+AH7 -> 9 | AJ7: =+AI7-AL7 -> 2 | AK7: =((AI7-AJ7)*$B7) -> 231000 | AL7: 7 | AN7: =+AL7+AM7 -> 7 | AO7: =+AN7-AQ7 -> 0 | AP7: =((AN7-AO7)*$B7) -> 231000 | AQ7: 7 | AS7: =+AQ7+AR7 -> 7 | AT7: =+AS7-AV7 -> 7 | AU7: =((AS7-AT7)*$B7) -> 0
A8: YASUM COLAGENO | B8: 50000 | AD8: =+AB8+AC8 -> 0 | AE8: =+AD8-AG8 -> -1 | AF8: =((AD8-AE8)*$B8) -> 50000 | AG8: 1 | AI8: =+AG8+AH8 -> 1 | AJ8: =+AI8-AL8 -> 1 | AK8: =((AI8-AJ8)*$B8) -> 0 | AL8: 0 | AN8: =+AL8+AM8 -> 0 | AO8: =+AN8-AQ8 -> 0 | AP8: =((AN8-AO8)*$B8) -> 0 | AQ8: 0 | AS8: =+AQ8+AR8 -> 0 | AT8: =+AS8-AV8 -> 0 | AU8: =((AS8-AT8)*$B8) -> 0
A9: SET CHARMS HELLO KITTY | B9: 12900 | AD9: =+AB9+AC9 -> 0 | AE9: =+AD9-AG9 -> 0 | AF9: =((AD9-AE9)*$B9) -> 0 | AI9: =+AG9+AH9 -> 0 | AJ9: =+AI9-AL9 -> 0 | AK9: =((AI9-AJ9)*$B9) -> 0 | AL9: 0 | AM9: 2 | AN9: =+AL9+AM9 -> 2 | AO9: =+AN9-AQ9 -> 0 | AP9: =((AN9-AO9)*$B9) -> 25800 | AQ9: 2 | AS9: =+AQ9+AR9 -> 2 | AT9: =+AS9-AV9 -> 2 | AU9: =((AS9-AT9)*$B9) -> 0
A10: ESPEJO HELLO KITTY | B10: 9600 | AD10: =+AB10+AC10 -> 0 | AE10: =+AD10-AG10 -> 0 | AF10: =((AD10-AE10)*$B10) -> 0 | AI10: =+AG10+AH10 -> 0 | AJ10: =+AI10-AL10 -> 0 | AK10: =((AI10-AJ10)*$B10) -> 0 | AL10: 0 | AM10: 4 | AN10: =+AL10+AM10 -> 4 | AO10: =+AN10-AQ10 -> 2 | AP10: =((AN10-AO10)*$B10) -> 19200 | AQ10: 2 | AS10: =+AQ10+AR10 -> 2 | AT10: =+AS10-AV10 -> 2 | AU10: =((AS10-AT10)*$B10) -> 0
